Workbook

Sheet Tubex_Dashboard
B2: TUBEX — July 2026 Month to Date Report
B3: Report Date (Yesterday's Production): | H3: =TODAY()-1 -> 46209
B5: TUBE — YESTERDAY | D5: TUBE — MTD | G5: TUBE — REJECT % | J5: Dispatch — MTD | M5: Press & Printing Downtime — MTD
B6: =SUMPRODUCT((Production_Log!$A$3:$A$8963=MAX(Production_Log!$A$3:$A$8963))*(LEFT(Production_Log!$B$3:$B$8963,5)="Print")*(ISERROR(SEARCH("(Varnish)",Production_Log!$D$3:$D$8963)))*Production_Log!$H$3:$H$8963) -> 21724 | D6: =SUMIF($B$11:$B$64,"TUBE",$H$11:$H$64) -> 83072 | G6: {=IFERROR(SUMPRODUCT((Production_Log!$F$3:$F$8963<>0)*(LEFT(Production_Log!$B$3:$B$8963,5)="Print")*(ISERROR(SEARCH("(Varnish)",Production_Log!$D$3:$D$8963)))*Production_Log!$I$3:$I$8963)/SUMPRODUCT((Production_Log!$F$3:$F$8963<>0)*(LEFT(Production_Log!$B$3:$B$8963,5)="Print")*(ISERROR(SEARCH("(Varnish)",Production_Log!$D$3:$D$8963)))*(Production_Log!$H$3:$H$8963+Production_Log!$I$3:$I$8963)),"-")} -> 0.022820308 | J6: =SUMIF($B$11:$B$64,"TUBE",$K$11:$K$64) -> 76160 | M6: Category | N6: Hours (MTD) | O6: % Share
B7: PET — YESTERDAY | D7: PET — MTD | G7: PET — REJECT % | J7: Dispatch — MTD | M7: =IFERROR(INDEX($S$9:$S$21,MATCH(LARGE($U$9:$U$21,1),$U$9:$U$21,0)),"") -> Operations | N7: =(IFERROR(INDEX($T$9:$T$21,MATCH(LARGE($U$9:$U$21,1),$U$9:$U$21,0)),""))/60 -> 14 | O7: =IFERROR(N7/$N$14,"") -> 0.42424242
B8: =SUMPRODUCT((Production_Log!$A$3:$A$8963=MAX(Production_Log!$A$3:$A$8963))*(Production_Log!$B$3:$B$8963="PF Machine")*Production_Log!$H$3:$H$8963) -> 5400 | D8: 5400 | G8: {=IFERROR(SUMPRODUCT((Production_Log!$B$3:$B$8963="PF Machine")*Production_Log!$I$3:$I$8963)/SUMPRODUCT((Production_Log!$B$3:$B$8963="PF Machine")*(Production_Log!$H$3:$H$8963+Production_Log!$I$3:$I$8963)),0)} -> 0.12903226 | J8: =SUMIF($B$11:$B$64,"PET",$K$11:$K$64) -> 13800 | M8: =IFERROR(INDEX($S$9:$S$21,MATCH(LARGE($U$9:$U$21,2),$U$9:$U$21,0)),"") -> Power Shutdown | N8: =IFERROR(INDEX($T$9:$T$21,MATCH(LARGE($U$9:$U$21,2),$U$9:$U$21,0)),"")/60 -> 11 | O8: =IFERROR(N8/$N$14,"") -> 0.33333333
B9: Summary of Production & Dispatch - MTD | M9: =IFERROR(INDEX($S$9:$S$21,MATCH(LARGE($U$9:$U$21,3),$U$9:$U$21,0)),"") -> Mechanical | N9: =IFERROR(INDEX($T$9:$T$21,MATCH(LARGE($U$9:$U$21,3),$U$9:$U$21,0)),"")/60 -> 8 | O9: =IFERROR(N9/$N$14,"") -> 0.24242424 | S9: Mechanical | T9: =SUMPRODUCT(((LEFT(Production_Log!$B$3:$B$8963,5)="Press")+(LEFT(Production_Log!$B$3:$B$8963,5)="Print"))*Production_Log!$K$3:$K$8963) -> 480 | U9: =T9+0.00001 -> 480.00001
B10: Type | C10: Customer | D10: Product Name | E10: Dia | F10: Prod ID | G10: Orders | H10: MTD Produced | I10: Remaining | J10: Compliance | K10: Dispatch | L10: Remarks | M10: =IFERROR(INDEX($S$9:$S$21,MATCH(LARGE($U$9:$U$21,4),$U$9:$U$21,0)),"") -> Workers Shortage | N10: =IFERROR(INDEX($T$9:$T$21,MATCH(LARGE($U$9:$U$21,4),$U$9:$U$21,0)),"")/60 -> 0 | O10: =IFERROR(N10/$N$14,"") -> 0 | S10: Electrical | T10: =SUMPRODUCT(((LEFT(Production_Log!$B$3:$B$8963,5)="Press")+(LEFT(Production_Log!$B$3:$B$8963,5)="Print"))*Production_Log!$L$3:$L$8963) -> 0 | U10: =T10+0.00002 -> 2e-05
B11: TUBE | C11: Brookes Pharma Private Limited | D11: ECZEMUS OINTMENT 0.03% 10G | E11: 16 | F11: 6561 | G11: =IFERROR(INDEX(MRP!$F$3:$F$8,MATCH(Tubex_Dashboard!F11,MRP!$D$3:$D$8,0)),0) -> 25000 | H11: =SUMPRODUCT((Production_Log!$F$3:$F$8963=F11)*(LEFT(Production_Log!$B$3:$B$8963,5)="Print")*(ISERROR(SEARCH("(Varnish)",Production_Log!$D$3:$D$8963)))*Production_Log!$H$3:$H$8963) -> 0 | I11: =G11-H11 -> 25000 | J11: =IF(G11=0,"-",H11/G11) -> 0 | L11: Hold (Caps Not Approved) | M11: =IFERROR(INDEX($S$9:$S$21,MATCH(LARGE($U$9:$U$21,5),$U$9:$U$21,0)),"") -> Gas Shutdown | N11: =IFERROR(INDEX($T$9:$T$21,MATCH(LARGE($U$9:$U$21,5),$U$9:$U$21,0)),"")/60 -> 0 | O11: =IFERROR(N11/$N$14,"") -> 0
B12: TUBE | C12: Samsol International Private Limited | D12: S 43 25MM | E12: 25 | F12: 3447 | G12: =IFERROR(INDEX(MRP!$F$3:$F$8,MATCH(Tubex_Dashboard!F12,MRP!$D$3:$D$8,0)),0) -> 78976 | H12: =SUMPRODUCT((Production_Log!$F$3:$F$8963=F12)*(LEFT(Production_Log!$B$3:$B$8963,5)="Print")*(ISERROR(SEARCH("(Varnish)",Production_Log!$D$3:$D$8963)))*Production_Log!$H$3:$H$8963) -> 10416 | I12: =G12-H12 -> 68560 | J12: =IF(G12=0,"-",H12/G12) -> 0.13188817 | L12: 100k Extra Planned | M12: =IFERROR(INDEX($S$9:$S$21,MATCH(LARGE($U$9:$U$21,6),$U$9:$U$21,0)),"") -> Changeover | N12: =IFERROR(INDEX($T$9:$T$21,MATCH(LARGE($U$9:$U$21,6),$U$9:$U$21,0)),"")/60 -> 0 | O12: =IFERROR(N12/$N$14,"") -> 0 | S12: Material Shortage | T12: =SUMPRODUCT(((LEFT(Production_Log!$B$3:$B$8963,5)="Press")+(LEFT(Production_Log!$B$3:$B$8963,5)="Print"))*Production_Log!$M$3:$M$8963) -> 0 | U12: =T12+0.00003 -> 3e-05
B13: TUBE | C13: Samsol International Private Limited | D13: S-45 | E13: 25 | F13: 5389 | G13: =IFERROR(INDEX(MRP!$F$3:$F$8,MATCH(Tubex_Dashboard!F13,MRP!$D$3:$D$8,0)),0) -> 100000 | H13: =SUMPRODUCT((Production_Log!$F$3:$F$8963=F13)*(LEFT(Production_Log!$B$3:$B$8963,5)="Print")*(ISERROR(SEARCH("(Varnish)",Production_Log!$D$3:$D$8963)))*Production_Log!$H$3:$H$8963) -> 0 | I13: =G13-H13 -> 100000 | J13: =IF(G13=0,"-",H13/G13) -> 0 | L13: 100k Extra Planned | M13: =IFERROR(INDEX($S$9:$S$21,MATCH(LARGE($U$9:$U$21,7),$U$9:$U$21,0)),"") -> Material Shortage | N13: =IFERROR(INDEX($T$9:$T$21,MATCH(LARGE($U$9:$U$21,7),$U$9:$U$21,0)),"")/60 -> 0 | O13: =IFERROR(N13/$N$14,"") -> 0 | S13: Changeover | T13: =SUMPRODUCT(((LEFT(Production_Log!$B$3:$B$8963,5)="Press")+(LEFT(Production_Log!$B$3:$B$8963,5)="Print"))*Production_Log!$N$3:$N$8963) -> 0 | U13: =T13+0.00004 -> 4e-05
B14: TUBE | C14: Golden Pearl Cosmetics (PVT) LTD | D14: HELLO HAIR COLOR | E14: 30 | F14: 6206 | G14: =IFERROR(INDEX(MRP!$F$3:$F$8,MATCH(Tubex_Dashboard!F14,MRP!$D$3:$D$8,0)),0) -> 174138 | H14: =SUMPRODUCT((Production_Log!$F$3:$F$8963=F14)*(LEFT(Production_Log!$B$3:$B$8963,5)="Print")*(ISERROR(SEARCH("(Varnish)",Production_Log!$D$3:$D$8963)))*Production_Log!$H$3:$H$8963) -> 72656 | I14: =G14-H14 -> 101482 | J14: =IF(G14=0,"-",H14/G14) -> 0.41723231 | K14: 76160 | M14: TOTAL | N14: =SUM($T$9:$T$21)/60 -> 33 | O14: 100% | S14: Operations | T14: =SUMPRODUCT(((LEFT(Production_Log!$B$3:$B$8963,5)="Press")+(LEFT(Production_Log!$B$3:$B$8963,5)="Print"))*Production_Log!$O$3:$O$8963) -> 840 | U14: =T14+0.00005 -> 840.00005
B15: TUBE | C15: Mablay Beauty PVT LTD. | D15: VINCE NURTURAL | E15: 30 | F15: 5814 | G15: =IFERROR(INDEX(MRP!$F$3:$F$8,MATCH(Tubex_Dashboard!F15,MRP!$D$3:$D$8,0)),0) -> 30000 | H15: =SUMPRODUCT((Production_Log!$F$3:$F$8963=F15)*(LEFT(Production_Log!$B$3:$B$8963,5)="Print")*(ISERROR(SEARCH("(Varnish)",Production_Log!$D$3:$D$8963)))*Production_Log!$H$3:$H$8963) -> 0 | I15: =G15-H15 -> 30000 | J15: =IF(G15=0,"-",H15/G15) -> 0
B16: TUBE | C16: Adore | D16: V- HC BROWN | E16: 35 | F16: 6530 | G16: =IFERROR(INDEX(MRP!$F$3:$F$8,MATCH(Tubex_Dashboard!F16,MRP!$D$3:$D$8,0)),0) -> 13300 | H16: =SUMPRODUCT((Production_Log!$F$3:$F$8963=F16)*(LEFT(Production_Log!$B$3:$B$8963,5)="Print")*(ISERROR(SEARCH("(Varnish)",Production_Log!$D$3:$D$8963)))*Production_Log!$H$3:$H$8963) -> 0 | I16: =G16-H16 -> 13300 | J16: =IF(G16=0,"-",H16/G16) -> 0 | L16: Hold | S16: Power Shutdown | T16: =SUMPRODUCT(((LEFT(Production_Log!$B$3:$B$8963,5)="Press")+(LEFT(Production_Log!$B$3:$B$8963,5)="Print"))*Production_Log!$P$3:$P$8963) -> 660 | U16: =T16+0.00006 -> 660.00006
D17: TOTAL | G17: =SUM(G11:G16) -> 421414 | H17: =SUM(H11:H16) -> 83072 | I17: =SUMIF(I11:I16,">"&0) -> 338342 | K17: =SUM(K11:K16) -> 76160
B18: PET | C18: Samsol International Private Limited | D18: PET BOTTLE SMALL (120ML) YELLOW | E18: 120 ml | F18: 8005 | G18: 19840 | H18: =SUMPRODUCT((Production_Log!$F$3:$F$8963=F18)*Production_Log!$H$3:$H$8963) -> 0 | I18: =G18-H18 -> 19840 | J18: =IF(G18=0,"-",H18/G18) -> 0 | S18: Gas Shutdown | T18: =SUMPRODUCT(((LEFT(Production_Log!$B$3:$B$8963,5)="Press")+(LEFT(Production_Log!$B$3:$B$8963,5)="Print"))*Production_Log!$Q$3:$Q$8963) -> 0 | U18: =T18+0.00007 -> 7e-05
B19: PET | C19: Mablay Beauty PVT LTD. | D19: PET BOTTLE 130ML WHITE | E19: 130 ml | F19: 8015 | G19: 15000 | H19: =SUMPRODUCT((Production_Log!$F$3:$F$8963=F19)*Production_Log!$H$3:$H$8963) -> 0 | I19: =G19-H19 -> 15000 | J19: =IF(G19=0,"-",H19/G19) -> 0 | S19: Workers Shortage | T19: =SUMPRODUCT(((LEFT(Production_Log!$B$3:$B$8963,5)="Press")+(LEFT(Production_Log!$B$3:$B$8963,5)="Print"))*Production_Log!$R$3:$R$8963) -> 0 | U19: =T19+0.00008 -> 8e-05
B20: PET | C20: Alpha Labs PVT LTD | D20: TRANSPARENT BOTTLE 150ML | E20: 150 ml | F20: 8001 | G20: 153167 | H20: =SUMPRODUCT((Production_Log!$F$3:$F$8963=F20)*Production_Log!$H$3:$H$8963) -> 0 | I20: =G20-H20 -> 153167 | J20: =IF(G20=0,"-",H20/G20) -> 0 | K20: 13800
B21: PET | C21: Samsol International Private Limited | D21: PET BOTTLE LARGE 200ML WHITE | E21: 200 ml | F21: 8007 | G21: 10000 | H21: =SUMPRODUCT((Production_Log!$F$3:$F$8963=F21)*Production_Log!$H$3:$H$8963) -> 0 | I21: =G21-H21 -> 10000 | J21: =IF(G21=0,"-",H21/G21) -> 0
B22: PET | C22: Samsol International Private Limited | D22: PET BOTTLE LARGE (200 ML) YELLOW | E22: 200 ml | F22: 8006 | G22: 42400 | H22: =SUMPRODUCT((Production_Log!$F$3:$F$8963=F22)*Production_Log!$H$3:$H$8963) -> 0 | I22: =G22-H22 -> 42400 | J22: =IF(G22=0,"-",H22/G22) -> 0
B23: PET | C23: Samsol International Private Limited | D23: BT-200ML MUSTARD OIL (TRANSPARENT) | E23: 200 ml | F23: 8014 | G23: 10000 | H23: =SUMPRODUCT((Production_Log!$F$3:$F$8963=F23)*Production_Log!$H$3:$H$8963) -> 0 | I23: =G23-H23 -> 10000 | J23: =IF(G23=0,"-",H23/G23) -> 0
D24: TOTAL | G24: =SUM(G18:G23) -> 250407 | H24: =SUM(H18:H23) -> 0 | I24: =SUMIF(I18:I23,">"&0) -> 250407 | K24: =SUM(K18:K23) -> 13800
B25: TUBE | C25: Bahadur | D25: BAHADUR TUBE 12.5MM | E25: 12.5 | F25: 9004 | G25: =IFERROR(INDEX(MRP!$F$3:$F$8,MATCH(Tubex_Dashboard!F25,MRP!$D$3:$D$8,0)),0) -> 0 | H25: =SUMPRODUCT((Production_Log!$F$3:$F$8963=F25)*(LEFT(Production_Log!$B$3:$B$8963,5)="Print")*(ISERROR(SEARCH("(Varnish)",Production_Log!$D$3:$D$8963)))*Production_Log!$H$3:$H$8963) -> 0 | I25: =G25-H25 -> 0 | J25: =IF(G25=0,"-",H25/G25) -> -
B26: TUBE | C26: Samsol International Private Limited | D26: S-45 DIA 19MM | E26: 19 | F26: 6624 | G26: =IFERROR(INDEX(MRP!$F$3:$F$8,MATCH(Tubex_Dashboard!F26,MRP!$D$3:$D$8,0)),0) -> 0 | H26: =SUMPRODUCT((Production_Log!$F$3:$F$8963=F26)*(LEFT(Production_Log!$B$3:$B$8963,5)="Print")*(ISERROR(SEARCH("(Varnish)",Production_Log!$D$3:$D$8963)))*Production_Log!$H$3:$H$8963) -> 0 | I26: =G26-H26 -> 0 | J26: =IF(G26=0,"-",H26/G26) -> -
B27: TUBE | C27: Samsol International Private Limited | D27: S-43 DIA 19MM | E27: 19 | F27: 6623 | G27: =IFERROR(INDEX(MRP!$F$3:$F$8,MATCH(Tubex_Dashboard!F27,MRP!$D$3:$D$8,0)),0) -> 0 | H27: =SUMPRODUCT((Production_Log!$F$3:$F$8963=F27)*(LEFT(Production_Log!$B$3:$B$8963,5)="Print")*(ISERROR(SEARCH("(Varnish)",Production_Log!$D$3:$D$8963)))*Production_Log!$H$3:$H$8963) -> 0 | I27: =G27-H27 -> 0 | J27: =IF(G27=0,"-",H27/G27) -> -
B28: TUBE | C28: Brookes Pharma Private Limited | D28: PHLOGIN GEL 20G | E28: 19 | F28: 6559 | G28: =IFERROR(INDEX(MRP!$F$3:$F$8,MATCH(Tubex_Dashboard!F28,MRP!$D$3:$D$8,0)),0) -> 0 | H28: =SUMPRODUCT((Production_Log!$F$3:$F$8963=F28)*(LEFT(Production_Log!$B$3:$B$8963,5)="Print")*(ISERROR(SEARCH("(Varnish)",Production_Log!$D$3:$D$8963)))*Production_Log!$H$3:$H$8963) -> 0 | I28: =G28-H28 -> 0 | J28: =IF(G28=0,"-",H28/G28) -> -
B29: TUBE | C29: Brookes Pharma Private Limited | D29: PYODINE GEL 20GM | E29: 19 | F29: 1085 | G29: =IFERROR(INDEX(MRP!$F$3:$F$8,MATCH(Tubex_Dashboard!F29,MRP!$D$3:$D$8,0)),0) -> 0 | H29: =SUMPRODUCT((Production_Log!$F$3:$F$8963=F29)*(LEFT(Production_Log!$B$3:$B$8963,5)="Print")*(ISERROR(SEARCH("(Varnish)",Production_Log!$D$3:$D$8963)))*Production_Log!$H$3:$H$8963) -> 0 | I29: =G29-H29 -> 0 | J29: =IF(G29=0,"-",H29/G29) -> -
B30: TUBE | C30: Brookes Pharma Private Limited | D30: CONTRATUBEX GEL 20G | E30: 19 | F30: 6560 | G30: =IFERROR(INDEX(MRP!$F$3:$F$8,MATCH(Tubex_Dashboard!F30,MRP!$D$3:$D$8,0)),0) -> 0 | H30: =SUMPRODUCT((Production_Log!$F$3:$F$8963=F30)*(LEFT(Production_Log!$B$3:$B$8963,5)="Print")*(ISERROR(SEARCH("(Varnish)",Production_Log!$D$3:$D$8963)))*Production_Log!$H$3:$H$8963) -> 0 | I30: =G30-H30 -> 0 | J30: =IF(G30=0,"-",H30/G30) -> -
B31: TUBE | C31: Samsol International Private Limited | D31: S-43 DIA 20.5 | E31: 20.5 | F31: 5699 | G31: =IFERROR(INDEX(MRP!$F$3:$F$8,MATCH(Tubex_Dashboard!F31,MRP!$D$3:$D$8,0)),0) -> 0 | H31: =SUMPRODUCT((Production_Log!$F$3:$F$8963=F31)*(LEFT(Production_Log!$B$3:$B$8963,5)="Print")*(ISERROR(SEARCH("(Varnish)",Production_Log!$D$3:$D$8963)))*Production_Log!$H$3:$H$8963) -> 0 | I31: =G31-H31 -> 0 | J31: =IF(G31=0,"-",H31/G31) -> -
B32: TUBE | C32: Mablay Beauty PVT LTD. | D32: VINCE HIS ONLY BEARD & MUSTACHE COLOR CREAM | E32: 20.5 | F32: 6077 | G32: =IFERROR(INDEX(MRP!$F$3:$F$8,MATCH(Tubex_Dashboard!F32,MRP!$D$3:$D$8,0)),0) -> 0 | H32: =SUMPRODUCT((Production_Log!$F$3:$F$8963=F32)*(LEFT(Production_Log!$B$3:$B$8963,5)="Print")*(ISERROR(SEARCH("(Varnish)",Production_Log!$D$3:$D$8963)))*Production_Log!$H$3:$H$8963) -> 0 | I32: =G32-H32 -> 0 | J32: =IF(G32=0,"-",H32/G32) -> -
B33: TUBE | C33: Samsol International Private Limited | D33: S-45 DIA 20.5 | E33: 20.5 | F33: 5698 | G33: =IFERROR(INDEX(MRP!$F$3:$F$8,MATCH(Tubex_Dashboard!F33,MRP!$D$3:$D$8,0)),0) -> 0 | H33: =SUMPRODUCT((Production_Log!$F$3:$F$8963=F33)*(LEFT(Production_Log!$B$3:$B$8963,5)="Print")*(ISERROR(SEARCH("(Varnish)",Production_Log!$D$3:$D$8963)))*Production_Log!$H$3:$H$8963) -> 0 | I33: =G33-H33 -> 0 | J33: =IF(G33=0,"-",H33/G33) -> - | S33: Gas Shutdown | T33: =SUMPRODUCT((MONTH(Production_Log!$A$3:$A$8963)=MONTH(TODAY()))*(YEAR(Production_Log!$A$3:$A$8963)=YEAR(TODAY()))*Production_Log!$Q$3:$Q$8963) -> 0 | U33: =T34+0.00006 -> 6e-05
B34: TUBE | C34: Samsol International Private Limited | D34: SAMSOL HAIR COLOR 45 DIA 20.5 MM | E34: 20.5 | F34: 5731 | G34: =IFERROR(INDEX(MRP!$F$3:$F$8,MATCH(Tubex_Dashboard!F34,MRP!$D$3:$D$8,0)),0) -> 0 | H34: =SUMPRODUCT((Production_Log!$F$3:$F$8963=F34)*(LEFT(Production_Log!$B$3:$B$8963,5)="Print")*(ISERROR(SEARCH("(Varnish)",Production_Log!$D$3:$D$8963)))*Production_Log!$H$3:$H$8963) -> 0 | I34: =G34-H34 -> 0 | J34: =IF(G34=0,"-",H34/G34) -> -
B35: TUBE | C35: Samsol International Private Limited | D35: SAMSOL HAIR COLOR 43 DIA 20.5 MM | E35: 20.5 | F35: 5732 | G35: =IFERROR(INDEX(MRP!$F$3:$F$8,MATCH(Tubex_Dashboard!F35,MRP!$D$3:$D$8,0)),0) -> 0 | H35: =SUMPRODUCT((Production_Log!$F$3:$F$8963=F35)*(LEFT(Production_Log!$B$3:$B$8963,5)="Print")*(ISERROR(SEARCH("(Varnish)",Production_Log!$D$3:$D$8963)))*Production_Log!$H$3:$H$8963) -> 0 | I35: =G35-H35 -> 0 | J35: =IF(G35=0,"-",H35/G35) -> -
B36: TUBE | C36: Samsol International Private Limited | D36: SAMSOL HAIR COLOR 39 SMALL PURPLE | E36: 20.5 | F36: 6556 | G36: =IFERROR(INDEX(MRP!$F$3:$F$8,MATCH(Tubex_Dashboard!F36,MRP!$D$3:$D$8,0)),0) -> 0 | H36: =SUMPRODUCT((Production_Log!$F$3:$F$8963=F36)*(LEFT(Production_Log!$B$3:$B$8963,5)="Print")*(ISERROR(SEARCH("(Varnish)",Production_Log!$D$3:$D$8963)))*Production_Log!$H$3:$H$8963) -> 0 | I36: =G36-H36 -> 0 | J36: =IF(G36=0,"-",H36/G36) -> -
B37: TUBE | C37: Samsol International Private Limited | D37: SAMSOL HAIR COLOR 41 SMALL PURPLE | E37: 20.5 | F37: 6557 | G37: =IFERROR(INDEX(MRP!$F$3:$F$8,MATCH(Tubex_Dashboard!F37,MRP!$D$3:$D$8,0)),0) -> 0 | H37: =SUMPRODUCT((Production_Log!$F$3:$F$8963=F37)*(LEFT(Production_Log!$B$3:$B$8963,5)="Print")*(ISERROR(SEARCH("(Varnish)",Production_Log!$D$3:$D$8963)))*Production_Log!$H$3:$H$8963) -> 0 | I37: =G37-H37 -> 0 | J37: =IF(G37=0,"-",H37/G37) -> -
B38: TUBE | C38: Samsol International Private Limited | D38: TUBES COMMON RED | E38: 25 | F38: 6470 | G38: =IFERROR(INDEX(MRP!$F$3:$F$8,MATCH(Tubex_Dashboard!F38,MRP!$D$3:$D$8,0)),0) -> 0 | H38: =SUMPRODUCT((Production_Log!$F$3:$F$8963=F38)*(LEFT(Production_Log!$B$3:$B$8963,5)="Print")*(ISERROR(SEARCH("(Varnish)",Production_Log!$D$3:$D$8963)))*Production_Log!$H$3:$H$8963) -> 0 | I38: =G38-H38 -> 0 | J38: =IF(G38=0,"-",H38/G38) -> -
B39: TUBE | C39: Samsol International Private Limited | D39: TUBE COMMON PURPLE | E39: 25 | F39: 6532 | G39: =IFERROR(INDEX(MRP!$F$3:$F$8,MATCH(Tubex_Dashboard!F39,MRP!$D$3:$D$8,0)),0) -> 0 | H39: =SUMPRODUCT((Production_Log!$F$3:$F$8963=F39)*(LEFT(Production_Log!$B$3:$B$8963,5)="Print")*(ISERROR(SEARCH("(Varnish)",Production_Log!$D$3:$D$8963)))*Production_Log!$H$3:$H$8963) -> 0 | I39: =G39-H39 -> 0 | J39: =IF(G39=0,"-",H39/G39) -> -
B40: TUBE | C40: Samsol International Private Limited | D40: TUBES | E40: 25 | F40: 3726 | G40: =IFERROR(INDEX(MRP!$F$3:$F$8,MATCH(Tubex_Dashboard!F40,MRP!$D$3:$D$8,0)),0) -> 0 | H40: =SUMPRODUCT((Production_Log!$F$3:$F$8963=F40)*(LEFT(Production_Log!$B$3:$B$8963,5)="Print")*(ISERROR(SEARCH("(Varnish)",Production_Log!$D$3:$D$8963)))*Production_Log!$H$3:$H$8963) -> 0 | I40: =G40-H40 -> 0 | J40: =IF(G40=0,"-",H40/G40) -> -
B41: TUBE | C41: Mablay Beauty PVT LTD. | D41: HIS ONLY HAIR COLOR CREAM 40GM | E41: 25 | F41: 6228 | G41: =IFERROR(INDEX(MRP!$F$3:$F$8,MATCH(Tubex_Dashboard!F41,MRP!$D$3:$D$8,0)),0) -> 0 | H41: =SUMPRODUCT((Production_Log!$F$3:$F$8963=F41)*(LEFT(Production_Log!$B$3:$B$8963,5)="Print")*(ISERROR(SEARCH("(Varnish)",Production_Log!$D$3:$D$8963)))*Production_Log!$H$3:$H$8963) -> 0 | I41: =G41-H41 -> 0 | J41: =IF(G41=0,"-",H41/G41) -> -
B42: TUBE | C42: DTM | D42: DTM DIA 25MM | E42: 25 | F42: 6338 | G42: =IFERROR(INDEX(MRP!$F$3:$F$8,MATCH(Tubex_Dashboard!F42,MRP!$D$3:$D$8,0)),0) -> 0 | H42: =SUMPRODUCT((Production_Log!$F$3:$F$8963=F42)*(LEFT(Production_Log!$B$3:$B$8963,5)="Print")*(ISERROR(SEARCH("(Varnish)",Production_Log!$D$3:$D$8963)))*Production_Log!$H$3:$H$8963) -> 0 | I42: =G42-H42 -> 0 | J42: =IF(G42=0,"-",H42/G42) -> -
B43: TUBE | C43: Samsol International Private Limited | D43: TUBES MEN BLUE | E43: 25 | F43: 6506 | G43: =IFERROR(INDEX(MRP!$F$3:$F$8,MATCH(Tubex_Dashboard!F43,MRP!$D$3:$D$8,0)),0) -> 0 | H43: =SUMPRODUCT((Production_Log!$F$3:$F$8963=F43)*(LEFT(Production_Log!$B$3:$B$8963,5)="Print")*(ISERROR(SEARCH("(Varnish)",Production_Log!$D$3:$D$8963)))*Production_Log!$H$3:$H$8963) -> 0 | I43: =G43-H43 -> 0 | J43: =IF(G43=0,"-",H43/G43) -> -
B44: TUBE | C44: Samsol International Private Limited | D44: SAMSOL RED 25MM | E44: 25 | F44: 9006 | G44: =IFERROR(INDEX(MRP!$F$3:$F$8,MATCH(Tubex_Dashboard!F44,MRP!$D$3:$D$8,0)),0) -> 0 | H44: =SUMPRODUCT((Production_Log!$F$3:$F$8963=F44)*(LEFT(Production_Log!$B$3:$B$8963,5)="Print")*(ISERROR(SEARCH("(Varnish)",Production_Log!$D$3:$D$8963)))*Production_Log!$H$3:$H$8963) -> 0 | I44: =G44-H44 -> 0 | J44: =IF(G44=0,"-",H44/G44) -> -
B45: TUBE | C45: Professional Beauty Solution (Pvt) Ltd | D45: BELINI HAIR COLOR 50ML | E45: 25 | F45: 4227 | G45: =IFERROR(INDEX(MRP!$F$3:$F$8,MATCH(Tubex_Dashboard!F45,MRP!$D$3:$D$8,0)),0) -> 0 | H45: =SUMPRODUCT((Production_Log!$F$3:$F$8963=F45)*(LEFT(Production_Log!$B$3:$B$8963,5)="Print")*(ISERROR(SEARCH("(Varnish)",Production_Log!$D$3:$D$8963)))*Production_Log!$H$3:$H$8963) -> 0 | I45: =G45-H45 -> 0 | J45: =IF(G45=0,"-",H45/G45) -> -
... B58: TUBE | C58: Adore | D58: ANVIL 45 | E58: 35 | F58: 6021 | G58: =IFERROR(INDEX(MRP!$F$3:$F$8,MATCH(Tubex_Dashboard!F58,MRP!$D$3:$D$8,0)),0) -> 0 | H58: =SUMPRODUCT((Production_Log!$F$3:$F$8963=F58)*(LEFT(Production_Log!$B$3:$B$8963,5)="Print")*(ISERROR(SEARCH("(Varnish)",Production_Log!$D$3:$D$8963)))*Production_Log!$H$3:$H$8963) -> 0 | I58: =G58-H58 -> 0 | J58: =IF(G58=0,"-",H58/G58) -> -
B59: PET | C59: Samsol International Private Limited | D59: BLACK SMALL BOTTLE 120ML | E59: 120 ml | F59: 8011 | G59: 0 | H59: =SUMPRODUCT((Production_Log!$F$3:$F$8963=F59)*Production_Log!$H$3:$H$8963) -> 0 | I59: =G59-H59 -> 0 | J59: =IF(G59=0,"-",H59/G59) -> -
B60: PET | C60: Samsol International Private Limited | D60: WHITE SMALL BOTTLE 120ML | E60: 120 ml | F60: 8012 | G60: 0 | H60: =SUMPRODUCT((Production_Log!$F$3:$F$8963=F60)*Production_Log!$H$3:$H$8963) -> 0 | I60: =G60-H60 -> 0 | J60: =IF(G60=0,"-",H60/G60) -> -
B61: PET | C61: Mablay Beauty PVT LTD. | D61: PET BOTTLE SMALL (130ML) TRANSPARENT | E61: 130 ml | F61: 8010 | G61: 0 | H61: =SUMPRODUCT((Production_Log!$F$3:$F$8963=F61)*Production_Log!$H$3:$H$8963) -> 0 | I61: =G61-H61 -> 0 | J61: =IF(G61=0,"-",H61/G61) -> -
B62: PET | C62: Samsol International Private Limited | D62: BLACK BOTTLE 200ML | E62: 200 ml | F62: 8008 | G62: 0 | H62: =SUMPRODUCT((Production_Log!$F$3:$F$8963=F62)*Production_Log!$H$3:$H$8963) -> 0 | I62: =G62-H62 -> 0 | J62: =IF(G62=0,"-",H62/G62) -> -
B63: PET | C63: Mablay Beauty PVT LTD. | D63: TRANSPARENT BOTTLE 300ML | E63: 300 ml | F63: 8009 | G63: 0 | H63: =SUMPRODUCT((Production_Log!$F$3:$F$8963=F63)*Production_Log!$H$3:$H$8963) -> 0 | I63: =G63-H63 -> 0 | J63: =IF(G63=0,"-",H63/G63) -> -
B64: PET | C64: Mablay Beauty PVT LTD. | D64: TRANSPARENT JAR 500ML | E64: 500 ml | F64: 8013 | G64: 0 | H64: =SUMPRODUCT((Production_Log!$F$3:$F$8963=F64)*Production_Log!$H$3:$H$8963) -> 0 | I64: =G64-H64 -> 0 | J64: =IF(G64=0,"-",H64/G64) -> -

Sheet MRP
A1: JULY 2026 Tube Required Orders | G1: Date: | H1: =TODAY() -> 46210
A2: Dia | B2: Customer | C2: Product Name | D2: Product ID | E2: Job Order # | F2: Required Qty | G2: Produced | H2: Remaining Balance | I2: Remarks
A3: 16 | B3: Brookes Pharma Private Limited | C3: ECZEMUS OINTMENT 0.03% 10G | D3: 6561 | E3: 6849 | F3: 25000 | G3: =INDEX(Tubex_Dashboard!$H$11:$H$56,MATCH(MRP!D3,Tubex_Dashboard!$F$11:$F$56,0)) -> 0 | H3: =F3-G3 -> 25000 | I3: CAPS Not Approved
A4: 25 | B4: Samsol International Private Limited | C4: S-45 | D4: 5389 | E4: 6892 | F4: 100000 | G4: =INDEX(Tubex_Dashboard!$H$11:$H$56,MATCH(MRP!D4,Tubex_Dashboard!$F$11:$F$56,0)) -> 0 | H4: =F4-G4 -> 100000 | I4: 100k Extra Planned
A5: 25 | B5: Samsol International Private Limited | C5: S 43 25MM | D5: 3447 | E5: 6891 | F5: 78976 | G5: =INDEX(Tubex_Dashboard!$H$11:$H$56,MATCH(MRP!D5,Tubex_Dashboard!$F$11:$F$56,0)) -> 10416 | H5: =F5-G5 -> 68560 | I5: 100k Extra Planned
A6: 30 | B6: Mablay Beauty PVT LTD. | C6: VINCE NURTURAL | D6: 5814 | E6: 6887 | F6: 30000 | G6: =INDEX(Tubex_Dashboard!$H$11:$H$56,MATCH(MRP!D6,Tubex_Dashboard!$F$11:$F$56,0)) -> 0 | H6: =F6-G6 -> 30000
A7: 30 | B7: Golden Pearl Cosmetics (PVT) LTD | C7: HELLO HAIR COLOR | D7: 6206 | E7: 6894 | F7: 174138 | G7: =INDEX(Tubex_Dashboard!$H$11:$H$100,MATCH(MRP!D7,Tubex_Dashboard!$F$11:$F$100,0)) -> 72656 | H7: =F7-G7 -> 101482
A8: 35 | B8: Adore | C8: V- HC BROWN | D8: 6530 | E8: 6884 | F8: 13300 | G8: =INDEX(Tubex_Dashboard!$H$11:$H$56,MATCH(MRP!D8,Tubex_Dashboard!$F$11:$F$56,0)) -> 0 | H8: =F8-G8 -> 13300 | I8: HOLD
E9: TOTAL: | F9: =SUM(F3:F8) -> 421414 | G9: =SUM(G3:G8) -> 83072 | H9: =SUMIF(H3:H8, ">0") -> 338342
A10: JULY TUBES MATERIAL REQUIREMENT PLAN
A11: Item ID | B11: Category | C11: Item Name | D11: UOM | E11: Required Qty | F11: Current Stock (Store + WIP) | G11: Surplus / (Deficit) | H11: Product Name(s) | I11: Status
A12: 33 | B12: SLUG | C12: 12.5X4.5X4.8 | D12: kg | E12: =SUMPRODUCT((TableBOM[Item ID]=A12)*TableBOM[Per 1000 Units]*(1+TableBOM[Scrap %])*SUMIF($D$3:$D$8,TableBOM[Product ID],$H$3:$H$8)/1000) -> 0 | F12: =IFERROR(INDEX(TableInventory[Store Balance],MATCH(A12,TableInventory[Item ID],0)),0)+IFERROR(INDEX(TableInventory[Work In Process],MATCH(A12,TableInventory[Item ID],0)),0) -> 0 | G12: =F12-E12 -> 0 | H12: =IF(LEN(IF((COUNTIFS(TableBOM[Product ID],$D$3,TableBOM[Item ID],$A12)>0)*($H$3>0),$C$3&", ","") & IF((COUNTIFS(TableBOM[Product ID],$D$4,TableBOM[Item ID],$A12)>0)*($H$4>0),$C$4&", ","") & IF((COUNTIFS(TableBOM[Product ID],$D$5,TableBOM[Item ID],$A12)>0)*($H$5>0),$C$5&", ","") & IF((COUNTIFS(TableBOM[Product ID],$D$6,TableBOM[Item ID],$A12)>0)*($H$6>0),$C$6&", ","") & IF((COUNTIFS(TableBOM[Product ID],$D$7,TableBOM[Item ID],$A12)>0)*($H$7>0),$C$7&", ","") & IF((COUNTIFS(TableBOM[Product ID],$D$8,TableBOM[Item ID],$A12)>0)*($H$8>0),$C$8&", ",""))>1,LEFT(IF((COUNTIFS(TableBOM[Product ID],$D$3,TableBOM[Item ID],$A12)>0)*($H$3>0),$C$3&", ","") & IF((COUNTIFS(TableBOM[Product ID],$D$4,TableBOM[Item ID],$A12)>0)*($H$4>0),$C$4&", ","") & IF((COUNTIFS(TableBOM[Product ID],$D$5,TableBOM[Item ID],$A12)>0)*($H$5>0),$C$5&", ","") & IF((COUNTIFS(TableBOM[Product ID],$D$6,TableBOM[Item ID],$A12)>0)*($H$6>0),$C$6&", ","") & IF((COUNTIFS(TableBOM[Product ID],$D$7,TableBOM[Item ID],$A12)>0)*($H$7>0),$C$7&", ","") & IF((COUNTIFS(TableBOM[Product ID],$D$8,TableBOM[Item ID],$A12)>0)*($H$8>0),$C$8&", ",""),LEN(IF((COUNTIFS(TableBOM[Product ID],$D$3,TableBOM[Item ID],$A12)>0)*($H$3>0),$C$3&", ","") & IF((COUNTIFS(TableBOM[Product ID],$D$4,TableBOM[Item ID],$A12)>0)*($H$4>0),$C$4&", ","") & IF((COUNTIFS(TableBOM[Product ID],$D$5,TableBOM[Item ID],$A12)>0)*($H$5>0),$C$5&", ","") & IF((COUNTIFS(TableBOM[Product ID],$D$6,TableBOM[Item ID],$A12)>0)*($H$6>0),$C$6&", ","") & IF((COUNTIFS(TableBOM[Product ID],$D$7,TableBOM[Item ID],$A12)>0)*($H$7>0),$C$7&", ","") & IF((COUNTIFS(TableBOM[Product ID],$D$8,TableBOM[Item ID],$A12)>0)*($H$8>0),$C$8&", ",""))-2),"") | I12: =IF(E12=0,"Not needed",IF(G12<0,"SHORTAGE",IF(G12<F12*0.1,"LOW","OK"))) -> Not needed
A13: 31 | B13: SLUG | C13: 13.5X4.2 | D13: kg | E13: =SUMPRODUCT((TableBOM[Item ID]=A13)*TableBOM[Per 1000 Units]*(1+TableBOM[Scrap %])*SUMIF($D$3:$D$8,TableBOM[Product ID],$H$3:$H$8)/1000) -> 0 | F13: =IFERROR(INDEX(TableInventory[Store Balance],MATCH(A13,TableInventory[Item ID],0)),0)+IFERROR(INDEX(TableInventory[Work In Process],MATCH(A13,TableInventory[Item ID],0)),0) -> 71.5 | G13: =F13-E13 -> 71.5 | H13: =IF(LEN(IF((COUNTIFS(TableBOM[Product ID],$D$3,TableBOM[Item ID],$A13)>0)*($H$3>0),$C$3&", ","") & IF((COUNTIFS(TableBOM[Product ID],$D$4,TableBOM[Item ID],$A13)>0)*($H$4>0),$C$4&", ","") & IF((COUNTIFS(TableBOM[Product ID],$D$5,TableBOM[Item ID],$A13)>0)*($H$5>0),$C$5&", ","") & IF((COUNTIFS(TableBOM[Product ID],$D$6,TableBOM[Item ID],$A13)>0)*($H$6>0),$C$6&", ","") & IF((COUNTIFS(TableBOM[Product ID],$D$7,TableBOM[Item ID],$A13)>0)*($H$7>0),$C$7&", ","") & IF((COUNTIFS(TableBOM[Product ID],$D$8,TableBOM[Item ID],$A13)>0)*($H$8>0),$C$8&", ",""))>1,LEFT(IF((COUNTIFS(TableBOM[Product ID],$D$3,TableBOM[Item ID],$A13)>0)*($H$3>0),$C$3&", ","") & IF((COUNTIFS(TableBOM[Product ID],$D$4,TableBOM[Item ID],$A13)>0)*($H$4>0),$C$4&", ","") & IF((COUNTIFS(TableBOM[Product ID],$D$5,TableBOM[Item ID],$A13)>0)*($H$5>0),$C$5&", ","") & IF((COUNTIFS(TableBOM[Product ID],$D$6,TableBOM[Item ID],$A13)>0)*($H$6>0),$C$6&", ","") & IF((COUNTIFS(TableBOM[Product ID],$D$7,TableBOM[Item ID],$A13)>0)*($H$7>0),$C$7&", ","") & IF((COUNTIFS(TableBOM[Product ID],$D$8,TableBOM[Item ID],$A13)>0)*($H$8>0),$C$8&", ",""),LEN(IF((COUNTIFS(TableBOM[Product ID],$D$3,TableBOM[Item ID],$A13)>0)*($H$3>0),$C$3&", ","") & IF((COUNTIFS(TableBOM[Product ID],$D$4,TableBOM[Item ID],$A13)>0)*($H$4>0),$C$4&", ","") & IF((COUNTIFS(TableBOM[Product ID],$D$5,TableBOM[Item ID],$A13)>0)*($H$5>0),$C$5&", ","") & IF((COUNTIFS(TableBOM[Product ID],$D$6,TableBOM[Item ID],$A13)>0)*($H$6>0),$C$6&", ","") & IF((COUNTIFS(TableBOM[Product ID],$D$7,TableBOM[Item ID],$A13)>0)*($H$7>0),$C$7&", ","") & IF((COUNTIFS(TableBOM[Product ID],$D$8,TableBOM[Item ID],$A13)>0)*($H$8>0),$C$8&", ",""))-2),"") | I13: =IF(E13=0,"Not needed",IF(G13<0,"SHORTAGE",IF(G13<F13*0.1,"LOW","OK"))) -> Not needed
A14: 2799 | B14: SLUG | C14: 16x4.5 | D14: kg | E14: =SUMPRODUCT((TableBOM[Item ID]=A14)*TableBOM[Per 1000 Units]*(1+TableBOM[Scrap %])*SUMIF($D$3:$D$8,TableBOM[Product ID],$H$3:$H$8)/1000) -> 69.269475 | F14: =IFERROR(INDEX(TableInventory[Store Balance],MATCH(A14,TableInventory[Item ID],0)),0)+IFERROR(INDEX(TableInventory[Work In Process],MATCH(A14,TableInventory[Item ID],0)),0) -> 88 | G14: =F14-E14 -> 18.730525 | H14: =IF(LEN(IF((COUNTIFS(TableBOM[Product ID],$D$3,TableBOM[Item ID],$A14)>0)*($H$3>0),$C$3&", ","") & IF((COUNTIFS(TableBOM[Product ID],$D$4,TableBOM[Item ID],$A14)>0)*($H$4>0),$C$4&", ","") & IF((COUNTIFS(TableBOM[Product ID],$D$5,TableBOM[Item ID],$A14)>0)*($H$5>0),$C$5&", ","") & IF((COUNTIFS(TableBOM[Product ID],$D$6,TableBOM[Item ID],$A14)>0)*($H$6>0),$C$6&", ","") & IF((COUNTIFS(TableBOM[Product ID],$D$7,TableBOM[Item ID],$A14)>0)*($H$7>0),$C$7&", ","") & IF((COUNTIFS(TableBOM[Product ID],$D$8,TableBOM[Item ID],$A14)>0)*($H$8>0),$C$8&", ",""))>1,LEFT(IF((COUNTIFS(TableBOM[Product ID],$D$3,TableBOM[Item ID],$A14)>0)*($H$3>0),$C$3&", ","") & IF((COUNTIFS(TableBOM[Product ID],$D$4,TableBOM[Item ID],$A14)>0)*($H$4>0),$C$4&", ","") & IF((COUNTIFS(TableBOM[Product ID],$D$5,TableBOM[Item ID],$A14)>0)*($H$5>0),$C$5&", ","") & IF((COUNTIFS(TableBOM[Product ID],$D$6,TableBOM[Item ID],$A14)>0)*($H$6>0),$C$6&", ","") & IF((COUNTIFS(TableBOM[Product ID],$D$7,TableBOM[Item ID],$A14)>0)*($H$7>0),$C$7&", ","") & IF((COUNTIFS(TableBOM[Product ID],$D$8,TableBOM[Item ID],$A14)>0)*($H$8>0),$C$8&", ",""),LEN(IF((COUNTIFS(TableBOM[Product ID],$D$3,TableBOM[Item ID],$A14)>0)*($H$3>0),$C$3&", ","") & IF((COUNTIFS(TableBOM[Product ID],$D$4,TableBOM[Item ID],$A14)>0)*($H$4>0),$C$4&", ","") & IF((COUNTIFS(TableBOM[Product ID],$D$5,TableBOM[Item ID],$A14)>0)*($H$5>0),$C$5&", ","") & IF((COUNTIFS(TableBOM[Product ID],$D$6,TableBOM[Item ID],$A14)>0)*($H$6>0),$C$6&", ","") & IF((COUNTIFS(TableBOM[Product ID],$D$7,TableBOM[Item ID],$A14)>0)*($H$7>0),$C$7&", ","") & IF((COUNTIFS(TableBOM[Product ID],$D$8,TableBOM[Item ID],$A14)>0)*($H$8>0),$C$8&", ",""))-2),"") -> ECZEMUS OINTMENT 0.03% 10G | I14: =IF(E14=0,"Not needed",IF(G14<0,"SHORTAGE",IF(G14<F14*0.1,"LOW","OK"))) -> OK
A15: 25 | B15: SLUG | C15: 16X4.8 S/M | D15: kg | E15: =SUMPRODUCT((TableBOM[Item ID]=A15)*TableBOM[Per 1000 Units]*(1+TableBOM[Scrap %])*SUMIF($D$3:$D$8,TableBOM[Product ID],$H$3:$H$8)/1000) -> 0 | F15: =IFERROR(INDEX(TableInventory[Store Balance],MATCH(A15,TableInventory[Item ID],0)),0)+IFERROR(INDEX(TableInventory[Work In Process],MATCH(A15,TableInventory[Item ID],0)),0) -> 0 | G15: =F15-E15 -> 0 | H15: =IF(LEN(IF((COUNTIFS(TableBOM[Product ID],$D$3,TableBOM[Item ID],$A15)>0)*($H$3>0),$C$3&", ","") & IF((COUNTIFS(TableBOM[Product ID],$D$4,TableBOM[Item ID],$A15)>0)*($H$4>0),$C$4&", ","") & IF((COUNTIFS(TableBOM[Product ID],$D$5,TableBOM[Item ID],$A15)>0)*($H$5>0),$C$5&", ","") & IF((COUNTIFS(TableBOM[Product ID],$D$6,TableBOM[Item ID],$A15)>0)*($H$6>0),$C$6&", ","") & IF((COUNTIFS(TableBOM[Product ID],$D$7,TableBOM[Item ID],$A15)>0)*($H$7>0),$C$7&", ","") & IF((COUNTIFS(TableBOM[Product ID],$D$8,TableBOM[Item ID],$A15)>0)*($H$8>0),$C$8&", ",""))>1,LEFT(IF((COUNTIFS(TableBOM[Product ID],$D$3,TableBOM[Item ID],$A15)>0)*($H$3>0),$C$3&", ","") & IF((COUNTIFS(TableBOM[Product ID],$D$4,TableBOM[Item ID],$A15)>0)*($H$4>0),$C$4&", ","") & IF((COUNTIFS(TableBOM[Product ID],$D$5,TableBOM[Item ID],$A15)>0)*($H$5>0),$C$5&", ","") & IF((COUNTIFS(TableBOM[Product ID],$D$6,TableBOM[Item ID],$A15)>0)*($H$6>0),$C$6&", ","") & IF((COUNTIFS(TableBOM[Product ID],$D$7,TableBOM[Item ID],$A15)>0)*($H$7>0),$C$7&", ","") & IF((COUNTIFS(TableBOM[Product ID],$D$8,TableBOM[Item ID],$A15)>0)*($H$8>0),$C$8&", ",""),LEN(IF((COUNTIFS(TableBOM[Product ID],$D$3,TableBOM[Item ID],$A15)>0)*($H$3>0),$C$3&", ","") & IF((COUNTIFS(TableBOM[Product ID],$D$4,TableBOM[Item ID],$A15)>0)*($H$4>0),$C$4&", ","") & IF((COUNTIFS(TableBOM[Product ID],$D$5,TableBOM[Item ID],$A15)>0)*($H$5>0),$C$5&", ","") & IF((COUNTIFS(TableBOM[Product ID],$D$6,TableBOM[Item ID],$A15)>0)*($H$6>0),$C$6&", ","") & IF((COUNTIFS(TableBOM[Product ID],$D$7,TableBOM[Item ID],$A15)>0)*($H$7>0),$C$7&", ","") & IF((COUNTIFS(TableBOM[Product ID],$D$8,TableBOM[Item ID],$A15)>0)*($H$8>0),$C$8&", ",""))-2),"") | I15: =IF(E15=0,"Not needed",IF(G15<0,"SHORTAGE",IF(G15<F15*0.1,"LOW","OK"))) -> Not needed
A16: 22 | B16: SLUG | C16: 19X4.2 | D16: kg | E16: =SUMPRODUCT((TableBOM[Item ID]=A16)*TableBOM[Per 1000 Units]*(1+TableBOM[Scrap %])*SUMIF($D$3:$D$8,TableBOM[Product ID],$H$3:$H$8)/1000) -> 0 | F16: =IFERROR(INDEX(TableInventory[Store Balance],MATCH(A16,TableInventory[Item ID],0)),0)+IFERROR(INDEX(TableInventory[Work In Process],MATCH(A16,TableInventory[Item ID],0)),0) -> 0 | G16: =F16-E16 -> 0 | H16: =IF(LEN(IF((COUNTIFS(TableBOM[Product ID],$D$3,TableBOM[Item ID],$A16)>0)*($H$3>0),$C$3&", ","") & IF((COUNTIFS(TableBOM[Product ID],$D$4,TableBOM[Item ID],$A16)>0)*($H$4>0),$C$4&", ","") & IF((COUNTIFS(TableBOM[Product ID],$D$5,TableBOM[Item ID],$A16)>0)*($H$5>0),$C$5&", ","") & IF((COUNTIFS(TableBOM[Product ID],$D$6,TableBOM[Item ID],$A16)>0)*($H$6>0),$C$6&", ","") & IF((COUNTIFS(TableBOM[Product ID],$D$7,TableBOM[Item ID],$A16)>0)*($H$7>0),$C$7&", ","") & IF((COUNTIFS(TableBOM[Product ID],$D$8,TableBOM[Item ID],$A16)>0)*($H$8>0),$C$8&", ",""))>1,LEFT(IF((COUNTIFS(TableBOM[Product ID],$D$3,TableBOM[Item ID],$A16)>0)*($H$3>0),$C$3&", ","") & IF((COUNTIFS(TableBOM[Product ID],$D$4,TableBOM[Item ID],$A16)>0)*($H$4>0),$C$4&", ","") & IF((COUNTIFS(TableBOM[Product ID],$D$5,TableBOM[Item ID],$A16)>0)*($H$5>0),$C$5&", ","") & IF((COUNTIFS(TableBOM[Product ID],$D$6,TableBOM[Item ID],$A16)>0)*($H$6>0),$C$6&", ","") & IF((COUNTIFS(TableBOM[Product ID],$D$7,TableBOM[Item ID],$A16)>0)*($H$7>0),$C$7&", ","") & IF((COUNTIFS(TableBOM[Product ID],$D$8,TableBOM[Item ID],$A16)>0)*($H$8>0),$C$8&", ",""),LEN(IF((COUNTIFS(TableBOM[Product ID],$D$3,TableBOM[Item ID],$A16)>0)*($H$3>0),$C$3&", ","") & IF((COUNTIFS(TableBOM[Product ID],$D$4,TableBOM[Item ID],$A16)>0)*($H$4>0),$C$4&", ","") & IF((COUNTIFS(TableBOM[Product ID],$D$5,TableBOM[Item ID],$A16)>0)*($H$5>0),$C$5&", ","") & IF((COUNTIFS(TableBOM[Product ID],$D$6,TableBOM[Item ID],$A16)>0)*($H$6>0),$C$6&", ","") & IF((COUNTIFS(TableBOM[Product ID],$D$7,TableBOM[Item ID],$A16)>0)*($H$7>0),$C$7&", ","") & IF((COUNTIFS(TableBOM[Product ID],$D$8,TableBOM[Item ID],$A16)>0)*($H$8>0),$C$8&", ",""))-2),"") | I16: =IF(E16=0,"Not needed",IF(G16<0,"SHORTAGE",IF(G16<F16*0.1,"LOW","OK"))) -> Not needed
A17: 19 | B17: SLUG | C17: 19X4.5 S/M | D17: kg | E17: =SUMPRODUCT((TableBOM[Item ID]=A17)*TableBOM[Per 1000 Units]*(1+TableBOM[Scrap %])*SUMIF($D$3:$D$8,TableBOM[Product ID],$H$3:$H$8)/1000) -> 0 | F17: =IFERROR(INDEX(TableInventory[Store Balance],MATCH(A17,TableInventory[Item ID],0)),0)+IFERROR(INDEX(TableInventory[Work In Process],MATCH(A17,TableInventory[Item ID],0)),0) -> 425 | G17: =F17-E17 -> 425 | H17: =IF(LEN(IF((COUNTIFS(TableBOM[Product ID],$D$3,TableBOM[Item ID],$A17)>0)*($H$3>0),$C$3&", ","") & IF((COUNTIFS(TableBOM[Product ID],$D$4,TableBOM[Item ID],$A17)>0)*($H$4>0),$C$4&", ","") & IF((COUNTIFS(TableBOM[Product ID],$D$5,TableBOM[Item ID],$A17)>0)*($H$5>0),$C$5&", ","") & IF((COUNTIFS(TableBOM[Product ID],$D$6,TableBOM[Item ID],$A17)>0)*($H$6>0),$C$6&", ","") & IF((COUNTIFS(TableBOM[Product ID],$D$7,TableBOM[Item ID],$A17)>0)*($H$7>0),$C$7&", ","") & IF((COUNTIFS(TableBOM[Product ID],$D$8,TableBOM[Item ID],$A17)>0)*($H$8>0),$C$8&", ",""))>1,LEFT(IF((COUNTIFS(TableBOM[Product ID],$D$3,TableBOM[Item ID],$A17)>0)*($H$3>0),$C$3&", ","") & IF((COUNTIFS(TableBOM[Product ID],$D$4,TableBOM[Item ID],$A17)>0)*($H$4>0),$C$4&", ","") & IF((COUNTIFS(TableBOM[Product ID],$D$5,TableBOM[Item ID],$A17)>0)*($H$5>0),$C$5&", ","") & IF((COUNTIFS(TableBOM[Product ID],$D$6,TableBOM[Item ID],$A17)>0)*($H$6>0),$C$6&", ","") & IF((COUNTIFS(TableBOM[Product ID],$D$7,TableBOM[Item ID],$A17)>0)*($H$7>0),$C$7&", ","") & IF((COUNTIFS(TableBOM[Product ID],$D$8,TableBOM[Item ID],$A17)>0)*($H$8>0),$C$8&", ",""),LEN(IF((COUNTIFS(TableBOM[Product ID],$D$3,TableBOM[Item ID],$A17)>0)*($H$3>0),$C$3&", ","") & IF((COUNTIFS(TableBOM[Product ID],$D$4,TableBOM[Item ID],$A17)>0)*($H$4>0),$C$4&", ","") & IF((COUNTIFS(TableBOM[Product ID],$D$5,TableBOM[Item ID],$A17)>0)*($H$5>0),$C$5&", ","") & IF((COUNTIFS(TableBOM[Product ID],$D$6,TableBOM[Item ID],$A17)>0)*($H$6>0),$C$6&", ","") & IF((COUNTIFS(TableBOM[Product ID],$D$7,TableBOM[Item ID],$A17)>0)*($H$7>0),$C$7&", ","") & IF((COUNTIFS(TableBOM[Product ID],$D$8,TableBOM[Item ID],$A17)>0)*($H$8>0),$C$8&", ",""))-2),"") | I17: =IF(E17=0,"Not needed",IF(G17<0,"SHORTAGE",IF(G17<F17*0.1,"LOW","OK"))) -> Not needed
A18: 4179 | B18: SLUG | C18: 20.5x4.5 | D18: kg | E18: =SUMPRODUCT((TableBOM[Item ID]=A18)*TableBOM[Per 1000 Units]*(1+TableBOM[Scrap %])*SUMIF($D$3:$D$8,TableBOM[Product ID],$H$3:$H$8)/1000) -> 0 | F18: =IFERROR(INDEX(TableInventory[Store Balance],MATCH(A18,TableInventory[Item ID],0)),0)+IFERROR(INDEX(TableInventory[Work In Process],MATCH(A18,TableInventory[Item ID],0)),0) -> 132 | G18: =F18-E18 -> 132 | H18: =IF(LEN(IF((COUNTIFS(TableBOM[Product ID],$D$3,TableBOM[Item ID],$A18)>0)*($H$3>0),$C$3&", ","") & IF((COUNTIFS(TableBOM[Product ID],$D$4,TableBOM[Item ID],$A18)>0)*($H$4>0),$C$4&", ","") & IF((COUNTIFS(TableBOM[Product ID],$D$5,TableBOM[Item ID],$A18)>0)*($H$5>0),$C$5&", ","") & IF((COUNTIFS(TableBOM[Product ID],$D$6,TableBOM[Item ID],$A18)>0)*($H$6>0),$C$6&", ","") & IF((COUNTIFS(TableBOM[Product ID],$D$7,TableBOM[Item ID],$A18)>0)*($H$7>0),$C$7&", ","") & IF((COUNTIFS(TableBOM[Product ID],$D$8,TableBOM[Item ID],$A18)>0)*($H$8>0),$C$8&", ",""))>1,LEFT(IF((COUNTIFS(TableBOM[Product ID],$D$3,TableBOM[Item ID],$A18)>0)*($H$3>0),$C$3&", ","") & IF((COUNTIFS(TableBOM[Product ID],$D$4,TableBOM[Item ID],$A18)>0)*($H$4>0),$C$4&", ","") & IF((COUNTIFS(TableBOM[Product ID],$D$5,TableBOM[Item ID],$A18)>0)*($H$5>0),$C$5&", ","") & IF((COUNTIFS(TableBOM[Product ID],$D$6,TableBOM[Item ID],$A18)>0)*($H$6>0),$C$6&", ","") & IF((COUNTIFS(TableBOM[Product ID],$D$7,TableBOM[Item ID],$A18)>0)*($H$7>0),$C$7&", ","") & IF((COUNTIFS(TableBOM[Product ID],$D$8,TableBOM[Item ID],$A18)>0)*($H$8>0),$C$8&", ",""),LEN(IF((COUNTIFS(TableBOM[Product ID],$D$3,TableBOM[Item ID],$A18)>0)*($H$3>0),$C$3&", ","") & IF((COUNTIFS(TableBOM[Product ID],$D$4,TableBOM[Item ID],$A18)>0)*($H$4>0),$C$4&", ","") & IF((COUNTIFS(TableBOM[Product ID],$D$5,TableBOM[Item ID],$A18)>0)*($H$5>0),$C$5&", ","") & IF((COUNTIFS(TableBOM[Product ID],$D$6,TableBOM[Item ID],$A18)>0)*($H$6>0),$C$6&", ","") & IF((COUNTIFS(TableBOM[Product ID],$D$7,TableBOM[Item ID],$A18)>0)*($H$7>0),$C$7&", ","") & IF((COUNTIFS(TableBOM[Product ID],$D$8,TableBOM[Item ID],$A18)>0)*($H$8>0),$C$8&", ",""))-2),"") | I18: =IF(E18=0,"Not needed",IF(G18<0,"SHORTAGE",IF(G18<F18*0.1,"LOW","OK"))) -> Not needed
A19: 6 | B19: SLUG | C19: 25X4.5 S/M | D19: kg | E19: =SUMPRODUCT((TableBOM[Item ID]=A19)*TableBOM[Per 1000 Units]*(1+TableBOM[Scrap %])*SUMIF($D$3:$D$8,TableBOM[Product ID],$H$3:$H$8)/1000) -> 1097.1065 | F19: =IFERROR(INDEX(TableInventory[Store Balance],MATCH(A19,TableInventory[Item ID],0)),0)+IFERROR(INDEX(TableInventory[Work In Process],MATCH(A19,TableInventory[Item ID],0)),0) -> 325 | G19: =F19-E19 -> -772.10647 | H19: =IF(LEN(IF((COUNTIFS(TableBOM[Product ID],$D$3,TableBOM[Item ID],$A19)>0)*($H$3>0),$C$3&", ","") & IF((COUNTIFS(TableBOM[Product ID],$D$4,TableBOM[Item ID],$A19)>0)*($H$4>0),$C$4&", ","") & IF((COUNTIFS(TableBOM[Product ID],$D$5,TableBOM[Item ID],$A19)>0)*($H$5>0),$C$5&", ","") & IF((COUNTIFS(TableBOM[Product ID],$D$6,TableBOM[Item ID],$A19)>0)*($H$6>0),$C$6&", ","") & IF((COUNTIFS(TableBOM[Product ID],$D$7,TableBOM[Item ID],$A19)>0)*($H$7>0),$C$7&", ","") & IF((COUNTIFS(TableBOM[Product ID],$D$8,TableBOM[Item ID],$A19)>0)*($H$8>0),$C$8&", ",""))>1,LEFT(IF((COUNTIFS(TableBOM[Product ID],$D$3,TableBOM[Item ID],$A19)>0)*($H$3>0),$C$3&", ","") & IF((COUNTIFS(TableBOM[Product ID],$D$4,TableBOM[Item ID],$A19)>0)*($H$4>0),$C$4&", ","") & IF((COUNTIFS(TableBOM[Product ID],$D$5,TableBOM[Item ID],$A19)>0)*($H$5>0),$C$5&", ","") & IF((COUNTIFS(TableBOM[Product ID],$D$6,TableBOM[Item ID],$A19)>0)*($H$6>0),$C$6&", ","") & IF((COUNTIFS(TableBOM[Product ID],$D$7,TableBOM[Item ID],$A19)>0)*($H$7>0),$C$7&", ","") & IF((COUNTIFS(TableBOM[Product ID],$D$8,TableBOM[Item ID],$A19)>0)*($H$8>0),$C$8&", ",""),LEN(IF((COUNTIFS(TableBOM[Product ID],$D$3,TableBOM[Item ID],$A19)>0)*($H$3>0),$C$3&", ","") & IF((COUNTIFS(TableBOM[Product ID],$D$4,TableBOM[Item ID],$A19)>0)*($H$4>0),$C$4&", ","") & IF((COUNTIFS(TableBOM[Product ID],$D$5,TableBOM[Item ID],$A19)>0)*($H$5>0),$C$5&", ","") & IF((COUNTIFS(TableBOM[Product ID],$D$6,TableBOM[Item ID],$A19)>0)*($H$6>0),$C$6&", ","") & IF((COUNTIFS(TableBOM[Product ID],$D$7,TableBOM[Item ID],$A19)>0)*($H$7>0),$C$7&", ","") & IF((COUNTIFS(TableBOM[Product ID],$D$8,TableBOM[Item ID],$A19)>0)*($H$8>0),$C$8&", ",""))-2),"") -> S-45, S 43 25MM | I19: =IF(E19=0,"Not needed",IF(G19<0,"SHORTAGE",IF(G19<F19*0.1,"LOW","OK"))) -> SHORTAGE
A20: 10 | B20: SLUG | C20: 25X4.8 S/M | D20: kg | E20: =SUMPRODUCT((TableBOM[Item ID]=A20)*TableBOM[Per 1000 Units]*(1+TableBOM[Scrap %])*SUMIF($D$3:$D$8,TableBOM[Product ID],$H$3:$H$8)/1000) -> 0 | F20: =IFERROR(INDEX(TableInventory[Store Balance],MATCH(A20,TableInventory[Item ID],0)),0)+IFERROR(INDEX(TableInventory[Work In Process],MATCH(A20,TableInventory[Item ID],0)),0) -> 0 | G20: =F20-E20 -> 0 | H20: =IF(LEN(IF((COUNTIFS(TableBOM[Product ID],$D$3,TableBOM[Item ID],$A20)>0)*($H$3>0),$C$3&", ","") & IF((COUNTIFS(TableBOM[Product ID],$D$4,TableBOM[Item ID],$A20)>0)*($H$4>0),$C$4&", ","") & IF((COUNTIFS(TableBOM[Product ID],$D$5,TableBOM[Item ID],$A20)>0)*($H$5>0),$C$5&", ","") & IF((COUNTIFS(TableBOM[Product ID],$D$6,TableBOM[Item ID],$A20)>0)*($H$6>0),$C$6&", ","") & IF((COUNTIFS(TableBOM[Product ID],$D$7,TableBOM[Item ID],$A20)>0)*($H$7>0),$C$7&", ","") & IF((COUNTIFS(TableBOM[Product ID],$D$8,TableBOM[Item ID],$A20)>0)*($H$8>0),$C$8&", ",""))>1,LEFT(IF((COUNTIFS(TableBOM[Product ID],$D$3,TableBOM[Item ID],$A20)>0)*($H$3>0),$C$3&", ","") & IF((COUNTIFS(TableBOM[Product ID],$D$4,TableBOM[Item ID],$A20)>0)*($H$4>0),$C$4&", ","") & IF((COUNTIFS(TableBOM[Product ID],$D$5,TableBOM[Item ID],$A20)>0)*($H$5>0),$C$5&", ","") & IF((COUNTIFS(TableBOM[Product ID],$D$6,TableBOM[Item ID],$A20)>0)*($H$6>0),$C$6&", ","") & IF((COUNTIFS(TableBOM[Product ID],$D$7,TableBOM[Item ID],$A20)>0)*($H$7>0),$C$7&", ","") & IF((COUNTIFS(TableBOM[Product ID],$D$8,TableBOM[Item ID],$A20)>0)*($H$8>0),$C$8&", ",""),LEN(IF((COUNTIFS(TableBOM[Product ID],$D$3,TableBOM[Item ID],$A20)>0)*($H$3>0),$C$3&", ","") & IF((COUNTIFS(TableBOM[Product ID],$D$4,TableBOM[Item ID],$A20)>0)*($H$4>0),$C$4&", ","") & IF((COUNTIFS(TableBOM[Product ID],$D$5,TableBOM[Item ID],$A20)>0)*($H$5>0),$C$5&", ","") & IF((COUNTIFS(TableBOM[Product ID],$D$6,TableBOM[Item ID],$A20)>0)*($H$6>0),$C$6&", ","") & IF((COUNTIFS(TableBOM[Product ID],$D$7,TableBOM[Item ID],$A20)>0)*($H$7>0),$C$7&", ","") & IF((COUNTIFS(TableBOM[Product ID],$D$8,TableBOM[Item ID],$A20)>0)*($H$8>0),$C$8&", ",""))-2),"") | I20: =IF(E20=0,"Not needed",IF(G20<0,"SHORTAGE",IF(G20<F20*0.1,"LOW","OK"))) -> Not needed
A21: 2 | B21: SLUG | C21: 30X4.3 | D21: kg | E21: =SUMPRODUCT((TableBOM[Item ID]=A21)*TableBOM[Per 1000 Units]*(1+TableBOM[Scrap %])*SUMIF($D$3:$D$8,TableBOM[Product ID],$H$3:$H$8)/1000) -> 0 | F21: =IFERROR(INDEX(TableInventory[Store Balance],MATCH(A21,TableInventory[Item ID],0)),0)+IFERROR(INDEX(TableInventory[Work In Process],MATCH(A21,TableInventory[Item ID],0)),0) -> 0 | G21: =F21-E21 -> 0 | H21: =IF(LEN(IF((COUNTIFS(TableBOM[Product ID],$D$3,TableBOM[Item ID],$A21)>0)*($H$3>0),$C$3&", ","") & IF((COUNTIFS(TableBOM[Product ID],$D$4,TableBOM[Item ID],$A21)>0)*($H$4>0),$C$4&", ","") & IF((COUNTIFS(TableBOM[Product ID],$D$5,TableBOM[Item ID],$A21)>0)*($H$5>0),$C$5&", ","") & IF((COUNTIFS(TableBOM[Product ID],$D$6,TableBOM[Item ID],$A21)>0)*($H$6>0),$C$6&", ","") & IF((COUNTIFS(TableBOM[Product ID],$D$7,TableBOM[Item ID],$A21)>0)*($H$7>0),$C$7&", ","") & IF((COUNTIFS(TableBOM[Product ID],$D$8,TableBOM[Item ID],$A21)>0)*($H$8>0),$C$8&", ",""))>1,LEFT(IF((COUNTIFS(TableBOM[Product ID],$D$3,TableBOM[Item ID],$A21)>0)*($H$3>0),$C$3&", ","") & IF((COUNTIFS(TableBOM[Product ID],$D$4,TableBOM[Item ID],$A21)>0)*($H$4>0),$C$4&", ","") & IF((COUNTIFS(TableBOM[Product ID],$D$5,TableBOM[Item ID],$A21)>0)*($H$5>0),$C$5&", ","") & IF((COUNTIFS(TableBOM[Product ID],$D$6,TableBOM[Item ID],$A21)>0)*($H$6>0),$C$6&", ","") & IF((COUNTIFS(TableBOM[Product ID],$D$7,TableBOM[Item ID],$A21)>0)*($H$7>0),$C$7&", ","") & IF((COUNTIFS(TableBOM[Product ID],$D$8,TableBOM[Item ID],$A21)>0)*($H$8>0),$C$8&", ",""),LEN(IF((COUNTIFS(TableBOM[Product ID],$D$3,TableBOM[Item ID],$A21)>0)*($H$3>0),$C$3&", ","") & IF((COUNTIFS(TableBOM[Product ID],$D$4,TableBOM[Item ID],$A21)>0)*($H$4>0),$C$4&", ","") & IF((COUNTIFS(TableBOM[Product ID],$D$5,TableBOM[Item ID],$A21)>0)*($H$5>0),$C$5&", ","") & IF((COUNTIFS(TableBOM[Product ID],$D$6,TableBOM[Item ID],$A21)>0)*($H$6>0),$C$6&", ","") & IF((COUNTIFS(TableBOM[Product ID],$D$7,TableBOM[Item ID],$A21)>0)*($H$7>0),$C$7&", ","") & IF((COUNTIFS(TableBOM[Product ID],$D$8,TableBOM[Item ID],$A21)>0)*($H$8>0),$C$8&", ",""))-2),"") | I21: =IF(E21=0,"Not needed",IF(G21<0,"SHORTAGE",IF(G21<F21*0.1,"LOW","OK"))) -> Not needed
A22: 406 | B22: SLUG | C22: 30X4.5 S/M | D22: kg | E22: =SUMPRODUCT((TableBOM[Item ID]=A22)*TableBOM[Per 1000 Units]*(1+TableBOM[Scrap %])*SUMIF($D$3:$D$8,TableBOM[Product ID],$H$3:$H$8)/1000) -> 1157.0416 | F22: =IFERROR(INDEX(TableInventory[Store Balance],MATCH(A22,TableInventory[Item ID],0)),0)+IFERROR(INDEX(TableInventory[Work In Process],MATCH(A22,TableInventory[Item ID],0)),0) -> 298 | G22: =F22-E22 -> -859.0416 | H22: =IF(LEN(IF((COUNTIFS(TableBOM[Product ID],$D$3,TableBOM[Item ID],$A22)>0)*($H$3>0),$C$3&", ","") & IF((COUNTIFS(TableBOM[Product ID],$D$4,TableBOM[Item ID],$A22)>0)*($H$4>0),$C$4&", ","") & IF((COUNTIFS(TableBOM[Product ID],$D$5,TableBOM[Item ID],$A22)>0)*($H$5>0),$C$5&", ","") & IF((COUNTIFS(TableBOM[Product ID],$D$6,TableBOM[Item ID],$A22)>0)*($H$6>0),$C$6&", ","") & IF((COUNTIFS(TableBOM[Product ID],$D$7,TableBOM[Item ID],$A22)>0)*($H$7>0),$C$7&", ","") & IF((COUNTIFS(TableBOM[Product ID],$D$8,TableBOM[Item ID],$A22)>0)*($H$8>0),$C$8&", ",""))>1,LEFT(IF((COUNTIFS(TableBOM[Product ID],$D$3,TableBOM[Item ID],$A22)>0)*($H$3>0),$C$3&", ","") & IF((COUNTIFS(TableBOM[Product ID],$D$4,TableBOM[Item ID],$A22)>0)*($H$4>0),$C$4&", ","") & IF((COUNTIFS(TableBOM[Product ID],$D$5,TableBOM[Item ID],$A22)>0)*($H$5>0),$C$5&", ","") & IF((COUNTIFS(TableBOM[Product ID],$D$6,TableBOM[Item ID],$A22)>0)*($H$6>0),$C$6&", ","") & IF((COUNTIFS(TableBOM[Product ID],$D$7,TableBOM[Item ID],$A22)>0)*($H$7>0),$C$7&", ","") & IF((COUNTIFS(TableBOM[Product ID],$D$8,TableBOM[Item ID],$A22)>0)*($H$8>0),$C$8&", ",""),LEN(IF((COUNTIFS(TableBOM[Product ID],$D$3,TableBOM[Item ID],$A22)>0)*($H$3>0),$C$3&", ","") & IF((COUNTIFS(TableBOM[Product ID],$D$4,TableBOM[Item ID],$A22)>0)*($H$4>0),$C$4&", ","") & IF((COUNTIFS(TableBOM[Product ID],$D$5,TableBOM[Item ID],$A22)>0)*($H$5>0),$C$5&", ","") & IF((COUNTIFS(TableBOM[Product ID],$D$6,TableBOM[Item ID],$A22)>0)*($H$6>0),$C$6&", ","") & IF((COUNTIFS(TableBOM[Product ID],$D$7,TableBOM[Item ID],$A22)>0)*($H$7>0),$C$7&", ","") & IF((COUNTIFS(TableBOM[Product ID],$D$8,TableBOM[Item ID],$A22)>0)*($H$8>0),$C$8&", ",""))-2),"") -> VINCE NURTURAL, HELLO HAIR COLOR | I22: =IF(E22=0,"Not needed",IF(G22<0,"SHORTAGE",IF(G22<F22*0.1,"LOW","OK"))) -> SHORTAGE
A23: 6961 | B23: SLUG | C23: 32X5.2 | D23: kg | E23: =SUMPRODUCT((TableBOM[Item ID]=A23)*TableBOM[Per 1000 Units]*(1+TableBOM[Scrap %])*SUMIF($D$3:$D$8,TableBOM[Product ID],$H$3:$H$8)/1000) -> 0 | F23: =IFERROR(INDEX(TableInventory[Store Balance],MATCH(A23,TableInventory[Item ID],0)),0)+IFERROR(INDEX(TableInventory[Work In Process],MATCH(A23,TableInventory[Item ID],0)),0) -> 0 | G23: =F23-E23 -> 0 | H23: =IF(LEN(IF((COUNTIFS(TableBOM[Product ID],$D$3,TableBOM[Item ID],$A23)>0)*($H$3>0),$C$3&", ","") & IF((COUNTIFS(TableBOM[Product ID],$D$4,TableBOM[Item ID],$A23)>0)*($H$4>0),$C$4&", ","") & IF((COUNTIFS(TableBOM[Product ID],$D$5,TableBOM[Item ID],$A23)>0)*($H$5>0),$C$5&", ","") & IF((COUNTIFS(TableBOM[Product ID],$D$6,TableBOM[Item ID],$A23)>0)*($H$6>0),$C$6&", ","") & IF((COUNTIFS(TableBOM[Product ID],$D$7,TableBOM[Item ID],$A23)>0)*($H$7>0),$C$7&", ","") & IF((COUNTIFS(TableBOM[Product ID],$D$8,TableBOM[Item ID],$A23)>0)*($H$8>0),$C$8&", ",""))>1,LEFT(IF((COUNTIFS(TableBOM[Product ID],$D$3,TableBOM[Item ID],$A23)>0)*($H$3>0),$C$3&", ","") & IF((COUNTIFS(TableBOM[Product ID],$D$4,TableBOM[Item ID],$A23)>0)*($H$4>0),$C$4&", ","") & IF((COUNTIFS(TableBOM[Product ID],$D$5,TableBOM[Item ID],$A23)>0)*($H$5>0),$C$5&", ","") & IF((COUNTIFS(TableBOM[Product ID],$D$6,TableBOM[Item ID],$A23)>0)*($H$6>0),$C$6&", ","") & IF((COUNTIFS(TableBOM[Product ID],$D$7,TableBOM[Item ID],$A23)>0)*($H$7>0),$C$7&", ","") & IF((COUNTIFS(TableBOM[Product ID],$D$8,TableBOM[Item ID],$A23)>0)*($H$8>0),$C$8&", ",""),LEN(IF((COUNTIFS(TableBOM[Product ID],$D$3,TableBOM[Item ID],$A23)>0)*($H$3>0),$C$3&", ","") & IF((COUNTIFS(TableBOM[Product ID],$D$4,TableBOM[Item ID],$A23)>0)*($H$4>0),$C$4&", ","") & IF((COUNTIFS(TableBOM[Product ID],$D$5,TableBOM[Item ID],$A23)>0)*($H$5>0),$C$5&", ","") & IF((COUNTIFS(TableBOM[Product ID],$D$6,TableBOM[Item ID],$A23)>0)*($H$6>0),$C$6&", ","") & IF((COUNTIFS(TableBOM[Product ID],$D$7,TableBOM[Item ID],$A23)>0)*($H$7>0),$C$7&", ","") & IF((COUNTIFS(TableBOM[Product ID],$D$8,TableBOM[Item ID],$A23)>0)*($H$8>0),$C$8&", ",""))-2),"") | I23: =IF(E23=0,"Not needed",IF(G23<0,"SHORTAGE",IF(G23<F23*0.1,"LOW","OK"))) -> Not needed
A24: 3935 | B24: SLUG | C24: 32x5.0 | D24: kg | E24: =SUMPRODUCT((TableBOM[Item ID]=A24)*TableBOM[Per 1000 Units]*(1+TableBOM[Scrap %])*SUMIF($D$3:$D$8,TableBOM[Product ID],$H$3:$H$8)/1000) -> 0 | F24: =IFERROR(INDEX(TableInventory[Store Balance],MATCH(A24,TableInventory[Item ID],0)),0)+IFERROR(INDEX(TableInventory[Work In Process],MATCH(A24,TableInventory[Item ID],0)),0) -> 444 | G24: =F24-E24 -> 444 | H24: =IF(LEN(IF((COUNTIFS(TableBOM[Product ID],$D$3,TableBOM[Item ID],$A24)>0)*($H$3>0),$C$3&", ","") & IF((COUNTIFS(TableBOM[Product ID],$D$4,TableBOM[Item ID],$A24)>0)*($H$4>0),$C$4&", ","") & IF((COUNTIFS(TableBOM[Product ID],$D$5,TableBOM[Item ID],$A24)>0)*($H$5>0),$C$5&", ","") & IF((COUNTIFS(TableBOM[Product ID],$D$6,TableBOM[Item ID],$A24)>0)*($H$6>0),$C$6&", ","") & IF((COUNTIFS(TableBOM[Product ID],$D$7,TableBOM[Item ID],$A24)>0)*($H$7>0),$C$7&", ","") & IF((COUNTIFS(TableBOM[Product ID],$D$8,TableBOM[Item ID],$A24)>0)*($H$8>0),$C$8&", ",""))>1,LEFT(IF((COUNTIFS(TableBOM[Product ID],$D$3,TableBOM[Item ID],$A24)>0)*($H$3>0),$C$3&", ","") & IF((COUNTIFS(TableBOM[Product ID],$D$4,TableBOM[Item ID],$A24)>0)*($H$4>0),$C$4&", ","") & IF((COUNTIFS(TableBOM[Product ID],$D$5,TableBOM[Item ID],$A24)>0)*($H$5>0),$C$5&", ","") & IF((COUNTIFS(TableBOM[Product ID],$D$6,TableBOM[Item ID],$A24)>0)*($H$6>0),$C$6&", ","") & IF((COUNTIFS(TableBOM[Product ID],$D$7,TableBOM[Item ID],$A24)>0)*($H$7>0),$C$7&", ","") & IF((COUNTIFS(TableBOM[Product ID],$D$8,TableBOM[Item ID],$A24)>0)*($H$8>0),$C$8&", ",""),LEN(IF((COUNTIFS(TableBOM[Product ID],$D$3,TableBOM[Item ID],$A24)>0)*($H$3>0),$C$3&", ","") & IF((COUNTIFS(TableBOM[Product ID],$D$4,TableBOM[Item ID],$A24)>0)*($H$4>0),$C$4&", ","") & IF((COUNTIFS(TableBOM[Product ID],$D$5,TableBOM[Item ID],$A24)>0)*($H$5>0),$C$5&", ","") & IF((COUNTIFS(TableBOM[Product ID],$D$6,TableBOM[Item ID],$A24)>0)*($H$6>0),$C$6&", ","") & IF((COUNTIFS(TableBOM[Product ID],$D$7,TableBOM[Item ID],$A24)>0)*($H$7>0),$C$7&", ","") & IF((COUNTIFS(TableBOM[Product ID],$D$8,TableBOM[Item ID],$A24)>0)*($H$8>0),$C$8&", ",""))-2),"") | I24: =IF(E24=0,"Not needed",IF(G24<0,"SHORTAGE",IF(G24<F24*0.1,"LOW","OK"))) -> Not needed
A25: 3503 | B25: SLUG | C25: 35X5.0 | D25: kg | E25: =SUMPRODUCT((TableBOM[Item ID]=A25)*TableBOM[Per 1000 Units]*(1+TableBOM[Scrap %])*SUMIF($D$3:$D$8,TableBOM[Product ID],$H$3:$H$8)/1000) -> 187.5566 | F25: =IFERROR(INDEX(TableInventory[Store Balance],MATCH(A25,TableInventory[Item ID],0)),0)+IFERROR(INDEX(TableInventory[Work In Process],MATCH(A25,TableInventory[Item ID],0)),0) -> 328 | G25: =F25-E25 -> 140.4434 | H25: =IF(LEN(IF((COUNTIFS(TableBOM[Product ID],$D$3,TableBOM[Item ID],$A25)>0)*($H$3>0),$C$3&", ","") & IF((COUNTIFS(TableBOM[Product ID],$D$4,TableBOM[Item ID],$A25)>0)*($H$4>0),$C$4&", ","") & IF((COUNTIFS(TableBOM[Product ID],$D$5,TableBOM[Item ID],$A25)>0)*($H$5>0),$C$5&", ","") & IF((COUNTIFS(TableBOM[Product ID],$D$6,TableBOM[Item ID],$A25)>0)*($H$6>0),$C$6&", ","") & IF((COUNTIFS(TableBOM[Product ID],$D$7,TableBOM[Item ID],$A25)>0)*($H$7>0),$C$7&", ","") & IF((COUNTIFS(TableBOM[Product ID],$D$8,TableBOM[Item ID],$A25)>0)*($H$8>0),$C$8&", ",""))>1,LEFT(IF((COUNTIFS(TableBOM[Product ID],$D$3,TableBOM[Item ID],$A25)>0)*($H$3>0),$C$3&", ","") & IF((COUNTIFS(TableBOM[Product ID],$D$4,TableBOM[Item ID],$A25)>0)*($H$4>0),$C$4&", ","") & IF((COUNTIFS(TableBOM[Product ID],$D$5,TableBOM[Item ID],$A25)>0)*($H$5>0),$C$5&", ","") & IF((COUNTIFS(TableBOM[Product ID],$D$6,TableBOM[Item ID],$A25)>0)*($H$6>0),$C$6&", ","") & IF((COUNTIFS(TableBOM[Product ID],$D$7,TableBOM[Item ID],$A25)>0)*($H$7>0),$C$7&", ","") & IF((COUNTIFS(TableBOM[Product ID],$D$8,TableBOM[Item ID],$A25)>0)*($H$8>0),$C$8&", ",""),LEN(IF((COUNTIFS(TableBOM[Product ID],$D$3,TableBOM[Item ID],$A25)>0)*($H$3>0),$C$3&", ","") & IF((COUNTIFS(TableBOM[Product ID],$D$4,TableBOM[Item ID],$A25)>0)*($H$4>0),$C$4&", ","") & IF((COUNTIFS(TableBOM[Product ID],$D$5,TableBOM[Item ID],$A25)>0)*($H$5>0),$C$5&", ","") & IF((COUNTIFS(TableBOM[Product ID],$D$6,TableBOM[Item ID],$A25)>0)*($H$6>0),$C$6&", ","") & IF((COUNTIFS(TableBOM[Product ID],$D$7,TableBOM[Item ID],$A25)>0)*($H$7>0),$C$7&", ","") & IF((COUNTIFS(TableBOM[Product ID],$D$8,TableBOM[Item ID],$A25)>0)*($H$8>0),$C$8&", ",""))-2),"") -> V- HC BROWN | I25: HOLD
A26: 184 | B26: LACQUER | C26: LACQUER IMP 49989 | D26: kg | E26: =SUMPRODUCT((TableBOM[Item ID]=A26)*TableBOM[Per 1000 Units]*(1+TableBOM[Scrap %])*SUMIF($D$3:$D$8,TableBOM[Product ID],$H$3:$H$8)/1000) -> 0 | F26: =IFERROR(INDEX(TableInventory[Store Balance],MATCH(A26,TableInventory[Item ID],0)),0)+IFERROR(INDEX(TableInventory[Work In Process],MATCH(A26,TableInventory[Item ID],0)),0) -> 0 | G26: =F26-E26 -> 0 | H26: =IF(LEN(IF((COUNTIFS(TableBOM[Product ID],$D$3,TableBOM[Item ID],$A26)>0)*($H$3>0),$C$3&", ","") & IF((COUNTIFS(TableBOM[Product ID],$D$4,TableBOM[Item ID],$A26)>0)*($H$4>0),$C$4&", ","") & IF((COUNTIFS(TableBOM[Product ID],$D$5,TableBOM[Item ID],$A26)>0)*($H$5>0),$C$5&", ","") & IF((COUNTIFS(TableBOM[Product ID],$D$6,TableBOM[Item ID],$A26)>0)*($H$6>0),$C$6&", ","") & IF((COUNTIFS(TableBOM[Product ID],$D$7,TableBOM[Item ID],$A26)>0)*($H$7>0),$C$7&", ","") & IF((COUNTIFS(TableBOM[Product ID],$D$8,TableBOM[Item ID],$A26)>0)*($H$8>0),$C$8&", ",""))>1,LEFT(IF((COUNTIFS(TableBOM[Product ID],$D$3,TableBOM[Item ID],$A26)>0)*($H$3>0),$C$3&", ","") & IF((COUNTIFS(TableBOM[Product ID],$D$4,TableBOM[Item ID],$A26)>0)*($H$4>0),$C$4&", ","") & IF((COUNTIFS(TableBOM[Product ID],$D$5,TableBOM[Item ID],$A26)>0)*($H$5>0),$C$5&", ","") & IF((COUNTIFS(TableBOM[Product ID],$D$6,TableBOM[Item ID],$A26)>0)*($H$6>0),$C$6&", ","") & IF((COUNTIFS(TableBOM[Product ID],$D$7,TableBOM[Item ID],$A26)>0)*($H$7>0),$C$7&", ","") & IF((COUNTIFS(TableBOM[Product ID],$D$8,TableBOM[Item ID],$A26)>0)*($H$8>0),$C$8&", ",""),LEN(IF((COUNTIFS(TableBOM[Product ID],$D$3,TableBOM[Item ID],$A26)>0)*($H$3>0),$C$3&", ","") & IF((COUNTIFS(TableBOM[Product ID],$D$4,TableBOM[Item ID],$A26)>0)*($H$4>0),$C$4&", ","") & IF((COUNTIFS(TableBOM[Product ID],$D$5,TableBOM[Item ID],$A26)>0)*($H$5>0),$C$5&", ","") & IF((COUNTIFS(TableBOM[Product ID],$D$6,TableBOM[Item ID],$A26)>0)*($H$6>0),$C$6&", ","") & IF((COUNTIFS(TableBOM[Product ID],$D$7,TableBOM[Item ID],$A26)>0)*($H$7>0),$C$7&", ","") & IF((COUNTIFS(TableBOM[Product ID],$D$8,TableBOM[Item ID],$A26)>0)*($H$8>0),$C$8&", ",""))-2),"") | I26: =IF(E26=0,"Not needed",IF(G26<0,"SHORTAGE",IF(G26<F26*0.1,"LOW","OK"))) -> Not needed
A27: 185 | B27: LACQUER | C27: EPOXY LACQUER (1500) | D27: L | E27: =SUMPRODUCT((TableBOM[Item ID]=A27)*TableBOM[Per 1000 Units]*(1+TableBOM[Scrap %])*SUMIF($D$3:$D$8,TableBOM[Product ID],$H$3:$H$8)/1000) -> 64.977959 | F27: =IFERROR(INDEX(TableInventory[Store Balance],MATCH(A27,TableInventory[Item ID],0)),0)+IFERROR(INDEX(TableInventory[Work In Process],MATCH(A27,TableInventory[Item ID],0)),0) -> 50 | G27: =F27-E27 -> -14.977959 | H27: =IF(LEN(IF((COUNTIFS(TableBOM[Product ID],$D$3,TableBOM[Item ID],$A27)>0)*($H$3>0),$C$3&", ","") & IF((COUNTIFS(TableBOM[Product ID],$D$4,TableBOM[Item ID],$A27)>0)*($H$4>0),$C$4&", ","") & IF((COUNTIFS(TableBOM[Product ID],$D$5,TableBOM[Item ID],$A27)>0)*($H$5>0),$C$5&", ","") & IF((COUNTIFS(TableBOM[Product ID],$D$6,TableBOM[Item ID],$A27)>0)*($H$6>0),$C$6&", ","") & IF((COUNTIFS(TableBOM[Product ID],$D$7,TableBOM[Item ID],$A27)>0)*($H$7>0),$C$7&", ","") & IF((COUNTIFS(TableBOM[Product ID],$D$8,TableBOM[Item ID],$A27)>0)*($H$8>0),$C$8&", ",""))>1,LEFT(IF((COUNTIFS(TableBOM[Product ID],$D$3,TableBOM[Item ID],$A27)>0)*($H$3>0),$C$3&", ","") & IF((COUNTIFS(TableBOM[Product ID],$D$4,TableBOM[Item ID],$A27)>0)*($H$4>0),$C$4&", ","") & IF((COUNTIFS(TableBOM[Product ID],$D$5,TableBOM[Item ID],$A27)>0)*($H$5>0),$C$5&", ","") & IF((COUNTIFS(TableBOM[Product ID],$D$6,TableBOM[Item ID],$A27)>0)*($H$6>0),$C$6&", ","") & IF((COUNTIFS(TableBOM[Product ID],$D$7,TableBOM[Item ID],$A27)>0)*($H$7>0),$C$7&", ","") & IF((COUNTIFS(TableBOM[Product ID],$D$8,TableBOM[Item ID],$A27)>0)*($H$8>0),$C$8&", ",""),LEN(IF((COUNTIFS(TableBOM[Product ID],$D$3,TableBOM[Item ID],$A27)>0)*($H$3>0),$C$3&", ","") & IF((COUNTIFS(TableBOM[Product ID],$D$4,TableBOM[Item ID],$A27)>0)*($H$4>0),$C$4&", ","") & IF((COUNTIFS(TableBOM[Product ID],$D$5,TableBOM[Item ID],$A27)>0)*($H$5>0),$C$5&", ","") & IF((COUNTIFS(TableBOM[Product ID],$D$6,TableBOM[Item ID],$A27)>0)*($H$6>0),$C$6&", ","") & IF((COUNTIFS(TableBOM[Product ID],$D$7,TableBOM[Item ID],$A27)>0)*($H$7>0),$C$7&", ","") & IF((COUNTIFS(TableBOM[Product ID],$D$8,TableBOM[Item ID],$A27)>0)*($H$8>0),$C$8&", ",""))-2),"") -> ECZEMUS OINTMENT 0.03% 10G, S-45, S 43 25MM | I27: =IF(E27=0,"Not needed",IF(G27<0,"SHORTAGE",IF(G27<F27*0.1,"LOW","OK"))) -> SHORTAGE
A28: 188 | B28: LACQUER | C28: LACQUER RHENANIA (ACTEGA COLL 299) | D28: kg | E28: =SUMPRODUCT((TableBOM[Item ID]=A28)*TableBOM[Per 1000 Units]*(1+TableBOM[Scrap %])*SUMIF($D$3:$D$8,TableBOM[Product ID],$H$3:$H$8)/1000) -> 0 | F28: =IFERROR(INDEX(TableInventory[Store Balance],MATCH(A28,TableInventory[Item ID],0)),0)+IFERROR(INDEX(TableInventory[Work In Process],MATCH(A28,TableInventory[Item ID],0)),0) -> 91 | G28: =F28-E28 -> 91 | H28: =IF(LEN(IF((COUNTIFS(TableBOM[Product ID],$D$3,TableBOM[Item ID],$A28)>0)*($H$3>0),$C$3&", ","") & IF((COUNTIFS(TableBOM[Product ID],$D$4,TableBOM[Item ID],$A28)>0)*($H$4>0),$C$4&", ","") & IF((COUNTIFS(TableBOM[Product ID],$D$5,TableBOM[Item ID],$A28)>0)*($H$5>0),$C$5&", ","") & IF((COUNTIFS(TableBOM[Product ID],$D$6,TableBOM[Item ID],$A28)>0)*($H$6>0),$C$6&", ","") & IF((COUNTIFS(TableBOM[Product ID],$D$7,TableBOM[Item ID],$A28)>0)*($H$7>0),$C$7&", ","") & IF((COUNTIFS(TableBOM[Product ID],$D$8,TableBOM[Item ID],$A28)>0)*($H$8>0),$C$8&", ",""))>1,LEFT(IF((COUNTIFS(TableBOM[Product ID],$D$3,TableBOM[Item ID],$A28)>0)*($H$3>0),$C$3&", ","") & IF((COUNTIFS(TableBOM[Product ID],$D$4,TableBOM[Item ID],$A28)>0)*($H$4>0),$C$4&", ","") & IF((COUNTIFS(TableBOM[Product ID],$D$5,TableBOM[Item ID],$A28)>0)*($H$5>0),$C$5&", ","") & IF((COUNTIFS(TableBOM[Product ID],$D$6,TableBOM[Item ID],$A28)>0)*($H$6>0),$C$6&", ","") & IF((COUNTIFS(TableBOM[Product ID],$D$7,TableBOM[Item ID],$A28)>0)*($H$7>0),$C$7&", ","") & IF((COUNTIFS(TableBOM[Product ID],$D$8,TableBOM[Item ID],$A28)>0)*($H$8>0),$C$8&", ",""),LEN(IF((COUNTIFS(TableBOM[Product ID],$D$3,TableBOM[Item ID],$A28)>0)*($H$3>0),$C$3&", ","") & IF((COUNTIFS(TableBOM[Product ID],$D$4,TableBOM[Item ID],$A28)>0)*($H$4>0),$C$4&", ","") & IF((COUNTIFS(TableBOM[Product ID],$D$5,TableBOM[Item ID],$A28)>0)*($H$5>0),$C$5&", ","") & IF((COUNTIFS(TableBOM[Product ID],$D$6,TableBOM[Item ID],$A28)>0)*($H$6>0),$C$6&", ","") & IF((COUNTIFS(TableBOM[Product ID],$D$7,TableBOM[Item ID],$A28)>0)*($H$7>0),$C$7&", ","") & IF((COUNTIFS(TableBOM[Product ID],$D$8,TableBOM[Item ID],$A28)>0)*($H$8>0),$C$8&", ",""))-2),"") | I28: =IF(E28=0,"Not needed",IF(G28<0,"SHORTAGE",IF(G28<F28*0.1,"LOW","OK"))) -> Not needed
A29: 1065 | B29: LACQUER | C29: PIGMENTED LACQUER 57300 | D29: kg | E29: =SUMPRODUCT((TableBOM[Item ID]=A29)*TableBOM[Per 1000 Units]*(1+TableBOM[Scrap %])*SUMIF($D$3:$D$8,TableBOM[Product ID],$H$3:$H$8)/1000) -> 0 | F29: =IFERROR(INDEX(TableInventory[Store Balance],MATCH(A29,TableInventory[Item ID],0)),0)+IFERROR(INDEX(TableInventory[Work In Process],MATCH(A29,TableInventory[Item ID],0)),0) -> 0 | G29: =F29-E29 -> 0 | H29: =IF(LEN(IF((COUNTIFS(TableBOM[Product ID],$D$3,TableBOM[Item ID],$A29)>0)*($H$3>0),$C$3&", ","") & IF((COUNTIFS(TableBOM[Product ID],$D$4,TableBOM[Item ID],$A29)>0)*($H$4>0),$C$4&", ","") & IF((COUNTIFS(TableBOM[Product ID],$D$5,TableBOM[Item ID],$A29)>0)*($H$5>0),$C$5&", ","") & IF((COUNTIFS(TableBOM[Product ID],$D$6,TableBOM[Item ID],$A29)>0)*($H$6>0),$C$6&", ","") & IF((COUNTIFS(TableBOM[Product ID],$D$7,TableBOM[Item ID],$A29)>0)*($H$7>0),$C$7&", ","") & IF((COUNTIFS(TableBOM[Product ID],$D$8,TableBOM[Item ID],$A29)>0)*($H$8>0),$C$8&", ",""))>1,LEFT(IF((COUNTIFS(TableBOM[Product ID],$D$3,TableBOM[Item ID],$A29)>0)*($H$3>0),$C$3&", ","") & IF((COUNTIFS(TableBOM[Product ID],$D$4,TableBOM[Item ID],$A29)>0)*($H$4>0),$C$4&", ","") & IF((COUNTIFS(TableBOM[Product ID],$D$5,TableBOM[Item ID],$A29)>0)*($H$5>0),$C$5&", ","") & IF((COUNTIFS(TableBOM[Product ID],$D$6,TableBOM[Item ID],$A29)>0)*($H$6>0),$C$6&", ","") & IF((COUNTIFS(TableBOM[Product ID],$D$7,TableBOM[Item ID],$A29)>0)*($H$7>0),$C$7&", ","") & IF((COUNTIFS(TableBOM[Product ID],$D$8,TableBOM[Item ID],$A29)>0)*($H$8>0),$C$8&", ",""),LEN(IF((COUNTIFS(TableBOM[Product ID],$D$3,TableBOM[Item ID],$A29)>0)*($H$3>0),$C$3&", ","") & IF((COUNTIFS(TableBOM[Product ID],$D$4,TableBOM[Item ID],$A29)>0)*($H$4>0),$C$4&", ","") & IF((COUNTIFS(TableBOM[Product ID],$D$5,TableBOM[Item ID],$A29)>0)*($H$5>0),$C$5&", ","") & IF((COUNTIFS(TableBOM[Product ID],$D$6,TableBOM[Item ID],$A29)>0)*($H$6>0),$C$6&", ","") & IF((COUNTIFS(TableBOM[Product ID],$D$7,TableBOM[Item ID],$A29)>0)*($H$7>0),$C$7&", ","") & IF((COUNTIFS(TableBOM[Product ID],$D$8,TableBOM[Item ID],$A29)>0)*($H$8>0),$C$8&", ",""))-2),"") | I29: =IF(E29=0,"Not needed",IF(G29<0,"SHORTAGE",IF(G29<F29*0.1,"LOW","OK"))) -> Not needed
A30: 4155 | B30: LACQUER | C30: E/P LACQUER 4000 A/R | D30: kg | E30: =SUMPRODUCT((TableBOM[Item ID]=A30)*TableBOM[Per 1000 Units]*(1+TableBOM[Scrap %])*SUMIF($D$3:$D$8,TableBOM[Product ID],$H$3:$H$8)/1000) -> 43.361956 | F30: =IFERROR(INDEX(TableInventory[Store Balance],MATCH(A30,TableInventory[Item ID],0)),0)+IFERROR(INDEX(TableInventory[Work In Process],MATCH(A30,TableInventory[Item ID],0)),0) -> 125 | G30: =F30-E30 -> 81.638044 | H30: =IF(LEN(IF((COUNTIFS(TableBOM[Product ID],$D$3,TableBOM[Item ID],$A30)>0)*($H$3>0),$C$3&", ","") & IF((COUNTIFS(TableBOM[Product ID],$D$4,TableBOM[Item ID],$A30)>0)*($H$4>0),$C$4&", ","") & IF((COUNTIFS(TableBOM[Product ID],$D$5,TableBOM[Item ID],$A30)>0)*($H$5>0),$C$5&", ","") & IF((COUNTIFS(TableBOM[Product ID],$D$6,TableBOM[Item ID],$A30)>0)*($H$6>0),$C$6&", ","") & IF((COUNTIFS(TableBOM[Product ID],$D$7,TableBOM[Item ID],$A30)>0)*($H$7>0),$C$7&", ","") & IF((COUNTIFS(TableBOM[Product ID],$D$8,TableBOM[Item ID],$A30)>0)*($H$8>0),$C$8&", ",""))>1,LEFT(IF((COUNTIFS(TableBOM[Product ID],$D$3,TableBOM[Item ID],$A30)>0)*($H$3>0),$C$3&", ","") & IF((COUNTIFS(TableBOM[Product ID],$D$4,TableBOM[Item ID],$A30)>0)*($H$4>0),$C$4&", ","") & IF((COUNTIFS(TableBOM[Product ID],$D$5,TableBOM[Item ID],$A30)>0)*($H$5>0),$C$5&", ","") & IF((COUNTIFS(TableBOM[Product ID],$D$6,TableBOM[Item ID],$A30)>0)*($H$6>0),$C$6&", ","") & IF((COUNTIFS(TableBOM[Product ID],$D$7,TableBOM[Item ID],$A30)>0)*($H$7>0),$C$7&", ","") & IF((COUNTIFS(TableBOM[Product ID],$D$8,TableBOM[Item ID],$A30)>0)*($H$8>0),$C$8&", ",""),LEN(IF((COUNTIFS(TableBOM[Product ID],$D$3,TableBOM[Item ID],$A30)>0)*($H$3>0),$C$3&", ","") & IF((COUNTIFS(TableBOM[Product ID],$D$4,TableBOM[Item ID],$A30)>0)*($H$4>0),$C$4&", ","") & IF((COUNTIFS(TableBOM[Product ID],$D$5,TableBOM[Item ID],$A30)>0)*($H$5>0),$C$5&", ","") & IF((COUNTIFS(TableBOM[Product ID],$D$6,TableBOM[Item ID],$A30)>0)*($H$6>0),$C$6&", ","") & IF((COUNTIFS(TableBOM[Product ID],$D$7,TableBOM[Item ID],$A30)>0)*($H$7>0),$C$7&", ","") & IF((COUNTIFS(TableBOM[Product ID],$D$8,TableBOM[Item ID],$A30)>0)*($H$8>0),$C$8&", ",""))-2),"") -> VINCE NURTURAL, HELLO HAIR COLOR, V- HC BROWN | I30: =IF(E30=0,"Not needed",IF(G30<0,"SHORTAGE",IF(G30<F30*0.1,"LOW","OK"))) -> OK
A31: 170 | B31: BASE COAT | C31: WHITE 5711200001 | D31: kg | E31: =SUMPRODUCT((TableBOM[Item ID]=A31)*TableBOM[Per 1000 Units]*(1+TableBOM[Scrap %])*SUMIF($D$3:$D$8,TableBOM[Product ID],$H$3:$H$8)/1000) -> 0 | F31: =IFERROR(INDEX(TableInventory[Store Balance],MATCH(A31,TableInventory[Item ID],0)),0)+IFERROR(INDEX(TableInventory[Work In Process],MATCH(A31,TableInventory[Item ID],0)),0) -> 0 | G31: =F31-E31 -> 0 | H31: =IF(LEN(IF((COUNTIFS(TableBOM[Product ID],$D$3,TableBOM[Item ID],$A31)>0)*($H$3>0),$C$3&", ","") & IF((COUNTIFS(TableBOM[Product ID],$D$4,TableBOM[Item ID],$A31)>0)*($H$4>0),$C$4&", ","") & IF((COUNTIFS(TableBOM[Product ID],$D$5,TableBOM[Item ID],$A31)>0)*($H$5>0),$C$5&", ","") & IF((COUNTIFS(TableBOM[Product ID],$D$6,TableBOM[Item ID],$A31)>0)*($H$6>0),$C$6&", ","") & IF((COUNTIFS(TableBOM[Product ID],$D$7,TableBOM[Item ID],$A31)>0)*($H$7>0),$C$7&", ","") & IF((COUNTIFS(TableBOM[Product ID],$D$8,TableBOM[Item ID],$A31)>0)*($H$8>0),$C$8&", ",""))>1,LEFT(IF((COUNTIFS(TableBOM[Product ID],$D$3,TableBOM[Item ID],$A31)>0)*($H$3>0),$C$3&", ","") & IF((COUNTIFS(TableBOM[Product ID],$D$4,TableBOM[Item ID],$A31)>0)*($H$4>0),$C$4&", ","") & IF((COUNTIFS(TableBOM[Product ID],$D$5,TableBOM[Item ID],$A31)>0)*($H$5>0),$C$5&", ","") & IF((COUNTIFS(TableBOM[Product ID],$D$6,TableBOM[Item ID],$A31)>0)*($H$6>0),$C$6&", ","") & IF((COUNTIFS(TableBOM[Product ID],$D$7,TableBOM[Item ID],$A31)>0)*($H$7>0),$C$7&", ","") & IF((COUNTIFS(TableBOM[Product ID],$D$8,TableBOM[Item ID],$A31)>0)*($H$8>0),$C$8&", ",""),LEN(IF((COUNTIFS(TableBOM[Product ID],$D$3,TableBOM[Item ID],$A31)>0)*($H$3>0),$C$3&", ","") & IF((COUNTIFS(TableBOM[Product ID],$D$4,TableBOM[Item ID],$A31)>0)*($H$4>0),$C$4&", ","") & IF((COUNTIFS(TableBOM[Product ID],$D$5,TableBOM[Item ID],$A31)>0)*($H$5>0),$C$5&", ","") & IF((COUNTIFS(TableBOM[Product ID],$D$6,TableBOM[Item ID],$A31)>0)*($H$6>0),$C$6&", ","") & IF((COUNTIFS(TableBOM[Product ID],$D$7,TableBOM[Item ID],$A31)>0)*($H$7>0),$C$7&", ","") & IF((COUNTIFS(TableBOM[Product ID],$D$8,TableBOM[Item ID],$A31)>0)*($H$8>0),$C$8&", ",""))-2),"") | I31: =IF(E31=0,"Not needed",IF(G31<0,"SHORTAGE",IF(G31<F31*0.1,"LOW","OK"))) -> Not needed
A32: 175 | B32: BASE COAT | C32: GOLD 5725100018 | D32: kg | E32: =SUMPRODUCT((TableBOM[Item ID]=A32)*TableBOM[Per 1000 Units]*(1+TableBOM[Scrap %])*SUMIF($D$3:$D$8,TableBOM[Product ID],$H$3:$H$8)/1000) -> 0 | F32: =IFERROR(INDEX(TableInventory[Store Balance],MATCH(A32,TableInventory[Item ID],0)),0)+IFERROR(INDEX(TableInventory[Work In Process],MATCH(A32,TableInventory[Item ID],0)),0) -> 30 | G32: =F32-E32 -> 30 | H32: =IF(LEN(IF((COUNTIFS(TableBOM[Product ID],$D$3,TableBOM[Item ID],$A32)>0)*($H$3>0),$C$3&", ","") & IF((COUNTIFS(TableBOM[Product ID],$D$4,TableBOM[Item ID],$A32)>0)*($H$4>0),$C$4&", ","") & IF((COUNTIFS(TableBOM[Product ID],$D$5,TableBOM[Item ID],$A32)>0)*($H$5>0),$C$5&", ","") & IF((COUNTIFS(TableBOM[Product ID],$D$6,TableBOM[Item ID],$A32)>0)*($H$6>0),$C$6&", ","") & IF((COUNTIFS(TableBOM[Product ID],$D$7,TableBOM[Item ID],$A32)>0)*($H$7>0),$C$7&", ","") & IF((COUNTIFS(TableBOM[Product ID],$D$8,TableBOM[Item ID],$A32)>0)*($H$8>0),$C$8&", ",""))>1,LEFT(IF((COUNTIFS(TableBOM[Product ID],$D$3,TableBOM[Item ID],$A32)>0)*($H$3>0),$C$3&", ","") & IF((COUNTIFS(TableBOM[Product ID],$D$4,TableBOM[Item ID],$A32)>0)*($H$4>0),$C$4&", ","") & IF((COUNTIFS(TableBOM[Product ID],$D$5,TableBOM[Item ID],$A32)>0)*($H$5>0),$C$5&", ","") & IF((COUNTIFS(TableBOM[Product ID],$D$6,TableBOM[Item ID],$A32)>0)*($H$6>0),$C$6&", ","") & IF((COUNTIFS(TableBOM[Product ID],$D$7,TableBOM[Item ID],$A32)>0)*($H$7>0),$C$7&", ","") & IF((COUNTIFS(TableBOM[Product ID],$D$8,TableBOM[Item ID],$A32)>0)*($H$8>0),$C$8&", ",""),LEN(IF((COUNTIFS(TableBOM[Product ID],$D$3,TableBOM[Item ID],$A32)>0)*($H$3>0),$C$3&", ","") & IF((COUNTIFS(TableBOM[Product ID],$D$4,TableBOM[Item ID],$A32)>0)*($H$4>0),$C$4&", ","") & IF((COUNTIFS(TableBOM[Product ID],$D$5,TableBOM[Item ID],$A32)>0)*($H$5>0),$C$5&", ","") & IF((COUNTIFS(TableBOM[Product ID],$D$6,TableBOM[Item ID],$A32)>0)*($H$6>0),$C$6&", ","") & IF((COUNTIFS(TableBOM[Product ID],$D$7,TableBOM[Item ID],$A32)>0)*($H$7>0),$C$7&", ","") & IF((COUNTIFS(TableBOM[Product ID],$D$8,TableBOM[Item ID],$A32)>0)*($H$8>0),$C$8&", ",""))-2),"") | I32: =IF(E32=0,"Not needed",IF(G32<0,"SHORTAGE",IF(G32<F32*0.1,"LOW","OK"))) -> Not needed
A33: 192 | B33: BASE COAT | C33: TRANSPARENT 234-786 | D33: kg | E33: =SUMPRODUCT((TableBOM[Item ID]=A33)*TableBOM[Per 1000 Units]*(1+TableBOM[Scrap %])*SUMIF($D$3:$D$8,TableBOM[Product ID],$H$3:$H$8)/1000) -> 0 | F33: =IFERROR(INDEX(TableInventory[Store Balance],MATCH(A33,TableInventory[Item ID],0)),0)+IFERROR(INDEX(TableInventory[Work In Process],MATCH(A33,TableInventory[Item ID],0)),0) -> 50 | G33: =F33-E33 -> 50 | H33: =IF(LEN(IF((COUNTIFS(TableBOM[Product ID],$D$3,TableBOM[Item ID],$A33)>0)*($H$3>0),$C$3&", ","") & IF((COUNTIFS(TableBOM[Product ID],$D$4,TableBOM[Item ID],$A33)>0)*($H$4>0),$C$4&", ","") & IF((COUNTIFS(TableBOM[Product ID],$D$5,TableBOM[Item ID],$A33)>0)*($H$5>0),$C$5&", ","") & IF((COUNTIFS(TableBOM[Product ID],$D$6,TableBOM[Item ID],$A33)>0)*($H$6>0),$C$6&", ","") & IF((COUNTIFS(TableBOM[Product ID],$D$7,TableBOM[Item ID],$A33)>0)*($H$7>0),$C$7&", ","") & IF((COUNTIFS(TableBOM[Product ID],$D$8,TableBOM[Item ID],$A33)>0)*($H$8>0),$C$8&", ",""))>1,LEFT(IF((COUNTIFS(TableBOM[Product ID],$D$3,TableBOM[Item ID],$A33)>0)*($H$3>0),$C$3&", ","") & IF((COUNTIFS(TableBOM[Product ID],$D$4,TableBOM[Item ID],$A33)>0)*($H$4>0),$C$4&", ","") & IF((COUNTIFS(TableBOM[Product ID],$D$5,TableBOM[Item ID],$A33)>0)*($H$5>0),$C$5&", ","") & IF((COUNTIFS(TableBOM[Product ID],$D$6,TableBOM[Item ID],$A33)>0)*($H$6>0),$C$6&", ","") & IF((COUNTIFS(TableBOM[Product ID],$D$7,TableBOM[Item ID],$A33)>0)*($H$7>0),$C$7&", ","") & IF((COUNTIFS(TableBOM[Product ID],$D$8,TableBOM[Item ID],$A33)>0)*($H$8>0),$C$8&", ",""),LEN(IF((COUNTIFS(TableBOM[Product ID],$D$3,TableBOM[Item ID],$A33)>0)*($H$3>0),$C$3&", ","") & IF((COUNTIFS(TableBOM[Product ID],$D$4,TableBOM[Item ID],$A33)>0)*($H$4>0),$C$4&", ","") & IF((COUNTIFS(TableBOM[Product ID],$D$5,TableBOM[Item ID],$A33)>0)*($H$5>0),$C$5&", ","") & IF((COUNTIFS(TableBOM[Product ID],$D$6,TableBOM[Item ID],$A33)>0)*($H$6>0),$C$6&", ","") & IF((COUNTIFS(TableBOM[Product ID],$D$7,TableBOM[Item ID],$A33)>0)*($H$7>0),$C$7&", ","") & IF((COUNTIFS(TableBOM[Product ID],$D$8,TableBOM[Item ID],$A33)>0)*($H$8>0),$C$8&", ",""))-2),"") | I33: =IF(E33=0,"Not needed",IF(G33<0,"SHORTAGE",IF(G33<F33*0.1,"LOW","OK"))) -> Not needed
A34: 3595 | B34: BASE COAT | C34: POLYSTER BASE COAT WHITE 23410 | D34: kg | E34: =SUMPRODUCT((TableBOM[Item ID]=A34)*TableBOM[Per 1000 Units]*(1+TableBOM[Scrap %])*SUMIF($D$3:$D$8,TableBOM[Product ID],$H$3:$H$8)/1000) -> 229.55959 | F34: =IFERROR(INDEX(TableInventory[Store Balance],MATCH(A34,TableInventory[Item ID],0)),0)+IFERROR(INDEX(TableInventory[Work In Process],MATCH(A34,TableInventory[Item ID],0)),0) -> 150 | G34: =F34-E34 -> -79.559594 | H34: =IF(LEN(IF((COUNTIFS(TableBOM[Product ID],$D$3,TableBOM[Item ID],$A34)>0)*($H$3>0),$C$3&", ","") & IF((COUNTIFS(TableBOM[Product ID],$D$4,TableBOM[Item ID],$A34)>0)*($H$4>0),$C$4&", ","") & IF((COUNTIFS(TableBOM[Product ID],$D$5,TableBOM[Item ID],$A34)>0)*($H$5>0),$C$5&", ","") & IF((COUNTIFS(TableBOM[Product ID],$D$6,TableBOM[Item ID],$A34)>0)*($H$6>0),$C$6&", ","") & IF((COUNTIFS(TableBOM[Product ID],$D$7,TableBOM[Item ID],$A34)>0)*($H$7>0),$C$7&", ","") & IF((COUNTIFS(TableBOM[Product ID],$D$8,TableBOM[Item ID],$A34)>0)*($H$8>0),$C$8&", ",""))>1,LEFT(IF((COUNTIFS(TableBOM[Product ID],$D$3,TableBOM[Item ID],$A34)>0)*($H$3>0),$C$3&", ","") & IF((COUNTIFS(TableBOM[Product ID],$D$4,TableBOM[Item ID],$A34)>0)*($H$4>0),$C$4&", ","") & IF((COUNTIFS(TableBOM[Product ID],$D$5,TableBOM[Item ID],$A34)>0)*($H$5>0),$C$5&", ","") & IF((COUNTIFS(TableBOM[Product ID],$D$6,TableBOM[Item ID],$A34)>0)*($H$6>0),$C$6&", ","") & IF((COUNTIFS(TableBOM[Product ID],$D$7,TableBOM[Item ID],$A34)>0)*($H$7>0),$C$7&", ","") & IF((COUNTIFS(TableBOM[Product ID],$D$8,TableBOM[Item ID],$A34)>0)*($H$8>0),$C$8&", ",""),LEN(IF((COUNTIFS(TableBOM[Product ID],$D$3,TableBOM[Item ID],$A34)>0)*($H$3>0),$C$3&", ","") & IF((COUNTIFS(TableBOM[Product ID],$D$4,TableBOM[Item ID],$A34)>0)*($H$4>0),$C$4&", ","") & IF((COUNTIFS(TableBOM[Product ID],$D$5,TableBOM[Item ID],$A34)>0)*($H$5>0),$C$5&", ","") & IF((COUNTIFS(TableBOM[Product ID],$D$6,TableBOM[Item ID],$A34)>0)*($H$6>0),$C$6&", ","") & IF((COUNTIFS(TableBOM[Product ID],$D$7,TableBOM[Item ID],$A34)>0)*($H$7>0),$C$7&", ","") & IF((COUNTIFS(TableBOM[Product ID],$D$8,TableBOM[Item ID],$A34)>0)*($H$8>0),$C$8&", ",""))-2),"") -> ECZEMUS OINTMENT 0.03% 10G, S-45, S 43 25MM, VINCE NURTURAL, HELLO HAIR COLOR, V- HC BROWN | I34: =IF(E34=0,"Not needed",IF(G34<0,"SHORTAGE",IF(G34<F34*0.1,"LOW","OK"))) -> SHORTAGE
A35: 3869 | B35: BASE COAT | C35: POLYESTER BASE COAT BEIGE 234-999 | D35: kg | E35: =SUMPRODUCT((TableBOM[Item ID]=A35)*TableBOM[Per 1000 Units]*(1+TableBOM[Scrap %])*SUMIF($D$3:$D$8,TableBOM[Product ID],$H$3:$H$8)/1000) -> 0 | F35: =IFERROR(INDEX(TableInventory[Store Balance],MATCH(A35,TableInventory[Item ID],0)),0)+IFERROR(INDEX(TableInventory[Work In Process],MATCH(A35,TableInventory[Item ID],0)),0) -> 60 | G35: =F35-E35 -> 60 | H35: =IF(LEN(IF((COUNTIFS(TableBOM[Product ID],$D$3,TableBOM[Item ID],$A35)>0)*($H$3>0),$C$3&", ","") & IF((COUNTIFS(TableBOM[Product ID],$D$4,TableBOM[Item ID],$A35)>0)*($H$4>0),$C$4&", ","") & IF((COUNTIFS(TableBOM[Product ID],$D$5,TableBOM[Item ID],$A35)>0)*($H$5>0),$C$5&", ","") & IF((COUNTIFS(TableBOM[Product ID],$D$6,TableBOM[Item ID],$A35)>0)*($H$6>0),$C$6&", ","") & IF((COUNTIFS(TableBOM[Product ID],$D$7,TableBOM[Item ID],$A35)>0)*($H$7>0),$C$7&", ","") & IF((COUNTIFS(TableBOM[Product ID],$D$8,TableBOM[Item ID],$A35)>0)*($H$8>0),$C$8&", ",""))>1,LEFT(IF((COUNTIFS(TableBOM[Product ID],$D$3,TableBOM[Item ID],$A35)>0)*($H$3>0),$C$3&", ","") & IF((COUNTIFS(TableBOM[Product ID],$D$4,TableBOM[Item ID],$A35)>0)*($H$4>0),$C$4&", ","") & IF((COUNTIFS(TableBOM[Product ID],$D$5,TableBOM[Item ID],$A35)>0)*($H$5>0),$C$5&", ","") & IF((COUNTIFS(TableBOM[Product ID],$D$6,TableBOM[Item ID],$A35)>0)*($H$6>0),$C$6&", ","") & IF((COUNTIFS(TableBOM[Product ID],$D$7,TableBOM[Item ID],$A35)>0)*($H$7>0),$C$7&", ","") & IF((COUNTIFS(TableBOM[Product ID],$D$8,TableBOM[Item ID],$A35)>0)*($H$8>0),$C$8&", ",""),LEN(IF((COUNTIFS(TableBOM[Product ID],$D$3,TableBOM[Item ID],$A35)>0)*($H$3>0),$C$3&", ","") & IF((COUNTIFS(TableBOM[Product ID],$D$4,TableBOM[Item ID],$A35)>0)*($H$4>0),$C$4&", ","") & IF((COUNTIFS(TableBOM[Product ID],$D$5,TableBOM[Item ID],$A35)>0)*($H$5>0),$C$5&", ","") & IF((COUNTIFS(TableBOM[Product ID],$D$6,TableBOM[Item ID],$A35)>0)*($H$6>0),$C$6&", ","") & IF((COUNTIFS(TableBOM[Product ID],$D$7,TableBOM[Item ID],$A35)>0)*($H$7>0),$C$7&", ","") & IF((COUNTIFS(TableBOM[Product ID],$D$8,TableBOM[Item ID],$A35)>0)*($H$8>0),$C$8&", ",""))-2),"") | I35: =IF(E35=0,"Not needed",IF(G35<0,"SHORTAGE",IF(G35<F35*0.1,"LOW","OK"))) -> Not needed
A36: 4156 | B36: BASE COAT | C36: BEIGE 5711200007 | D36: kg | E36: =SUMPRODUCT((TableBOM[Item ID]=A36)*TableBOM[Per 1000 Units]*(1+TableBOM[Scrap %])*SUMIF($D$3:$D$8,TableBOM[Product ID],$H$3:$H$8)/1000) -> 0 | F36: =IFERROR(INDEX(TableInventory[Store Balance],MATCH(A36,TableInventory[Item ID],0)),0)+IFERROR(INDEX(TableInventory[Work In Process],MATCH(A36,TableInventory[Item ID],0)),0) -> 0 | G36: =F36-E36 -> 0 | H36: =IF(LEN(IF((COUNTIFS(TableBOM[Product ID],$D$3,TableBOM[Item ID],$A36)>0)*($H$3>0),$C$3&", ","") & IF((COUNTIFS(TableBOM[Product ID],$D$4,TableBOM[Item ID],$A36)>0)*($H$4>0),$C$4&", ","") & IF((COUNTIFS(TableBOM[Product ID],$D$5,TableBOM[Item ID],$A36)>0)*($H$5>0),$C$5&", ","") & IF((COUNTIFS(TableBOM[Product ID],$D$6,TableBOM[Item ID],$A36)>0)*($H$6>0),$C$6&", ","") & IF((COUNTIFS(TableBOM[Product ID],$D$7,TableBOM[Item ID],$A36)>0)*($H$7>0),$C$7&", ","") & IF((COUNTIFS(TableBOM[Product ID],$D$8,TableBOM[Item ID],$A36)>0)*($H$8>0),$C$8&", ",""))>1,LEFT(IF((COUNTIFS(TableBOM[Product ID],$D$3,TableBOM[Item ID],$A36)>0)*($H$3>0),$C$3&", ","") & IF((COUNTIFS(TableBOM[Product ID],$D$4,TableBOM[Item ID],$A36)>0)*($H$4>0),$C$4&", ","") & IF((COUNTIFS(TableBOM[Product ID],$D$5,TableBOM[Item ID],$A36)>0)*($H$5>0),$C$5&", ","") & IF((COUNTIFS(TableBOM[Product ID],$D$6,TableBOM[Item ID],$A36)>0)*($H$6>0),$C$6&", ","") & IF((COUNTIFS(TableBOM[Product ID],$D$7,TableBOM[Item ID],$A36)>0)*($H$7>0),$C$7&", ","") & IF((COUNTIFS(TableBOM[Product ID],$D$8,TableBOM[Item ID],$A36)>0)*($H$8>0),$C$8&", ",""),LEN(IF((COUNTIFS(TableBOM[Product ID],$D$3,TableBOM[Item ID],$A36)>0)*($H$3>0),$C$3&", ","") & IF((COUNTIFS(TableBOM[Product ID],$D$4,TableBOM[Item ID],$A36)>0)*($H$4>0),$C$4&", ","") & IF((COUNTIFS(TableBOM[Product ID],$D$5,TableBOM[Item ID],$A36)>0)*($H$5>0),$C$5&", ","") & IF((COUNTIFS(TableBOM[Product ID],$D$6,TableBOM[Item ID],$A36)>0)*($H$6>0),$C$6&", ","") & IF((COUNTIFS(TableBOM[Product ID],$D$7,TableBOM[Item ID],$A36)>0)*($H$7>0),$C$7&", ","") & IF((COUNTIFS(TableBOM[Product ID],$D$8,TableBOM[Item ID],$A36)>0)*($H$8>0),$C$8&", ",""))-2),"") | I36: =IF(E36=0,"Not needed",IF(G36<0,"SHORTAGE",IF(G36<F36*0.1,"LOW","OK"))) -> Not needed
A37: 4157 | B37: BASE COAT | C37: SILVER METALLIC 5725100011 | D37: kg | E37: =SUMPRODUCT((TableBOM[Item ID]=A37)*TableBOM[Per 1000 Units]*(1+TableBOM[Scrap %])*SUMIF($D$3:$D$8,TableBOM[Product ID],$H$3:$H$8)/1000) -> 0 | F37: =IFERROR(INDEX(TableInventory[Store Balance],MATCH(A37,TableInventory[Item ID],0)),0)+IFERROR(INDEX(TableInventory[Work In Process],MATCH(A37,TableInventory[Item ID],0)),0) -> 240 | G37: =F37-E37 -> 240 | H37: =IF(LEN(IF((COUNTIFS(TableBOM[Product ID],$D$3,TableBOM[Item ID],$A37)>0)*($H$3>0),$C$3&", ","") & IF((COUNTIFS(TableBOM[Product ID],$D$4,TableBOM[Item ID],$A37)>0)*($H$4>0),$C$4&", ","") & IF((COUNTIFS(TableBOM[Product ID],$D$5,TableBOM[Item ID],$A37)>0)*($H$5>0),$C$5&", ","") & IF((COUNTIFS(TableBOM[Product ID],$D$6,TableBOM[Item ID],$A37)>0)*($H$6>0),$C$6&", ","") & IF((COUNTIFS(TableBOM[Product ID],$D$7,TableBOM[Item ID],$A37)>0)*($H$7>0),$C$7&", ","") & IF((COUNTIFS(TableBOM[Product ID],$D$8,TableBOM[Item ID],$A37)>0)*($H$8>0),$C$8&", ",""))>1,LEFT(IF((COUNTIFS(TableBOM[Product ID],$D$3,TableBOM[Item ID],$A37)>0)*($H$3>0),$C$3&", ","") & IF((COUNTIFS(TableBOM[Product ID],$D$4,TableBOM[Item ID],$A37)>0)*($H$4>0),$C$4&", ","") & IF((COUNTIFS(TableBOM[Product ID],$D$5,TableBOM[Item ID],$A37)>0)*($H$5>0),$C$5&", ","") & IF((COUNTIFS(TableBOM[Product ID],$D$6,TableBOM[Item ID],$A37)>0)*($H$6>0),$C$6&", ","") & IF((COUNTIFS(TableBOM[Product ID],$D$7,TableBOM[Item ID],$A37)>0)*($H$7>0),$C$7&", ","") & IF((COUNTIFS(TableBOM[Product ID],$D$8,TableBOM[Item ID],$A37)>0)*($H$8>0),$C$8&", ",""),LEN(IF((COUNTIFS(TableBOM[Product ID],$D$3,TableBOM[Item ID],$A37)>0)*($H$3>0),$C$3&", ","") & IF((COUNTIFS(TableBOM[Product ID],$D$4,TableBOM[Item ID],$A37)>0)*($H$4>0),$C$4&", ","") & IF((COUNTIFS(TableBOM[Product ID],$D$5,TableBOM[Item ID],$A37)>0)*($H$5>0),$C$5&", ","") & IF((COUNTIFS(TableBOM[Product ID],$D$6,TableBOM[Item ID],$A37)>0)*($H$6>0),$C$6&", ","") & IF((COUNTIFS(TableBOM[Product ID],$D$7,TableBOM[Item ID],$A37)>0)*($H$7>0),$C$7&", ","") & IF((COUNTIFS(TableBOM[Product ID],$D$8,TableBOM[Item ID],$A37)>0)*($H$8>0),$C$8&", ",""))-2),"") | I37: =IF(E37=0,"Not needed",IF(G37<0,"SHORTAGE",IF(G37<F37*0.1,"LOW","OK"))) -> Not needed
... A44: 4165 | B44: ZINC POWDER | C44: ZINC ARCHIMATE | D44: kg | E44: =SUMPRODUCT((TableBOM[Item ID]=A44)*TableBOM[Per 1000 Units]*(1+TableBOM[Scrap %])*SUMIF($D$3:$D$8,TableBOM[Product ID],$H$3:$H$8)/1000) -> 0 | F44: =IFERROR(INDEX(TableInventory[Store Balance],MATCH(A44,TableInventory[Item ID],0)),0)+IFERROR(INDEX(TableInventory[Work In Process],MATCH(A44,TableInventory[Item ID],0)),0) -> 0 | G44: =F44-E44 -> 0 | H44: =IF(LEN(IF((COUNTIFS(TableBOM[Product ID],$D$3,TableBOM[Item ID],$A44)>0)*($H$3>0),$C$3&", ","") & IF((COUNTIFS(TableBOM[Product ID],$D$4,TableBOM[Item ID],$A44)>0)*($H$4>0),$C$4&", ","") & IF((COUNTIFS(TableBOM[Product ID],$D$5,TableBOM[Item ID],$A44)>0)*($H$5>0),$C$5&", ","") & IF((COUNTIFS(TableBOM[Product ID],$D$6,TableBOM[Item ID],$A44)>0)*($H$6>0),$C$6&", ","") & IF((COUNTIFS(TableBOM[Product ID],$D$7,TableBOM[Item ID],$A44)>0)*($H$7>0),$C$7&", ","") & IF((COUNTIFS(TableBOM[Product ID],$D$8,TableBOM[Item ID],$A44)>0)*($H$8>0),$C$8&", ",""))>1,LEFT(IF((COUNTIFS(TableBOM[Product ID],$D$3,TableBOM[Item ID],$A44)>0)*($H$3>0),$C$3&", ","") & IF((COUNTIFS(TableBOM[Product ID],$D$4,TableBOM[Item ID],$A44)>0)*($H$4>0),$C$4&", ","") & IF((COUNTIFS(TableBOM[Product ID],$D$5,TableBOM[Item ID],$A44)>0)*($H$5>0),$C$5&", ","") & IF((COUNTIFS(TableBOM[Product ID],$D$6,TableBOM[Item ID],$A44)>0)*($H$6>0),$C$6&", ","") & IF((COUNTIFS(TableBOM[Product ID],$D$7,TableBOM[Item ID],$A44)>0)*($H$7>0),$C$7&", ","") & IF((COUNTIFS(TableBOM[Product ID],$D$8,TableBOM[Item ID],$A44)>0)*($H$8>0),$C$8&", ",""),LEN(IF((COUNTIFS(TableBOM[Product ID],$D$3,TableBOM[Item ID],$A44)>0)*($H$3>0),$C$3&", ","") & IF((COUNTIFS(TableBOM[Product ID],$D$4,TableBOM[Item ID],$A44)>0)*($H$4>0),$C$4&", ","") & IF((COUNTIFS(TableBOM[Product ID],$D$5,TableBOM[Item ID],$A44)>0)*($H$5>0),$C$5&", ","") & IF((COUNTIFS(TableBOM[Product ID],$D$6,TableBOM[Item ID],$A44)>0)*($H$6>0),$C$6&", ","") & IF((COUNTIFS(TableBOM[Product ID],$D$7,TableBOM[Item ID],$A44)>0)*($H$7>0),$C$7&", ","") & IF((COUNTIFS(TableBOM[Product ID],$D$8,TableBOM[Item ID],$A44)>0)*($H$8>0),$C$8&", ",""))-2),"") | I44: =IF(E44=0,"Not needed",IF(G44<0,"SHORTAGE",IF(G44<F44*0.1,"LOW","OK"))) -> Not needed
A45: 69 | B45: CAP | C45: M-7 S/M F/P (S) WHITE | D45: PCS | E45: =SUMPRODUCT((TableBOM[Item ID]=A45)*TableBOM[Per 1000 Units]*(1+TableBOM[Scrap %])*SUMIF($D$3:$D$8,TableBOM[Product ID],$H$3:$H$8)/1000) -> 25500 | F45: =IFERROR(INDEX(TableInventory[Store Balance],MATCH(A45,TableInventory[Item ID],0)),0)+IFERROR(INDEX(TableInventory[Work In Process],MATCH(A45,TableInventory[Item ID],0)),0) -> 0 | G45: =F45-E45 -> -25500 | H45: =IF(LEN(IF((COUNTIFS(TableBOM[Product ID],$D$3,TableBOM[Item ID],$A45)>0)*($H$3>0),$C$3&", ","") & IF((COUNTIFS(TableBOM[Product ID],$D$4,TableBOM[Item ID],$A45)>0)*($H$4>0),$C$4&", ","") & IF((COUNTIFS(TableBOM[Product ID],$D$5,TableBOM[Item ID],$A45)>0)*($H$5>0),$C$5&", ","") & IF((COUNTIFS(TableBOM[Product ID],$D$6,TableBOM[Item ID],$A45)>0)*($H$6>0),$C$6&", ","") & IF((COUNTIFS(TableBOM[Product ID],$D$7,TableBOM[Item ID],$A45)>0)*($H$7>0),$C$7&", ","") & IF((COUNTIFS(TableBOM[Product ID],$D$8,TableBOM[Item ID],$A45)>0)*($H$8>0),$C$8&", ",""))>1,LEFT(IF((COUNTIFS(TableBOM[Product ID],$D$3,TableBOM[Item ID],$A45)>0)*($H$3>0),$C$3&", ","") & IF((COUNTIFS(TableBOM[Product ID],$D$4,TableBOM[Item ID],$A45)>0)*($H$4>0),$C$4&", ","") & IF((COUNTIFS(TableBOM[Product ID],$D$5,TableBOM[Item ID],$A45)>0)*($H$5>0),$C$5&", ","") & IF((COUNTIFS(TableBOM[Product ID],$D$6,TableBOM[Item ID],$A45)>0)*($H$6>0),$C$6&", ","") & IF((COUNTIFS(TableBOM[Product ID],$D$7,TableBOM[Item ID],$A45)>0)*($H$7>0),$C$7&", ","") & IF((COUNTIFS(TableBOM[Product ID],$D$8,TableBOM[Item ID],$A45)>0)*($H$8>0),$C$8&", ",""),LEN(IF((COUNTIFS(TableBOM[Product ID],$D$3,TableBOM[Item ID],$A45)>0)*($H$3>0),$C$3&", ","") & IF((COUNTIFS(TableBOM[Product ID],$D$4,TableBOM[Item ID],$A45)>0)*($H$4>0),$C$4&", ","") & IF((COUNTIFS(TableBOM[Product ID],$D$5,TableBOM[Item ID],$A45)>0)*($H$5>0),$C$5&", ","") & IF((COUNTIFS(TableBOM[Product ID],$D$6,TableBOM[Item ID],$A45)>0)*($H$6>0),$C$6&", ","") & IF((COUNTIFS(TableBOM[Product ID],$D$7,TableBOM[Item ID],$A45)>0)*($H$7>0),$C$7&", ","") & IF((COUNTIFS(TableBOM[Product ID],$D$8,TableBOM[Item ID],$A45)>0)*($H$8>0),$C$8&", ",""))-2),"") -> ECZEMUS OINTMENT 0.03% 10G | I45: Hold. Caps not approved
A46: 99 | B46: CAP | C46: M-7 OPHTHALMIC PINK | D46: PCS | E46: =SUMPRODUCT((TableBOM[Item ID]=A46)*TableBOM[Per 1000 Units]*(1+TableBOM[Scrap %])*SUMIF($D$3:$D$8,TableBOM[Product ID],$H$3:$H$8)/1000) -> 0 | F46: =IFERROR(INDEX(TableInventory[Store Balance],MATCH(A46,TableInventory[Item ID],0)),0)+IFERROR(INDEX(TableInventory[Work In Process],MATCH(A46,TableInventory[Item ID],0)),0) -> 10000 | G46: =F46-E46 -> 10000 | H46: =IF(LEN(IF((COUNTIFS(TableBOM[Product ID],$D$3,TableBOM[Item ID],$A46)>0)*($H$3>0),$C$3&", ","") & IF((COUNTIFS(TableBOM[Product ID],$D$4,TableBOM[Item ID],$A46)>0)*($H$4>0),$C$4&", ","") & IF((COUNTIFS(TableBOM[Product ID],$D$5,TableBOM[Item ID],$A46)>0)*($H$5>0),$C$5&", ","") & IF((COUNTIFS(TableBOM[Product ID],$D$6,TableBOM[Item ID],$A46)>0)*($H$6>0),$C$6&", ","") & IF((COUNTIFS(TableBOM[Product ID],$D$7,TableBOM[Item ID],$A46)>0)*($H$7>0),$C$7&", ","") & IF((COUNTIFS(TableBOM[Product ID],$D$8,TableBOM[Item ID],$A46)>0)*($H$8>0),$C$8&", ",""))>1,LEFT(IF((COUNTIFS(TableBOM[Product ID],$D$3,TableBOM[Item ID],$A46)>0)*($H$3>0),$C$3&", ","") & IF((COUNTIFS(TableBOM[Product ID],$D$4,TableBOM[Item ID],$A46)>0)*($H$4>0),$C$4&", ","") & IF((COUNTIFS(TableBOM[Product ID],$D$5,TableBOM[Item ID],$A46)>0)*($H$5>0),$C$5&", ","") & IF((COUNTIFS(TableBOM[Product ID],$D$6,TableBOM[Item ID],$A46)>0)*($H$6>0),$C$6&", ","") & IF((COUNTIFS(TableBOM[Product ID],$D$7,TableBOM[Item ID],$A46)>0)*($H$7>0),$C$7&", ","") & IF((COUNTIFS(TableBOM[Product ID],$D$8,TableBOM[Item ID],$A46)>0)*($H$8>0),$C$8&", ",""),LEN(IF((COUNTIFS(TableBOM[Product ID],$D$3,TableBOM[Item ID],$A46)>0)*($H$3>0),$C$3&", ","") & IF((COUNTIFS(TableBOM[Product ID],$D$4,TableBOM[Item ID],$A46)>0)*($H$4>0),$C$4&", ","") & IF((COUNTIFS(TableBOM[Product ID],$D$5,TableBOM[Item ID],$A46)>0)*($H$5>0),$C$5&", ","") & IF((COUNTIFS(TableBOM[Product ID],$D$6,TableBOM[Item ID],$A46)>0)*($H$6>0),$C$6&", ","") & IF((COUNTIFS(TableBOM[Product ID],$D$7,TableBOM[Item ID],$A46)>0)*($H$7>0),$C$7&", ","") & IF((COUNTIFS(TableBOM[Product ID],$D$8,TableBOM[Item ID],$A46)>0)*($H$8>0),$C$8&", ",""))-2),"") | I46: =IF(E46=0,"Not needed",IF(G46<0,"SHORTAGE",IF(G46<F46*0.1,"LOW","OK"))) -> Not needed
A47: 72 | B47: CAP | C47: M-9 S/M SPR BLACK DIA 16MM | D47: PCS | E47: =SUMPRODUCT((TableBOM[Item ID]=A47)*TableBOM[Per 1000 Units]*(1+TableBOM[Scrap %])*SUMIF($D$3:$D$8,TableBOM[Product ID],$H$3:$H$8)/1000) -> 0 | F47: =IFERROR(INDEX(TableInventory[Store Balance],MATCH(A47,TableInventory[Item ID],0)),0)+IFERROR(INDEX(TableInventory[Work In Process],MATCH(A47,TableInventory[Item ID],0)),0) -> 23741 | G47: =F47-E47 -> 23741 | H47: =IF(LEN(IF((COUNTIFS(TableBOM[Product ID],$D$3,TableBOM[Item ID],$A47)>0)*($H$3>0),$C$3&", ","") & IF((COUNTIFS(TableBOM[Product ID],$D$4,TableBOM[Item ID],$A47)>0)*($H$4>0),$C$4&", ","") & IF((COUNTIFS(TableBOM[Product ID],$D$5,TableBOM[Item ID],$A47)>0)*($H$5>0),$C$5&", ","") & IF((COUNTIFS(TableBOM[Product ID],$D$6,TableBOM[Item ID],$A47)>0)*($H$6>0),$C$6&", ","") & IF((COUNTIFS(TableBOM[Product ID],$D$7,TableBOM[Item ID],$A47)>0)*($H$7>0),$C$7&", ","") & IF((COUNTIFS(TableBOM[Product ID],$D$8,TableBOM[Item ID],$A47)>0)*($H$8>0),$C$8&", ",""))>1,LEFT(IF((COUNTIFS(TableBOM[Product ID],$D$3,TableBOM[Item ID],$A47)>0)*($H$3>0),$C$3&", ","") & IF((COUNTIFS(TableBOM[Product ID],$D$4,TableBOM[Item ID],$A47)>0)*($H$4>0),$C$4&", ","") & IF((COUNTIFS(TableBOM[Product ID],$D$5,TableBOM[Item ID],$A47)>0)*($H$5>0),$C$5&", ","") & IF((COUNTIFS(TableBOM[Product ID],$D$6,TableBOM[Item ID],$A47)>0)*($H$6>0),$C$6&", ","") & IF((COUNTIFS(TableBOM[Product ID],$D$7,TableBOM[Item ID],$A47)>0)*($H$7>0),$C$7&", ","") & IF((COUNTIFS(TableBOM[Product ID],$D$8,TableBOM[Item ID],$A47)>0)*($H$8>0),$C$8&", ",""),LEN(IF((COUNTIFS(TableBOM[Product ID],$D$3,TableBOM[Item ID],$A47)>0)*($H$3>0),$C$3&", ","") & IF((COUNTIFS(TableBOM[Product ID],$D$4,TableBOM[Item ID],$A47)>0)*($H$4>0),$C$4&", ","") & IF((COUNTIFS(TableBOM[Product ID],$D$5,TableBOM[Item ID],$A47)>0)*($H$5>0),$C$5&", ","") & IF((COUNTIFS(TableBOM[Product ID],$D$6,TableBOM[Item ID],$A47)>0)*($H$6>0),$C$6&", ","") & IF((COUNTIFS(TableBOM[Product ID],$D$7,TableBOM[Item ID],$A47)>0)*($H$7>0),$C$7&", ","") & IF((COUNTIFS(TableBOM[Product ID],$D$8,TableBOM[Item ID],$A47)>0)*($H$8>0),$C$8&", ",""))-2),"") | I47: =IF(E47=0,"Not needed",IF(G47<0,"SHORTAGE",IF(G47<F47*0.1,"LOW","OK"))) -> Not needed
A48: 79 | B48: CAP | C48: M-9 S/M SPR WHITE LORINE | D48: PCS | E48: =SUMPRODUCT((TableBOM[Item ID]=A48)*TableBOM[Per 1000 Units]*(1+TableBOM[Scrap %])*SUMIF($D$3:$D$8,TableBOM[Product ID],$H$3:$H$8)/1000) -> 0 | F48: =IFERROR(INDEX(TableInventory[Store Balance],MATCH(A48,TableInventory[Item ID],0)),0)+IFERROR(INDEX(TableInventory[Work In Process],MATCH(A48,TableInventory[Item ID],0)),0) -> 83600 | G48: =F48-E48 -> 83600 | H48: =IF(LEN(IF((COUNTIFS(TableBOM[Product ID],$D$3,TableBOM[Item ID],$A48)>0)*($H$3>0),$C$3&", ","") & IF((COUNTIFS(TableBOM[Product ID],$D$4,TableBOM[Item ID],$A48)>0)*($H$4>0),$C$4&", ","") & IF((COUNTIFS(TableBOM[Product ID],$D$5,TableBOM[Item ID],$A48)>0)*($H$5>0),$C$5&", ","") & IF((COUNTIFS(TableBOM[Product ID],$D$6,TableBOM[Item ID],$A48)>0)*($H$6>0),$C$6&", ","") & IF((COUNTIFS(TableBOM[Product ID],$D$7,TableBOM[Item ID],$A48)>0)*($H$7>0),$C$7&", ","") & IF((COUNTIFS(TableBOM[Product ID],$D$8,TableBOM[Item ID],$A48)>0)*($H$8>0),$C$8&", ",""))>1,LEFT(IF((COUNTIFS(TableBOM[Product ID],$D$3,TableBOM[Item ID],$A48)>0)*($H$3>0),$C$3&", ","") & IF((COUNTIFS(TableBOM[Product ID],$D$4,TableBOM[Item ID],$A48)>0)*($H$4>0),$C$4&", ","") & IF((COUNTIFS(TableBOM[Product ID],$D$5,TableBOM[Item ID],$A48)>0)*($H$5>0),$C$5&", ","") & IF((COUNTIFS(TableBOM[Product ID],$D$6,TableBOM[Item ID],$A48)>0)*($H$6>0),$C$6&", ","") & IF((COUNTIFS(TableBOM[Product ID],$D$7,TableBOM[Item ID],$A48)>0)*($H$7>0),$C$7&", ","") & IF((COUNTIFS(TableBOM[Product ID],$D$8,TableBOM[Item ID],$A48)>0)*($H$8>0),$C$8&", ",""),LEN(IF((COUNTIFS(TableBOM[Product ID],$D$3,TableBOM[Item ID],$A48)>0)*($H$3>0),$C$3&", ","") & IF((COUNTIFS(TableBOM[Product ID],$D$4,TableBOM[Item ID],$A48)>0)*($H$4>0),$C$4&", ","") & IF((COUNTIFS(TableBOM[Product ID],$D$5,TableBOM[Item ID],$A48)>0)*($H$5>0),$C$5&", ","") & IF((COUNTIFS(TableBOM[Product ID],$D$6,TableBOM[Item ID],$A48)>0)*($H$6>0),$C$6&", ","") & IF((COUNTIFS(TableBOM[Product ID],$D$7,TableBOM[Item ID],$A48)>0)*($H$7>0),$C$7&", ","") & IF((COUNTIFS(TableBOM[Product ID],$D$8,TableBOM[Item ID],$A48)>0)*($H$8>0),$C$8&", ",""))-2),"") | I48: =IF(E48=0,"Not needed",IF(G48<0,"SHORTAGE",IF(G48<F48*0.1,"LOW","OK"))) -> Not needed
A49: 80 | B49: CAP | C49: M-9 S/M SPR WHITE DIA 19 | D49: PCS | E49: =SUMPRODUCT((TableBOM[Item ID]=A49)*TableBOM[Per 1000 Units]*(1+TableBOM[Scrap %])*SUMIF($D$3:$D$8,TableBOM[Product ID],$H$3:$H$8)/1000) -> 0 | F49: =IFERROR(INDEX(TableInventory[Store Balance],MATCH(A49,TableInventory[Item ID],0)),0)+IFERROR(INDEX(TableInventory[Work In Process],MATCH(A49,TableInventory[Item ID],0)),0) -> 100000 | G49: =F49-E49 -> 100000 | H49: =IF(LEN(IF((COUNTIFS(TableBOM[Product ID],$D$3,TableBOM[Item ID],$A49)>0)*($H$3>0),$C$3&", ","") & IF((COUNTIFS(TableBOM[Product ID],$D$4,TableBOM[Item ID],$A49)>0)*($H$4>0),$C$4&", ","") & IF((COUNTIFS(TableBOM[Product ID],$D$5,TableBOM[Item ID],$A49)>0)*($H$5>0),$C$5&", ","") & IF((COUNTIFS(TableBOM[Product ID],$D$6,TableBOM[Item ID],$A49)>0)*($H$6>0),$C$6&", ","") & IF((COUNTIFS(TableBOM[Product ID],$D$7,TableBOM[Item ID],$A49)>0)*($H$7>0),$C$7&", ","") & IF((COUNTIFS(TableBOM[Product ID],$D$8,TableBOM[Item ID],$A49)>0)*($H$8>0),$C$8&", ",""))>1,LEFT(IF((COUNTIFS(TableBOM[Product ID],$D$3,TableBOM[Item ID],$A49)>0)*($H$3>0),$C$3&", ","") & IF((COUNTIFS(TableBOM[Product ID],$D$4,TableBOM[Item ID],$A49)>0)*($H$4>0),$C$4&", ","") & IF((COUNTIFS(TableBOM[Product ID],$D$5,TableBOM[Item ID],$A49)>0)*($H$5>0),$C$5&", ","") & IF((COUNTIFS(TableBOM[Product ID],$D$6,TableBOM[Item ID],$A49)>0)*($H$6>0),$C$6&", ","") & IF((COUNTIFS(TableBOM[Product ID],$D$7,TableBOM[Item ID],$A49)>0)*($H$7>0),$C$7&", ","") & IF((COUNTIFS(TableBOM[Product ID],$D$8,TableBOM[Item ID],$A49)>0)*($H$8>0),$C$8&", ",""),LEN(IF((COUNTIFS(TableBOM[Product ID],$D$3,TableBOM[Item ID],$A49)>0)*($H$3>0),$C$3&", ","") & IF((COUNTIFS(TableBOM[Product ID],$D$4,TableBOM[Item ID],$A49)>0)*($H$4>0),$C$4&", ","") & IF((COUNTIFS(TableBOM[Product ID],$D$5,TableBOM[Item ID],$A49)>0)*($H$5>0),$C$5&", ","") & IF((COUNTIFS(TableBOM[Product ID],$D$6,TableBOM[Item ID],$A49)>0)*($H$6>0),$C$6&", ","") & IF((COUNTIFS(TableBOM[Product ID],$D$7,TableBOM[Item ID],$A49)>0)*($H$7>0),$C$7&", ","") & IF((COUNTIFS(TableBOM[Product ID],$D$8,TableBOM[Item ID],$A49)>0)*($H$8>0),$C$8&", ",""))-2),"") | I49: =IF(E49=0,"Not needed",IF(G49<0,"SHORTAGE",IF(G49<F49*0.1,"LOW","OK"))) -> Not needed
A50: 81 | B50: CAP | C50: M-9 S/M F/P WHITE (S) | D50: PCS | E50: =SUMPRODUCT((TableBOM[Item ID]=A50)*TableBOM[Per 1000 Units]*(1+TableBOM[Scrap %])*SUMIF($D$3:$D$8,TableBOM[Product ID],$H$3:$H$8)/1000) -> 0 | F50: =IFERROR(INDEX(TableInventory[Store Balance],MATCH(A50,TableInventory[Item ID],0)),0)+IFERROR(INDEX(TableInventory[Work In Process],MATCH(A50,TableInventory[Item ID],0)),0) -> 553124 | G50: =F50-E50 -> 553124 | H50: =IF(LEN(IF((COUNTIFS(TableBOM[Product ID],$D$3,TableBOM[Item ID],$A50)>0)*($H$3>0),$C$3&", ","") & IF((COUNTIFS(TableBOM[Product ID],$D$4,TableBOM[Item ID],$A50)>0)*($H$4>0),$C$4&", ","") & IF((COUNTIFS(TableBOM[Product ID],$D$5,TableBOM[Item ID],$A50)>0)*($H$5>0),$C$5&", ","") & IF((COUNTIFS(TableBOM[Product ID],$D$6,TableBOM[Item ID],$A50)>0)*($H$6>0),$C$6&", ","") & IF((COUNTIFS(TableBOM[Product ID],$D$7,TableBOM[Item ID],$A50)>0)*($H$7>0),$C$7&", ","") & IF((COUNTIFS(TableBOM[Product ID],$D$8,TableBOM[Item ID],$A50)>0)*($H$8>0),$C$8&", ",""))>1,LEFT(IF((COUNTIFS(TableBOM[Product ID],$D$3,TableBOM[Item ID],$A50)>0)*($H$3>0),$C$3&", ","") & IF((COUNTIFS(TableBOM[Product ID],$D$4,TableBOM[Item ID],$A50)>0)*($H$4>0),$C$4&", ","") & IF((COUNTIFS(TableBOM[Product ID],$D$5,TableBOM[Item ID],$A50)>0)*($H$5>0),$C$5&", ","") & IF((COUNTIFS(TableBOM[Product ID],$D$6,TableBOM[Item ID],$A50)>0)*($H$6>0),$C$6&", ","") & IF((COUNTIFS(TableBOM[Product ID],$D$7,TableBOM[Item ID],$A50)>0)*($H$7>0),$C$7&", ","") & IF((COUNTIFS(TableBOM[Product ID],$D$8,TableBOM[Item ID],$A50)>0)*($H$8>0),$C$8&", ",""),LEN(IF((COUNTIFS(TableBOM[Product ID],$D$3,TableBOM[Item ID],$A50)>0)*($H$3>0),$C$3&", ","") & IF((COUNTIFS(TableBOM[Product ID],$D$4,TableBOM[Item ID],$A50)>0)*($H$4>0),$C$4&", ","") & IF((COUNTIFS(TableBOM[Product ID],$D$5,TableBOM[Item ID],$A50)>0)*($H$5>0),$C$5&", ","") & IF((COUNTIFS(TableBOM[Product ID],$D$6,TableBOM[Item ID],$A50)>0)*($H$6>0),$C$6&", ","") & IF((COUNTIFS(TableBOM[Product ID],$D$7,TableBOM[Item ID],$A50)>0)*($H$7>0),$C$7&", ","") & IF((COUNTIFS(TableBOM[Product ID],$D$8,TableBOM[Item ID],$A50)>0)*($H$8>0),$C$8&", ",""))-2),"") | I50: =IF(E50=0,"Not needed",IF(G50<0,"SHORTAGE",IF(G50<F50*0.1,"LOW","OK"))) -> Not needed
A51: 1800 | B51: CAP | C51: M-9 S/M SPR BLACK DIA 19 | D51: PCS | E51: =SUMPRODUCT((TableBOM[Item ID]=A51)*TableBOM[Per 1000 Units]*(1+TableBOM[Scrap %])*SUMIF($D$3:$D$8,TableBOM[Product ID],$H$3:$H$8)/1000) -> 0 | F51: =IFERROR(INDEX(TableInventory[Store Balance],MATCH(A51,TableInventory[Item ID],0)),0)+IFERROR(INDEX(TableInventory[Work In Process],MATCH(A51,TableInventory[Item ID],0)),0) -> 0 | G51: =F51-E51 -> 0 | H51: =IF(LEN(IF((COUNTIFS(TableBOM[Product ID],$D$3,TableBOM[Item ID],$A51)>0)*($H$3>0),$C$3&", ","") & IF((COUNTIFS(TableBOM[Product ID],$D$4,TableBOM[Item ID],$A51)>0)*($H$4>0),$C$4&", ","") & IF((COUNTIFS(TableBOM[Product ID],$D$5,TableBOM[Item ID],$A51)>0)*($H$5>0),$C$5&", ","") & IF((COUNTIFS(TableBOM[Product ID],$D$6,TableBOM[Item ID],$A51)>0)*($H$6>0),$C$6&", ","") & IF((COUNTIFS(TableBOM[Product ID],$D$7,TableBOM[Item ID],$A51)>0)*($H$7>0),$C$7&", ","") & IF((COUNTIFS(TableBOM[Product ID],$D$8,TableBOM[Item ID],$A51)>0)*($H$8>0),$C$8&", ",""))>1,LEFT(IF((COUNTIFS(TableBOM[Product ID],$D$3,TableBOM[Item ID],$A51)>0)*($H$3>0),$C$3&", ","") & IF((COUNTIFS(TableBOM[Product ID],$D$4,TableBOM[Item ID],$A51)>0)*($H$4>0),$C$4&", ","") & IF((COUNTIFS(TableBOM[Product ID],$D$5,TableBOM[Item ID],$A51)>0)*($H$5>0),$C$5&", ","") & IF((COUNTIFS(TableBOM[Product ID],$D$6,TableBOM[Item ID],$A51)>0)*($H$6>0),$C$6&", ","") & IF((COUNTIFS(TableBOM[Product ID],$D$7,TableBOM[Item ID],$A51)>0)*($H$7>0),$C$7&", ","") & IF((COUNTIFS(TableBOM[Product ID],$D$8,TableBOM[Item ID],$A51)>0)*($H$8>0),$C$8&", ",""),LEN(IF((COUNTIFS(TableBOM[Product ID],$D$3,TableBOM[Item ID],$A51)>0)*($H$3>0),$C$3&", ","") & IF((COUNTIFS(TableBOM[Product ID],$D$4,TableBOM[Item ID],$A51)>0)*($H$4>0),$C$4&", ","") & IF((COUNTIFS(TableBOM[Product ID],$D$5,TableBOM[Item ID],$A51)>0)*($H$5>0),$C$5&", ","") & IF((COUNTIFS(TableBOM[Product ID],$D$6,TableBOM[Item ID],$A51)>0)*($H$6>0),$C$6&", ","") & IF((COUNTIFS(TableBOM[Product ID],$D$7,TableBOM[Item ID],$A51)>0)*($H$7>0),$C$7&", ","") & IF((COUNTIFS(TableBOM[Product ID],$D$8,TableBOM[Item ID],$A51)>0)*($H$8>0),$C$8&", ",""))-2),"") | I51: =IF(E51=0,"Not needed",IF(G51<0,"SHORTAGE",IF(G51<F51*0.1,"LOW","OK"))) -> Not needed
A52: 3211 | B52: CAP | C52: M-9 S/M SPR WHITE DIA 22 AUTO | D52: PCS | E52: =SUMPRODUCT((TableBOM[Item ID]=A52)*TableBOM[Per 1000 Units]*(1+TableBOM[Scrap %])*SUMIF($D$3:$D$8,TableBOM[Product ID],$H$3:$H$8)/1000) -> 0 | F52: =IFERROR(INDEX(TableInventory[Store Balance],MATCH(A52,TableInventory[Item ID],0)),0)+IFERROR(INDEX(TableInventory[Work In Process],MATCH(A52,TableInventory[Item ID],0)),0) -> 4000 | G52: =F52-E52 -> 4000 | H52: =IF(LEN(IF((COUNTIFS(TableBOM[Product ID],$D$3,TableBOM[Item ID],$A52)>0)*($H$3>0),$C$3&", ","") & IF((COUNTIFS(TableBOM[Product ID],$D$4,TableBOM[Item ID],$A52)>0)*($H$4>0),$C$4&", ","") & IF((COUNTIFS(TableBOM[Product ID],$D$5,TableBOM[Item ID],$A52)>0)*($H$5>0),$C$5&", ","") & IF((COUNTIFS(TableBOM[Product ID],$D$6,TableBOM[Item ID],$A52)>0)*($H$6>0),$C$6&", ","") & IF((COUNTIFS(TableBOM[Product ID],$D$7,TableBOM[Item ID],$A52)>0)*($H$7>0),$C$7&", ","") & IF((COUNTIFS(TableBOM[Product ID],$D$8,TableBOM[Item ID],$A52)>0)*($H$8>0),$C$8&", ",""))>1,LEFT(IF((COUNTIFS(TableBOM[Product ID],$D$3,TableBOM[Item ID],$A52)>0)*($H$3>0),$C$3&", ","") & IF((COUNTIFS(TableBOM[Product ID],$D$4,TableBOM[Item ID],$A52)>0)*($H$4>0),$C$4&", ","") & IF((COUNTIFS(TableBOM[Product ID],$D$5,TableBOM[Item ID],$A52)>0)*($H$5>0),$C$5&", ","") & IF((COUNTIFS(TableBOM[Product ID],$D$6,TableBOM[Item ID],$A52)>0)*($H$6>0),$C$6&", ","") & IF((COUNTIFS(TableBOM[Product ID],$D$7,TableBOM[Item ID],$A52)>0)*($H$7>0),$C$7&", ","") & IF((COUNTIFS(TableBOM[Product ID],$D$8,TableBOM[Item ID],$A52)>0)*($H$8>0),$C$8&", ",""),LEN(IF((COUNTIFS(TableBOM[Product ID],$D$3,TableBOM[Item ID],$A52)>0)*($H$3>0),$C$3&", ","") & IF((COUNTIFS(TableBOM[Product ID],$D$4,TableBOM[Item ID],$A52)>0)*($H$4>0),$C$4&", ","") & IF((COUNTIFS(TableBOM[Product ID],$D$5,TableBOM[Item ID],$A52)>0)*($H$5>0),$C$5&", ","") & IF((COUNTIFS(TableBOM[Product ID],$D$6,TableBOM[Item ID],$A52)>0)*($H$6>0),$C$6&", ","") & IF((COUNTIFS(TableBOM[Product ID],$D$7,TableBOM[Item ID],$A52)>0)*($H$7>0),$C$7&", ","") & IF((COUNTIFS(TableBOM[Product ID],$D$8,TableBOM[Item ID],$A52)>0)*($H$8>0),$C$8&", ",""))-2),"") | I52: =IF(E52=0,"Not needed",IF(G52<0,"SHORTAGE",IF(G52<F52*0.1,"LOW","OK"))) -> Not needed
A53: 4015 | B53: CAP | C53: M-9 S/M F/P ORANGE (NORMAL) | D53: PCS | E53: =SUMPRODUCT((TableBOM[Item ID]=A53)*TableBOM[Per 1000 Units]*(1+TableBOM[Scrap %])*SUMIF($D$3:$D$8,TableBOM[Product ID],$H$3:$H$8)/1000) -> 0 | F53: =IFERROR(INDEX(TableInventory[Store Balance],MATCH(A53,TableInventory[Item ID],0)),0)+IFERROR(INDEX(TableInventory[Work In Process],MATCH(A53,TableInventory[Item ID],0)),0) -> 475000 | G53: =F53-E53 -> 475000 | H53: =IF(LEN(IF((COUNTIFS(TableBOM[Product ID],$D$3,TableBOM[Item ID],$A53)>0)*($H$3>0),$C$3&", ","") & IF((COUNTIFS(TableBOM[Product ID],$D$4,TableBOM[Item ID],$A53)>0)*($H$4>0),$C$4&", ","") & IF((COUNTIFS(TableBOM[Product ID],$D$5,TableBOM[Item ID],$A53)>0)*($H$5>0),$C$5&", ","") & IF((COUNTIFS(TableBOM[Product ID],$D$6,TableBOM[Item ID],$A53)>0)*($H$6>0),$C$6&", ","") & IF((COUNTIFS(TableBOM[Product ID],$D$7,TableBOM[Item ID],$A53)>0)*($H$7>0),$C$7&", ","") & IF((COUNTIFS(TableBOM[Product ID],$D$8,TableBOM[Item ID],$A53)>0)*($H$8>0),$C$8&", ",""))>1,LEFT(IF((COUNTIFS(TableBOM[Product ID],$D$3,TableBOM[Item ID],$A53)>0)*($H$3>0),$C$3&", ","") & IF((COUNTIFS(TableBOM[Product ID],$D$4,TableBOM[Item ID],$A53)>0)*($H$4>0),$C$4&", ","") & IF((COUNTIFS(TableBOM[Product ID],$D$5,TableBOM[Item ID],$A53)>0)*($H$5>0),$C$5&", ","") & IF((COUNTIFS(TableBOM[Product ID],$D$6,TableBOM[Item ID],$A53)>0)*($H$6>0),$C$6&", ","") & IF((COUNTIFS(TableBOM[Product ID],$D$7,TableBOM[Item ID],$A53)>0)*($H$7>0),$C$7&", ","") & IF((COUNTIFS(TableBOM[Product ID],$D$8,TableBOM[Item ID],$A53)>0)*($H$8>0),$C$8&", ",""),LEN(IF((COUNTIFS(TableBOM[Product ID],$D$3,TableBOM[Item ID],$A53)>0)*($H$3>0),$C$3&", ","") & IF((COUNTIFS(TableBOM[Product ID],$D$4,TableBOM[Item ID],$A53)>0)*($H$4>0),$C$4&", ","") & IF((COUNTIFS(TableBOM[Product ID],$D$5,TableBOM[Item ID],$A53)>0)*($H$5>0),$C$5&", ","") & IF((COUNTIFS(TableBOM[Product ID],$D$6,TableBOM[Item ID],$A53)>0)*($H$6>0),$C$6&", ","") & IF((COUNTIFS(TableBOM[Product ID],$D$7,TableBOM[Item ID],$A53)>0)*($H$7>0),$C$7&", ","") & IF((COUNTIFS(TableBOM[Product ID],$D$8,TableBOM[Item ID],$A53)>0)*($H$8>0),$C$8&", ",""))-2),"") | I53: =IF(E53=0,"Not needed",IF(G53<0,"SHORTAGE",IF(G53<F53*0.1,"LOW","OK"))) -> Not needed
A54: 4044 | B54: CAP | C54: M-9 S/M SPR BEIGE DIA 20.5 | D54: PCS | E54: =SUMPRODUCT((TableBOM[Item ID]=A54)*TableBOM[Per 1000 Units]*(1+TableBOM[Scrap %])*SUMIF($D$3:$D$8,TableBOM[Product ID],$H$3:$H$8)/1000) -> 0 | F54: =IFERROR(INDEX(TableInventory[Store Balance],MATCH(A54,TableInventory[Item ID],0)),0)+IFERROR(INDEX(TableInventory[Work In Process],MATCH(A54,TableInventory[Item ID],0)),0) -> 0 | G54: =F54-E54 -> 0 | H54: =IF(LEN(IF((COUNTIFS(TableBOM[Product ID],$D$3,TableBOM[Item ID],$A54)>0)*($H$3>0),$C$3&", ","") & IF((COUNTIFS(TableBOM[Product ID],$D$4,TableBOM[Item ID],$A54)>0)*($H$4>0),$C$4&", ","") & IF((COUNTIFS(TableBOM[Product ID],$D$5,TableBOM[Item ID],$A54)>0)*($H$5>0),$C$5&", ","") & IF((COUNTIFS(TableBOM[Product ID],$D$6,TableBOM[Item ID],$A54)>0)*($H$6>0),$C$6&", ","") & IF((COUNTIFS(TableBOM[Product ID],$D$7,TableBOM[Item ID],$A54)>0)*($H$7>0),$C$7&", ","") & IF((COUNTIFS(TableBOM[Product ID],$D$8,TableBOM[Item ID],$A54)>0)*($H$8>0),$C$8&", ",""))>1,LEFT(IF((COUNTIFS(TableBOM[Product ID],$D$3,TableBOM[Item ID],$A54)>0)*($H$3>0),$C$3&", ","") & IF((COUNTIFS(TableBOM[Product ID],$D$4,TableBOM[Item ID],$A54)>0)*($H$4>0),$C$4&", ","") & IF((COUNTIFS(TableBOM[Product ID],$D$5,TableBOM[Item ID],$A54)>0)*($H$5>0),$C$5&", ","") & IF((COUNTIFS(TableBOM[Product ID],$D$6,TableBOM[Item ID],$A54)>0)*($H$6>0),$C$6&", ","") & IF((COUNTIFS(TableBOM[Product ID],$D$7,TableBOM[Item ID],$A54)>0)*($H$7>0),$C$7&", ","") & IF((COUNTIFS(TableBOM[Product ID],$D$8,TableBOM[Item ID],$A54)>0)*($H$8>0),$C$8&", ",""),LEN(IF((COUNTIFS(TableBOM[Product ID],$D$3,TableBOM[Item ID],$A54)>0)*($H$3>0),$C$3&", ","") & IF((COUNTIFS(TableBOM[Product ID],$D$4,TableBOM[Item ID],$A54)>0)*($H$4>0),$C$4&", ","") & IF((COUNTIFS(TableBOM[Product ID],$D$5,TableBOM[Item ID],$A54)>0)*($H$5>0),$C$5&", ","") & IF((COUNTIFS(TableBOM[Product ID],$D$6,TableBOM[Item ID],$A54)>0)*($H$6>0),$C$6&", ","") & IF((COUNTIFS(TableBOM[Product ID],$D$7,TableBOM[Item ID],$A54)>0)*($H$7>0),$C$7&", ","") & IF((COUNTIFS(TableBOM[Product ID],$D$8,TableBOM[Item ID],$A54)>0)*($H$8>0),$C$8&", ",""))-2),"") | I54: =IF(E54=0,"Not needed",IF(G54<0,"SHORTAGE",IF(G54<F54*0.1,"LOW","OK"))) -> Not needed
A55: 4088 | B55: CAP | C55: M-9 S/M SPR WHITE DIA 16MM | D55: PCS | E55: =SUMPRODUCT((TableBOM[Item ID]=A55)*TableBOM[Per 1000 Units]*(1+TableBOM[Scrap %])*SUMIF($D$3:$D$8,TableBOM[Product ID],$H$3:$H$8)/1000) -> 0 | F55: =IFERROR(INDEX(TableInventory[Store Balance],MATCH(A55,TableInventory[Item ID],0)),0)+IFERROR(INDEX(TableInventory[Work In Process],MATCH(A55,TableInventory[Item ID],0)),0) -> 60000 | G55: =F55-E55 -> 60000 | H55: =IF(LEN(IF((COUNTIFS(TableBOM[Product ID],$D$3,TableBOM[Item ID],$A55)>0)*($H$3>0),$C$3&", ","") & IF((COUNTIFS(TableBOM[Product ID],$D$4,TableBOM[Item ID],$A55)>0)*($H$4>0),$C$4&", ","") & IF((COUNTIFS(TableBOM[Product ID],$D$5,TableBOM[Item ID],$A55)>0)*($H$5>0),$C$5&", ","") & IF((COUNTIFS(TableBOM[Product ID],$D$6,TableBOM[Item ID],$A55)>0)*($H$6>0),$C$6&", ","") & IF((COUNTIFS(TableBOM[Product ID],$D$7,TableBOM[Item ID],$A55)>0)*($H$7>0),$C$7&", ","") & IF((COUNTIFS(TableBOM[Product ID],$D$8,TableBOM[Item ID],$A55)>0)*($H$8>0),$C$8&", ",""))>1,LEFT(IF((COUNTIFS(TableBOM[Product ID],$D$3,TableBOM[Item ID],$A55)>0)*($H$3>0),$C$3&", ","") & IF((COUNTIFS(TableBOM[Product ID],$D$4,TableBOM[Item ID],$A55)>0)*($H$4>0),$C$4&", ","") & IF((COUNTIFS(TableBOM[Product ID],$D$5,TableBOM[Item ID],$A55)>0)*($H$5>0),$C$5&", ","") & IF((COUNTIFS(TableBOM[Product ID],$D$6,TableBOM[Item ID],$A55)>0)*($H$6>0),$C$6&", ","") & IF((COUNTIFS(TableBOM[Product ID],$D$7,TableBOM[Item ID],$A55)>0)*($H$7>0),$C$7&", ","") & IF((COUNTIFS(TableBOM[Product ID],$D$8,TableBOM[Item ID],$A55)>0)*($H$8>0),$C$8&", ",""),LEN(IF((COUNTIFS(TableBOM[Product ID],$D$3,TableBOM[Item ID],$A55)>0)*($H$3>0),$C$3&", ","") & IF((COUNTIFS(TableBOM[Product ID],$D$4,TableBOM[Item ID],$A55)>0)*($H$4>0),$C$4&", ","") & IF((COUNTIFS(TableBOM[Product ID],$D$5,TableBOM[Item ID],$A55)>0)*($H$5>0),$C$5&", ","") & IF((COUNTIFS(TableBOM[Product ID],$D$6,TableBOM[Item ID],$A55)>0)*($H$6>0),$C$6&", ","") & IF((COUNTIFS(TableBOM[Product ID],$D$7,TableBOM[Item ID],$A55)>0)*($H$7>0),$C$7&", ","") & IF((COUNTIFS(TableBOM[Product ID],$D$8,TableBOM[Item ID],$A55)>0)*($H$8>0),$C$8&", ",""))-2),"") | I55: =IF(E55=0,"Not needed",IF(G55<0,"SHORTAGE",IF(G55<F55*0.1,"LOW","OK"))) -> Not needed
A56: 4143 | B56: CAP | C56: M-9 S/M F/P Normal White | D56: PCS | E56: =SUMPRODUCT((TableBOM[Item ID]=A56)*TableBOM[Per 1000 Units]*(1+TableBOM[Scrap %])*SUMIF($D$3:$D$8,TableBOM[Product ID],$H$3:$H$8)/1000) -> 0 | F56: =IFERROR(INDEX(TableInventory[Store Balance],MATCH(A56,TableInventory[Item ID],0)),0)+IFERROR(INDEX(TableInventory[Work In Process],MATCH(A56,TableInventory[Item ID],0)),0) -> 65000 | G56: =F56-E56 -> 65000 | H56: =IF(LEN(IF((COUNTIFS(TableBOM[Product ID],$D$3,TableBOM[Item ID],$A56)>0)*($H$3>0),$C$3&", ","") & IF((COUNTIFS(TableBOM[Product ID],$D$4,TableBOM[Item ID],$A56)>0)*($H$4>0),$C$4&", ","") & IF((COUNTIFS(TableBOM[Product ID],$D$5,TableBOM[Item ID],$A56)>0)*($H$5>0),$C$5&", ","") & IF((COUNTIFS(TableBOM[Product ID],$D$6,TableBOM[Item ID],$A56)>0)*($H$6>0),$C$6&", ","") & IF((COUNTIFS(TableBOM[Product ID],$D$7,TableBOM[Item ID],$A56)>0)*($H$7>0),$C$7&", ","") & IF((COUNTIFS(TableBOM[Product ID],$D$8,TableBOM[Item ID],$A56)>0)*($H$8>0),$C$8&", ",""))>1,LEFT(IF((COUNTIFS(TableBOM[Product ID],$D$3,TableBOM[Item ID],$A56)>0)*($H$3>0),$C$3&", ","") & IF((COUNTIFS(TableBOM[Product ID],$D$4,TableBOM[Item ID],$A56)>0)*($H$4>0),$C$4&", ","") & IF((COUNTIFS(TableBOM[Product ID],$D$5,TableBOM[Item ID],$A56)>0)*($H$5>0),$C$5&", ","") & IF((COUNTIFS(TableBOM[Product ID],$D$6,TableBOM[Item ID],$A56)>0)*($H$6>0),$C$6&", ","") & IF((COUNTIFS(TableBOM[Product ID],$D$7,TableBOM[Item ID],$A56)>0)*($H$7>0),$C$7&", ","") & IF((COUNTIFS(TableBOM[Product ID],$D$8,TableBOM[Item ID],$A56)>0)*($H$8>0),$C$8&", ",""),LEN(IF((COUNTIFS(TableBOM[Product ID],$D$3,TableBOM[Item ID],$A56)>0)*($H$3>0),$C$3&", ","") & IF((COUNTIFS(TableBOM[Product ID],$D$4,TableBOM[Item ID],$A56)>0)*($H$4>0),$C$4&", ","") & IF((COUNTIFS(TableBOM[Product ID],$D$5,TableBOM[Item ID],$A56)>0)*($H$5>0),$C$5&", ","") & IF((COUNTIFS(TableBOM[Product ID],$D$6,TableBOM[Item ID],$A56)>0)*($H$6>0),$C$6&", ","") & IF((COUNTIFS(TableBOM[Product ID],$D$7,TableBOM[Item ID],$A56)>0)*($H$7>0),$C$7&", ","") & IF((COUNTIFS(TableBOM[Product ID],$D$8,TableBOM[Item ID],$A56)>0)*($H$8>0),$C$8&", ",""))-2),"") | I56: =IF(E56=0,"Not needed",IF(G56<0,"SHORTAGE",IF(G56<F56*0.1,"LOW","OK"))) -> Not needed
A57: 6971 | B57: CAP | C57: M-9 S/M SPR WHITE DIA 20.5MM | D57: PCS | E57: =SUMPRODUCT((TableBOM[Item ID]=A57)*TableBOM[Per 1000 Units]*(1+TableBOM[Scrap %])*SUMIF($D$3:$D$8,TableBOM[Product ID],$H$3:$H$8)/1000) -> 0 | F57: =IFERROR(INDEX(TableInventory[Store Balance],MATCH(A57,TableInventory[Item ID],0)),0)+IFERROR(INDEX(TableInventory[Work In Process],MATCH(A57,TableInventory[Item ID],0)),0) -> 0 | G57: =F57-E57 -> 0 | H57: =IF(LEN(IF((COUNTIFS(TableBOM[Product ID],$D$3,TableBOM[Item ID],$A57)>0)*($H$3>0),$C$3&", ","") & IF((COUNTIFS(TableBOM[Product ID],$D$4,TableBOM[Item ID],$A57)>0)*($H$4>0),$C$4&", ","") & IF((COUNTIFS(TableBOM[Product ID],$D$5,TableBOM[Item ID],$A57)>0)*($H$5>0),$C$5&", ","") & IF((COUNTIFS(TableBOM[Product ID],$D$6,TableBOM[Item ID],$A57)>0)*($H$6>0),$C$6&", ","") & IF((COUNTIFS(TableBOM[Product ID],$D$7,TableBOM[Item ID],$A57)>0)*($H$7>0),$C$7&", ","") & IF((COUNTIFS(TableBOM[Product ID],$D$8,TableBOM[Item ID],$A57)>0)*($H$8>0),$C$8&", ",""))>1,LEFT(IF((COUNTIFS(TableBOM[Product ID],$D$3,TableBOM[Item ID],$A57)>0)*($H$3>0),$C$3&", ","") & IF((COUNTIFS(TableBOM[Product ID],$D$4,TableBOM[Item ID],$A57)>0)*($H$4>0),$C$4&", ","") & IF((COUNTIFS(TableBOM[Product ID],$D$5,TableBOM[Item ID],$A57)>0)*($H$5>0),$C$5&", ","") & IF((COUNTIFS(TableBOM[Product ID],$D$6,TableBOM[Item ID],$A57)>0)*($H$6>0),$C$6&", ","") & IF((COUNTIFS(TableBOM[Product ID],$D$7,TableBOM[Item ID],$A57)>0)*($H$7>0),$C$7&", ","") & IF((COUNTIFS(TableBOM[Product ID],$D$8,TableBOM[Item ID],$A57)>0)*($H$8>0),$C$8&", ",""),LEN(IF((COUNTIFS(TableBOM[Product ID],$D$3,TableBOM[Item ID],$A57)>0)*($H$3>0),$C$3&", ","") & IF((COUNTIFS(TableBOM[Product ID],$D$4,TableBOM[Item ID],$A57)>0)*($H$4>0),$C$4&", ","") & IF((COUNTIFS(TableBOM[Product ID],$D$5,TableBOM[Item ID],$A57)>0)*($H$5>0),$C$5&", ","") & IF((COUNTIFS(TableBOM[Product ID],$D$6,TableBOM[Item ID],$A57)>0)*($H$6>0),$C$6&", ","") & IF((COUNTIFS(TableBOM[Product ID],$D$7,TableBOM[Item ID],$A57)>0)*($H$7>0),$C$7&", ","") & IF((COUNTIFS(TableBOM[Product ID],$D$8,TableBOM[Item ID],$A57)>0)*($H$8>0),$C$8&", ",""))-2),"") | I57: =IF(E57=0,"Not needed",IF(G57<0,"SHORTAGE",IF(G57<F57*0.1,"LOW","OK"))) -> Not needed
... A67: 9903 | B67: CARTON | C67: CARTON 12.5MM (est) | D67: PCS | E67: =SUMPRODUCT((TableBOM[Item ID]=A67)*TableBOM[Per 1000 Units]*(1+TableBOM[Scrap %])*SUMIF($D$3:$D$8,TableBOM[Product ID],$H$3:$H$8)/1000) -> 0 | F67: =IFERROR(INDEX(TableInventory[Store Balance],MATCH(A67,TableInventory[Item ID],0)),0)+IFERROR(INDEX(TableInventory[Work In Process],MATCH(A67,TableInventory[Item ID],0)),0) -> 0 | G67: =F67-E67 -> 0 | H67: =IF(LEN(IF((COUNTIFS(TableBOM[Product ID],$D$3,TableBOM[Item ID],$A67)>0)*($H$3>0),$C$3&", ","") & IF((COUNTIFS(TableBOM[Product ID],$D$4,TableBOM[Item ID],$A67)>0)*($H$4>0),$C$4&", ","") & IF((COUNTIFS(TableBOM[Product ID],$D$5,TableBOM[Item ID],$A67)>0)*($H$5>0),$C$5&", ","") & IF((COUNTIFS(TableBOM[Product ID],$D$6,TableBOM[Item ID],$A67)>0)*($H$6>0),$C$6&", ","") & IF((COUNTIFS(TableBOM[Product ID],$D$7,TableBOM[Item ID],$A67)>0)*($H$7>0),$C$7&", ","") & IF((COUNTIFS(TableBOM[Product ID],$D$8,TableBOM[Item ID],$A67)>0)*($H$8>0),$C$8&", ",""))>1,LEFT(IF((COUNTIFS(TableBOM[Product ID],$D$3,TableBOM[Item ID],$A67)>0)*($H$3>0),$C$3&", ","") & IF((COUNTIFS(TableBOM[Product ID],$D$4,TableBOM[Item ID],$A67)>0)*($H$4>0),$C$4&", ","") & IF((COUNTIFS(TableBOM[Product ID],$D$5,TableBOM[Item ID],$A67)>0)*($H$5>0),$C$5&", ","") & IF((COUNTIFS(TableBOM[Product ID],$D$6,TableBOM[Item ID],$A67)>0)*($H$6>0),$C$6&", ","") & IF((COUNTIFS(TableBOM[Product ID],$D$7,TableBOM[Item ID],$A67)>0)*($H$7>0),$C$7&", ","") & IF((COUNTIFS(TableBOM[Product ID],$D$8,TableBOM[Item ID],$A67)>0)*($H$8>0),$C$8&", ",""),LEN(IF((COUNTIFS(TableBOM[Product ID],$D$3,TableBOM[Item ID],$A67)>0)*($H$3>0),$C$3&", ","") & IF((COUNTIFS(TableBOM[Product ID],$D$4,TableBOM[Item ID],$A67)>0)*($H$4>0),$C$4&", ","") & IF((COUNTIFS(TableBOM[Product ID],$D$5,TableBOM[Item ID],$A67)>0)*($H$5>0),$C$5&", ","") & IF((COUNTIFS(TableBOM[Product ID],$D$6,TableBOM[Item ID],$A67)>0)*($H$6>0),$C$6&", ","") & IF((COUNTIFS(TableBOM[Product ID],$D$7,TableBOM[Item ID],$A67)>0)*($H$7>0),$C$7&", ","") & IF((COUNTIFS(TableBOM[Product ID],$D$8,TableBOM[Item ID],$A67)>0)*($H$8>0),$C$8&", ",""))-2),"") | I67: =IF(E67=0,"Not needed",IF(G67<0,"SHORTAGE",IF(G67<F67*0.1,"LOW","OK"))) -> Not needed
A68: 36 | B68: CARTON | C68: 16X200 3Ply | D68: PCS | E68: =SUMPRODUCT((TableBOM[Item ID]=A68)*TableBOM[Per 1000 Units]*(1+TableBOM[Scrap %])*SUMIF($D$3:$D$8,TableBOM[Product ID],$H$3:$H$8)/1000) -> 137.5 | F68: =IFERROR(INDEX(TableInventory[Store Balance],MATCH(A68,TableInventory[Item ID],0)),0)+IFERROR(INDEX(TableInventory[Work In Process],MATCH(A68,TableInventory[Item ID],0)),0) -> 0 | G68: =F68-E68 -> -137.5 | H68: =IF(LEN(IF((COUNTIFS(TableBOM[Product ID],$D$3,TableBOM[Item ID],$A68)>0)*($H$3>0),$C$3&", ","") & IF((COUNTIFS(TableBOM[Product ID],$D$4,TableBOM[Item ID],$A68)>0)*($H$4>0),$C$4&", ","") & IF((COUNTIFS(TableBOM[Product ID],$D$5,TableBOM[Item ID],$A68)>0)*($H$5>0),$C$5&", ","") & IF((COUNTIFS(TableBOM[Product ID],$D$6,TableBOM[Item ID],$A68)>0)*($H$6>0),$C$6&", ","") & IF((COUNTIFS(TableBOM[Product ID],$D$7,TableBOM[Item ID],$A68)>0)*($H$7>0),$C$7&", ","") & IF((COUNTIFS(TableBOM[Product ID],$D$8,TableBOM[Item ID],$A68)>0)*($H$8>0),$C$8&", ",""))>1,LEFT(IF((COUNTIFS(TableBOM[Product ID],$D$3,TableBOM[Item ID],$A68)>0)*($H$3>0),$C$3&", ","") & IF((COUNTIFS(TableBOM[Product ID],$D$4,TableBOM[Item ID],$A68)>0)*($H$4>0),$C$4&", ","") & IF((COUNTIFS(TableBOM[Product ID],$D$5,TableBOM[Item ID],$A68)>0)*($H$5>0),$C$5&", ","") & IF((COUNTIFS(TableBOM[Product ID],$D$6,TableBOM[Item ID],$A68)>0)*($H$6>0),$C$6&", ","") & IF((COUNTIFS(TableBOM[Product ID],$D$7,TableBOM[Item ID],$A68)>0)*($H$7>0),$C$7&", ","") & IF((COUNTIFS(TableBOM[Product ID],$D$8,TableBOM[Item ID],$A68)>0)*($H$8>0),$C$8&", ",""),LEN(IF((COUNTIFS(TableBOM[Product ID],$D$3,TableBOM[Item ID],$A68)>0)*($H$3>0),$C$3&", ","") & IF((COUNTIFS(TableBOM[Product ID],$D$4,TableBOM[Item ID],$A68)>0)*($H$4>0),$C$4&", ","") & IF((COUNTIFS(TableBOM[Product ID],$D$5,TableBOM[Item ID],$A68)>0)*($H$5>0),$C$5&", ","") & IF((COUNTIFS(TableBOM[Product ID],$D$6,TableBOM[Item ID],$A68)>0)*($H$6>0),$C$6&", ","") & IF((COUNTIFS(TableBOM[Product ID],$D$7,TableBOM[Item ID],$A68)>0)*($H$7>0),$C$7&", ","") & IF((COUNTIFS(TableBOM[Product ID],$D$8,TableBOM[Item ID],$A68)>0)*($H$8>0),$C$8&", ",""))-2),"") -> ECZEMUS OINTMENT 0.03% 10G | I68: Hold. Caps not approved
A69: 200 | B69: CARTON | C69: DIA 16 5Ply | D69: PCS | E69: =SUMPRODUCT((TableBOM[Item ID]=A69)*TableBOM[Per 1000 Units]*(1+TableBOM[Scrap %])*SUMIF($D$3:$D$8,TableBOM[Product ID],$H$3:$H$8)/1000) -> 15.125 | F69: =IFERROR(INDEX(TableInventory[Store Balance],MATCH(A69,TableInventory[Item ID],0)),0)+IFERROR(INDEX(TableInventory[Work In Process],MATCH(A69,TableInventory[Item ID],0)),0) -> 0 | G69: =F69-E69 -> -15.125 | H69: =IF(LEN(IF((COUNTIFS(TableBOM[Product ID],$D$3,TableBOM[Item ID],$A69)>0)*($H$3>0),$C$3&", ","") & IF((COUNTIFS(TableBOM[Product ID],$D$4,TableBOM[Item ID],$A69)>0)*($H$4>0),$C$4&", ","") & IF((COUNTIFS(TableBOM[Product ID],$D$5,TableBOM[Item ID],$A69)>0)*($H$5>0),$C$5&", ","") & IF((COUNTIFS(TableBOM[Product ID],$D$6,TableBOM[Item ID],$A69)>0)*($H$6>0),$C$6&", ","") & IF((COUNTIFS(TableBOM[Product ID],$D$7,TableBOM[Item ID],$A69)>0)*($H$7>0),$C$7&", ","") & IF((COUNTIFS(TableBOM[Product ID],$D$8,TableBOM[Item ID],$A69)>0)*($H$8>0),$C$8&", ",""))>1,LEFT(IF((COUNTIFS(TableBOM[Product ID],$D$3,TableBOM[Item ID],$A69)>0)*($H$3>0),$C$3&", ","") & IF((COUNTIFS(TableBOM[Product ID],$D$4,TableBOM[Item ID],$A69)>0)*($H$4>0),$C$4&", ","") & IF((COUNTIFS(TableBOM[Product ID],$D$5,TableBOM[Item ID],$A69)>0)*($H$5>0),$C$5&", ","") & IF((COUNTIFS(TableBOM[Product ID],$D$6,TableBOM[Item ID],$A69)>0)*($H$6>0),$C$6&", ","") & IF((COUNTIFS(TableBOM[Product ID],$D$7,TableBOM[Item ID],$A69)>0)*($H$7>0),$C$7&", ","") & IF((COUNTIFS(TableBOM[Product ID],$D$8,TableBOM[Item ID],$A69)>0)*($H$8>0),$C$8&", ",""),LEN(IF((COUNTIFS(TableBOM[Product ID],$D$3,TableBOM[Item ID],$A69)>0)*($H$3>0),$C$3&", ","") & IF((COUNTIFS(TableBOM[Product ID],$D$4,TableBOM[Item ID],$A69)>0)*($H$4>0),$C$4&", ","") & IF((COUNTIFS(TableBOM[Product ID],$D$5,TableBOM[Item ID],$A69)>0)*($H$5>0),$C$5&", ","") & IF((COUNTIFS(TableBOM[Product ID],$D$6,TableBOM[Item ID],$A69)>0)*($H$6>0),$C$6&", ","") & IF((COUNTIFS(TableBOM[Product ID],$D$7,TableBOM[Item ID],$A69)>0)*($H$7>0),$C$7&", ","") & IF((COUNTIFS(TableBOM[Product ID],$D$8,TableBOM[Item ID],$A69)>0)*($H$8>0),$C$8&", ",""))-2),"") -> ECZEMUS OINTMENT 0.03% 10G | I69: Hold. Caps not approved
A70: 39 | B70: CARTON | C70: 19X200 3Ply | D70: PCS | E70: =SUMPRODUCT((TableBOM[Item ID]=A70)*TableBOM[Per 1000 Units]*(1+TableBOM[Scrap %])*SUMIF($D$3:$D$8,TableBOM[Product ID],$H$3:$H$8)/1000) -> 0 | F70: =IFERROR(INDEX(TableInventory[Store Balance],MATCH(A70,TableInventory[Item ID],0)),0)+IFERROR(INDEX(TableInventory[Work In Process],MATCH(A70,TableInventory[Item ID],0)),0) -> 0 | G70: =F70-E70 -> 0 | H70: =IF(LEN(IF((COUNTIFS(TableBOM[Product ID],$D$3,TableBOM[Item ID],$A70)>0)*($H$3>0),$C$3&", ","") & IF((COUNTIFS(TableBOM[Product ID],$D$4,TableBOM[Item ID],$A70)>0)*($H$4>0),$C$4&", ","") & IF((COUNTIFS(TableBOM[Product ID],$D$5,TableBOM[Item ID],$A70)>0)*($H$5>0),$C$5&", ","") & IF((COUNTIFS(TableBOM[Product ID],$D$6,TableBOM[Item ID],$A70)>0)*($H$6>0),$C$6&", ","") & IF((COUNTIFS(TableBOM[Product ID],$D$7,TableBOM[Item ID],$A70)>0)*($H$7>0),$C$7&", ","") & IF((COUNTIFS(TableBOM[Product ID],$D$8,TableBOM[Item ID],$A70)>0)*($H$8>0),$C$8&", ",""))>1,LEFT(IF((COUNTIFS(TableBOM[Product ID],$D$3,TableBOM[Item ID],$A70)>0)*($H$3>0),$C$3&", ","") & IF((COUNTIFS(TableBOM[Product ID],$D$4,TableBOM[Item ID],$A70)>0)*($H$4>0),$C$4&", ","") & IF((COUNTIFS(TableBOM[Product ID],$D$5,TableBOM[Item ID],$A70)>0)*($H$5>0),$C$5&", ","") & IF((COUNTIFS(TableBOM[Product ID],$D$6,TableBOM[Item ID],$A70)>0)*($H$6>0),$C$6&", ","") & IF((COUNTIFS(TableBOM[Product ID],$D$7,TableBOM[Item ID],$A70)>0)*($H$7>0),$C$7&", ","") & IF((COUNTIFS(TableBOM[Product ID],$D$8,TableBOM[Item ID],$A70)>0)*($H$8>0),$C$8&", ",""),LEN(IF((COUNTIFS(TableBOM[Product ID],$D$3,TableBOM[Item ID],$A70)>0)*($H$3>0),$C$3&", ","") & IF((COUNTIFS(TableBOM[Product ID],$D$4,TableBOM[Item ID],$A70)>0)*($H$4>0),$C$4&", ","") & IF((COUNTIFS(TableBOM[Product ID],$D$5,TableBOM[Item ID],$A70)>0)*($H$5>0),$C$5&", ","") & IF((COUNTIFS(TableBOM[Product ID],$D$6,TableBOM[Item ID],$A70)>0)*($H$6>0),$C$6&", ","") & IF((COUNTIFS(TableBOM[Product ID],$D$7,TableBOM[Item ID],$A70)>0)*($H$7>0),$C$7&", ","") & IF((COUNTIFS(TableBOM[Product ID],$D$8,TableBOM[Item ID],$A70)>0)*($H$8>0),$C$8&", ",""))-2),"") | I70: =IF(E70=0,"Not needed",IF(G70<0,"SHORTAGE",IF(G70<F70*0.1,"LOW","OK"))) -> Not needed
A71: 3619 | B71: CARTON | C71: 20.5x510 5ply | D71: PCS | E71: =SUMPRODUCT((TableBOM[Item ID]=A71)*TableBOM[Per 1000 Units]*(1+TableBOM[Scrap %])*SUMIF($D$3:$D$8,TableBOM[Product ID],$H$3:$H$8)/1000) -> 0 | F71: =IFERROR(INDEX(TableInventory[Store Balance],MATCH(A71,TableInventory[Item ID],0)),0)+IFERROR(INDEX(TableInventory[Work In Process],MATCH(A71,TableInventory[Item ID],0)),0) -> 280 | G71: =F71-E71 -> 280 | H71: =IF(LEN(IF((COUNTIFS(TableBOM[Product ID],$D$3,TableBOM[Item ID],$A71)>0)*($H$3>0),$C$3&", ","") & IF((COUNTIFS(TableBOM[Product ID],$D$4,TableBOM[Item ID],$A71)>0)*($H$4>0),$C$4&", ","") & IF((COUNTIFS(TableBOM[Product ID],$D$5,TableBOM[Item ID],$A71)>0)*($H$5>0),$C$5&", ","") & IF((COUNTIFS(TableBOM[Product ID],$D$6,TableBOM[Item ID],$A71)>0)*($H$6>0),$C$6&", ","") & IF((COUNTIFS(TableBOM[Product ID],$D$7,TableBOM[Item ID],$A71)>0)*($H$7>0),$C$7&", ","") & IF((COUNTIFS(TableBOM[Product ID],$D$8,TableBOM[Item ID],$A71)>0)*($H$8>0),$C$8&", ",""))>1,LEFT(IF((COUNTIFS(TableBOM[Product ID],$D$3,TableBOM[Item ID],$A71)>0)*($H$3>0),$C$3&", ","") & IF((COUNTIFS(TableBOM[Product ID],$D$4,TableBOM[Item ID],$A71)>0)*($H$4>0),$C$4&", ","") & IF((COUNTIFS(TableBOM[Product ID],$D$5,TableBOM[Item ID],$A71)>0)*($H$5>0),$C$5&", ","") & IF((COUNTIFS(TableBOM[Product ID],$D$6,TableBOM[Item ID],$A71)>0)*($H$6>0),$C$6&", ","") & IF((COUNTIFS(TableBOM[Product ID],$D$7,TableBOM[Item ID],$A71)>0)*($H$7>0),$C$7&", ","") & IF((COUNTIFS(TableBOM[Product ID],$D$8,TableBOM[Item ID],$A71)>0)*($H$8>0),$C$8&", ",""),LEN(IF((COUNTIFS(TableBOM[Product ID],$D$3,TableBOM[Item ID],$A71)>0)*($H$3>0),$C$3&", ","") & IF((COUNTIFS(TableBOM[Product ID],$D$4,TableBOM[Item ID],$A71)>0)*($H$4>0),$C$4&", ","") & IF((COUNTIFS(TableBOM[Product ID],$D$5,TableBOM[Item ID],$A71)>0)*($H$5>0),$C$5&", ","") & IF((COUNTIFS(TableBOM[Product ID],$D$6,TableBOM[Item ID],$A71)>0)*($H$6>0),$C$6&", ","") & IF((COUNTIFS(TableBOM[Product ID],$D$7,TableBOM[Item ID],$A71)>0)*($H$7>0),$C$7&", ","") & IF((COUNTIFS(TableBOM[Product ID],$D$8,TableBOM[Item ID],$A71)>0)*($H$8>0),$C$8&", ",""))-2),"") | I71: =IF(E71=0,"Not needed",IF(G71<0,"SHORTAGE",IF(G71<F71*0.1,"LOW","OK"))) -> Not needed
A72: 3598 | B72: CARTON | C72: 25x336 5Ply | D72: PCS | E72: =SUMPRODUCT((TableBOM[Item ID]=A72)*TableBOM[Per 1000 Units]*(1+TableBOM[Scrap %])*SUMIF($D$3:$D$8,TableBOM[Product ID],$H$3:$H$8)/1000) -> 1020.8235 | F72: =IFERROR(INDEX(TableInventory[Store Balance],MATCH(A72,TableInventory[Item ID],0)),0)+IFERROR(INDEX(TableInventory[Work In Process],MATCH(A72,TableInventory[Item ID],0)),0) -> 360 | G72: =F72-E72 -> -660.82346 | H72: =IF(LEN(IF((COUNTIFS(TableBOM[Product ID],$D$3,TableBOM[Item ID],$A72)>0)*($H$3>0),$C$3&", ","") & IF((COUNTIFS(TableBOM[Product ID],$D$4,TableBOM[Item ID],$A72)>0)*($H$4>0),$C$4&", ","") & IF((COUNTIFS(TableBOM[Product ID],$D$5,TableBOM[Item ID],$A72)>0)*($H$5>0),$C$5&", ","") & IF((COUNTIFS(TableBOM[Product ID],$D$6,TableBOM[Item ID],$A72)>0)*($H$6>0),$C$6&", ","") & IF((COUNTIFS(TableBOM[Product ID],$D$7,TableBOM[Item ID],$A72)>0)*($H$7>0),$C$7&", ","") & IF((COUNTIFS(TableBOM[Product ID],$D$8,TableBOM[Item ID],$A72)>0)*($H$8>0),$C$8&", ",""))>1,LEFT(IF((COUNTIFS(TableBOM[Product ID],$D$3,TableBOM[Item ID],$A72)>0)*($H$3>0),$C$3&", ","") & IF((COUNTIFS(TableBOM[Product ID],$D$4,TableBOM[Item ID],$A72)>0)*($H$4>0),$C$4&", ","") & IF((COUNTIFS(TableBOM[Product ID],$D$5,TableBOM[Item ID],$A72)>0)*($H$5>0),$C$5&", ","") & IF((COUNTIFS(TableBOM[Product ID],$D$6,TableBOM[Item ID],$A72)>0)*($H$6>0),$C$6&", ","") & IF((COUNTIFS(TableBOM[Product ID],$D$7,TableBOM[Item ID],$A72)>0)*($H$7>0),$C$7&", ","") & IF((COUNTIFS(TableBOM[Product ID],$D$8,TableBOM[Item ID],$A72)>0)*($H$8>0),$C$8&", ",""),LEN(IF((COUNTIFS(TableBOM[Product ID],$D$3,TableBOM[Item ID],$A72)>0)*($H$3>0),$C$3&", ","") & IF((COUNTIFS(TableBOM[Product ID],$D$4,TableBOM[Item ID],$A72)>0)*($H$4>0),$C$4&", ","") & IF((COUNTIFS(TableBOM[Product ID],$D$5,TableBOM[Item ID],$A72)>0)*($H$5>0),$C$5&", ","") & IF((COUNTIFS(TableBOM[Product ID],$D$6,TableBOM[Item ID],$A72)>0)*($H$6>0),$C$6&", ","") & IF((COUNTIFS(TableBOM[Product ID],$D$7,TableBOM[Item ID],$A72)>0)*($H$7>0),$C$7&", ","") & IF((COUNTIFS(TableBOM[Product ID],$D$8,TableBOM[Item ID],$A72)>0)*($H$8>0),$C$8&", ",""))-2),"") -> S-45, S 43 25MM, HELLO HAIR COLOR | I72: =IF(E72=0,"Not needed",IF(G72<0,"SHORTAGE",IF(G72<F72*0.1,"LOW","OK"))) -> SHORTAGE
A73: 45 | B73: CARTON | C73: 30X150 3Ply | D73: PCS | E73: =SUMPRODUCT((TableBOM[Item ID]=A73)*TableBOM[Per 1000 Units]*(1+TableBOM[Scrap %])*SUMIF($D$3:$D$8,TableBOM[Product ID],$H$3:$H$8)/1000) -> 0 | F73: =IFERROR(INDEX(TableInventory[Store Balance],MATCH(A73,TableInventory[Item ID],0)),0)+IFERROR(INDEX(TableInventory[Work In Process],MATCH(A73,TableInventory[Item ID],0)),0) -> 460 | G73: =F73-E73 -> 460 | H73: =IF(LEN(IF((COUNTIFS(TableBOM[Product ID],$D$3,TableBOM[Item ID],$A73)>0)*($H$3>0),$C$3&", ","") & IF((COUNTIFS(TableBOM[Product ID],$D$4,TableBOM[Item ID],$A73)>0)*($H$4>0),$C$4&", ","") & IF((COUNTIFS(TableBOM[Product ID],$D$5,TableBOM[Item ID],$A73)>0)*($H$5>0),$C$5&", ","") & IF((COUNTIFS(TableBOM[Product ID],$D$6,TableBOM[Item ID],$A73)>0)*($H$6>0),$C$6&", ","") & IF((COUNTIFS(TableBOM[Product ID],$D$7,TableBOM[Item ID],$A73)>0)*($H$7>0),$C$7&", ","") & IF((COUNTIFS(TableBOM[Product ID],$D$8,TableBOM[Item ID],$A73)>0)*($H$8>0),$C$8&", ",""))>1,LEFT(IF((COUNTIFS(TableBOM[Product ID],$D$3,TableBOM[Item ID],$A73)>0)*($H$3>0),$C$3&", ","") & IF((COUNTIFS(TableBOM[Product ID],$D$4,TableBOM[Item ID],$A73)>0)*($H$4>0),$C$4&", ","") & IF((COUNTIFS(TableBOM[Product ID],$D$5,TableBOM[Item ID],$A73)>0)*($H$5>0),$C$5&", ","") & IF((COUNTIFS(TableBOM[Product ID],$D$6,TableBOM[Item ID],$A73)>0)*($H$6>0),$C$6&", ","") & IF((COUNTIFS(TableBOM[Product ID],$D$7,TableBOM[Item ID],$A73)>0)*($H$7>0),$C$7&", ","") & IF((COUNTIFS(TableBOM[Product ID],$D$8,TableBOM[Item ID],$A73)>0)*($H$8>0),$C$8&", ",""),LEN(IF((COUNTIFS(TableBOM[Product ID],$D$3,TableBOM[Item ID],$A73)>0)*($H$3>0),$C$3&", ","") & IF((COUNTIFS(TableBOM[Product ID],$D$4,TableBOM[Item ID],$A73)>0)*($H$4>0),$C$4&", ","") & IF((COUNTIFS(TableBOM[Product ID],$D$5,TableBOM[Item ID],$A73)>0)*($H$5>0),$C$5&", ","") & IF((COUNTIFS(TableBOM[Product ID],$D$6,TableBOM[Item ID],$A73)>0)*($H$6>0),$C$6&", ","") & IF((COUNTIFS(TableBOM[Product ID],$D$7,TableBOM[Item ID],$A73)>0)*($H$7>0),$C$7&", ","") & IF((COUNTIFS(TableBOM[Product ID],$D$8,TableBOM[Item ID],$A73)>0)*($H$8>0),$C$8&", ",""))-2),"") | I73: =IF(E73=0,"Not needed",IF(G73<0,"SHORTAGE",IF(G73<F73*0.1,"LOW","OK"))) -> Not needed
A74: 3988 | B74: CARTON | C74: 35x165 5ply | D74: PCS | E74: =SUMPRODUCT((TableBOM[Item ID]=A74)*TableBOM[Per 1000 Units]*(1+TableBOM[Scrap %])*SUMIF($D$3:$D$8,TableBOM[Product ID],$H$3:$H$8)/1000) -> 88.6578 | F74: =IFERROR(INDEX(TableInventory[Store Balance],MATCH(A74,TableInventory[Item ID],0)),0)+IFERROR(INDEX(TableInventory[Work In Process],MATCH(A74,TableInventory[Item ID],0)),0) -> 349 | G74: =F74-E74 -> 260.3422 | H74: =IF(LEN(IF((COUNTIFS(TableBOM[Product ID],$D$3,TableBOM[Item ID],$A74)>0)*($H$3>0),$C$3&", ","") & IF((COUNTIFS(TableBOM[Product ID],$D$4,TableBOM[Item ID],$A74)>0)*($H$4>0),$C$4&", ","") & IF((COUNTIFS(TableBOM[Product ID],$D$5,TableBOM[Item ID],$A74)>0)*($H$5>0),$C$5&", ","") & IF((COUNTIFS(TableBOM[Product ID],$D$6,TableBOM[Item ID],$A74)>0)*($H$6>0),$C$6&", ","") & IF((COUNTIFS(TableBOM[Product ID],$D$7,TableBOM[Item ID],$A74)>0)*($H$7>0),$C$7&", ","") & IF((COUNTIFS(TableBOM[Product ID],$D$8,TableBOM[Item ID],$A74)>0)*($H$8>0),$C$8&", ",""))>1,LEFT(IF((COUNTIFS(TableBOM[Product ID],$D$3,TableBOM[Item ID],$A74)>0)*($H$3>0),$C$3&", ","") & IF((COUNTIFS(TableBOM[Product ID],$D$4,TableBOM[Item ID],$A74)>0)*($H$4>0),$C$4&", ","") & IF((COUNTIFS(TableBOM[Product ID],$D$5,TableBOM[Item ID],$A74)>0)*($H$5>0),$C$5&", ","") & IF((COUNTIFS(TableBOM[Product ID],$D$6,TableBOM[Item ID],$A74)>0)*($H$6>0),$C$6&", ","") & IF((COUNTIFS(TableBOM[Product ID],$D$7,TableBOM[Item ID],$A74)>0)*($H$7>0),$C$7&", ","") & IF((COUNTIFS(TableBOM[Product ID],$D$8,TableBOM[Item ID],$A74)>0)*($H$8>0),$C$8&", ",""),LEN(IF((COUNTIFS(TableBOM[Product ID],$D$3,TableBOM[Item ID],$A74)>0)*($H$3>0),$C$3&", ","") & IF((COUNTIFS(TableBOM[Product ID],$D$4,TableBOM[Item ID],$A74)>0)*($H$4>0),$C$4&", ","") & IF((COUNTIFS(TableBOM[Product ID],$D$5,TableBOM[Item ID],$A74)>0)*($H$5>0),$C$5&", ","") & IF((COUNTIFS(TableBOM[Product ID],$D$6,TableBOM[Item ID],$A74)>0)*($H$6>0),$C$6&", ","") & IF((COUNTIFS(TableBOM[Product ID],$D$7,TableBOM[Item ID],$A74)>0)*($H$7>0),$C$7&", ","") & IF((COUNTIFS(TableBOM[Product ID],$D$8,TableBOM[Item ID],$A74)>0)*($H$8>0),$C$8&", ",""))-2),"") -> V- HC BROWN | I74: =IF(E74=0,"Not needed",IF(G74<0,"SHORTAGE",IF(G74<F74*0.1,"LOW","OK"))) -> OK
A75: 5977 | B75: CARTON | C75: MASTER CARTON 38"X24"X15.5" | D75: PCS | E75: =SUMPRODUCT((TableBOM[Item ID]=A75)*TableBOM[Per 1000 Units]*(1+TableBOM[Scrap %])*SUMIF($D$3:$D$8,TableBOM[Product ID],$H$3:$H$8)/1000) -> 0 | F75: =IFERROR(INDEX(TableInventory[Store Balance],MATCH(A75,TableInventory[Item ID],0)),0)+IFERROR(INDEX(TableInventory[Work In Process],MATCH(A75,TableInventory[Item ID],0)),0) -> 61 | G75: =F75-E75 -> 61 | H75: =IF(LEN(IF((COUNTIFS(TableBOM[Product ID],$D$3,TableBOM[Item ID],$A75)>0)*($H$3>0),$C$3&", ","") & IF((COUNTIFS(TableBOM[Product ID],$D$4,TableBOM[Item ID],$A75)>0)*($H$4>0),$C$4&", ","") & IF((COUNTIFS(TableBOM[Product ID],$D$5,TableBOM[Item ID],$A75)>0)*($H$5>0),$C$5&", ","") & IF((COUNTIFS(TableBOM[Product ID],$D$6,TableBOM[Item ID],$A75)>0)*($H$6>0),$C$6&", ","") & IF((COUNTIFS(TableBOM[Product ID],$D$7,TableBOM[Item ID],$A75)>0)*($H$7>0),$C$7&", ","") & IF((COUNTIFS(TableBOM[Product ID],$D$8,TableBOM[Item ID],$A75)>0)*($H$8>0),$C$8&", ",""))>1,LEFT(IF((COUNTIFS(TableBOM[Product ID],$D$3,TableBOM[Item ID],$A75)>0)*($H$3>0),$C$3&", ","") & IF((COUNTIFS(TableBOM[Product ID],$D$4,TableBOM[Item ID],$A75)>0)*($H$4>0),$C$4&", ","") & IF((COUNTIFS(TableBOM[Product ID],$D$5,TableBOM[Item ID],$A75)>0)*($H$5>0),$C$5&", ","") & IF((COUNTIFS(TableBOM[Product ID],$D$6,TableBOM[Item ID],$A75)>0)*($H$6>0),$C$6&", ","") & IF((COUNTIFS(TableBOM[Product ID],$D$7,TableBOM[Item ID],$A75)>0)*($H$7>0),$C$7&", ","") & IF((COUNTIFS(TableBOM[Product ID],$D$8,TableBOM[Item ID],$A75)>0)*($H$8>0),$C$8&", ",""),LEN(IF((COUNTIFS(TableBOM[Product ID],$D$3,TableBOM[Item ID],$A75)>0)*($H$3>0),$C$3&", ","") & IF((COUNTIFS(TableBOM[Product ID],$D$4,TableBOM[Item ID],$A75)>0)*($H$4>0),$C$4&", ","") & IF((COUNTIFS(TableBOM[Product ID],$D$5,TableBOM[Item ID],$A75)>0)*($H$5>0),$C$5&", ","") & IF((COUNTIFS(TableBOM[Product ID],$D$6,TableBOM[Item ID],$A75)>0)*($H$6>0),$C$6&", ","") & IF((COUNTIFS(TableBOM[Product ID],$D$7,TableBOM[Item ID],$A75)>0)*($H$7>0),$C$7&", ","") & IF((COUNTIFS(TableBOM[Product ID],$D$8,TableBOM[Item ID],$A75)>0)*($H$8>0),$C$8&", ",""))-2),"") | I75: =IF(E75=0,"Not needed",IF(G75<0,"SHORTAGE",IF(G75<F75*0.1,"LOW","OK"))) -> Not needed
A76: 3635 | B76: TAPE | C76: PACKING TAPE 2" OF 60 YARDS | D76: PCS | E76: =SUMPRODUCT((TableBOM[Item ID]=A76)*TableBOM[Per 1000 Units]*(1+TableBOM[Scrap %])*SUMIF($D$3:$D$8,TableBOM[Product ID],$H$3:$H$8)/1000) -> 392.34284 | F76: =IFERROR(INDEX(TableInventory[Store Balance],MATCH(A76,TableInventory[Item ID],0)),0)+IFERROR(INDEX(TableInventory[Work In Process],MATCH(A76,TableInventory[Item ID],0)),0) -> 513 | G76: =F76-E76 -> 120.65716 | H76: =IF(LEN(IF((COUNTIFS(TableBOM[Product ID],$D$3,TableBOM[Item ID],$A76)>0)*($H$3>0),$C$3&", ","") & IF((COUNTIFS(TableBOM[Product ID],$D$4,TableBOM[Item ID],$A76)>0)*($H$4>0),$C$4&", ","") & IF((COUNTIFS(TableBOM[Product ID],$D$5,TableBOM[Item ID],$A76)>0)*($H$5>0),$C$5&", ","") & IF((COUNTIFS(TableBOM[Product ID],$D$6,TableBOM[Item ID],$A76)>0)*($H$6>0),$C$6&", ","") & IF((COUNTIFS(TableBOM[Product ID],$D$7,TableBOM[Item ID],$A76)>0)*($H$7>0),$C$7&", ","") & IF((COUNTIFS(TableBOM[Product ID],$D$8,TableBOM[Item ID],$A76)>0)*($H$8>0),$C$8&", ",""))>1,LEFT(IF((COUNTIFS(TableBOM[Product ID],$D$3,TableBOM[Item ID],$A76)>0)*($H$3>0),$C$3&", ","") & IF((COUNTIFS(TableBOM[Product ID],$D$4,TableBOM[Item ID],$A76)>0)*($H$4>0),$C$4&", ","") & IF((COUNTIFS(TableBOM[Product ID],$D$5,TableBOM[Item ID],$A76)>0)*($H$5>0),$C$5&", ","") & IF((COUNTIFS(TableBOM[Product ID],$D$6,TableBOM[Item ID],$A76)>0)*($H$6>0),$C$6&", ","") & IF((COUNTIFS(TableBOM[Product ID],$D$7,TableBOM[Item ID],$A76)>0)*($H$7>0),$C$7&", ","") & IF((COUNTIFS(TableBOM[Product ID],$D$8,TableBOM[Item ID],$A76)>0)*($H$8>0),$C$8&", ",""),LEN(IF((COUNTIFS(TableBOM[Product ID],$D$3,TableBOM[Item ID],$A76)>0)*($H$3>0),$C$3&", ","") & IF((COUNTIFS(TableBOM[Product ID],$D$4,TableBOM[Item ID],$A76)>0)*($H$4>0),$C$4&", ","") & IF((COUNTIFS(TableBOM[Product ID],$D$5,TableBOM[Item ID],$A76)>0)*($H$5>0),$C$5&", ","") & IF((COUNTIFS(TableBOM[Product ID],$D$6,TableBOM[Item ID],$A76)>0)*($H$6>0),$C$6&", ","") & IF((COUNTIFS(TableBOM[Product ID],$D$7,TableBOM[Item ID],$A76)>0)*($H$7>0),$C$7&", ","") & IF((COUNTIFS(TableBOM[Product ID],$D$8,TableBOM[Item ID],$A76)>0)*($H$8>0),$C$8&", ",""))-2),"") -> ECZEMUS OINTMENT 0.03% 10G, S-45, S 43 25MM, VINCE NURTURAL, HELLO HAIR COLOR, V- HC BROWN | I76: =IF(E76=0,"Not needed",IF(G76<0,"SHORTAGE",IF(G76<F76*0.1,"LOW","OK"))) -> OK
A77: 190 | B77: THINNER | C77: THINNER FOR LACQUER SOL R/C | D77: L | E77: =SUMPRODUCT((TableBOM[Item ID]=A77)*TableBOM[Per 1000 Units]*(1+TableBOM[Scrap %])*SUMIF($D$3:$D$8,TableBOM[Product ID],$H$3:$H$8)/1000) -> 1.65 | F77: =IFERROR(INDEX(TableInventory[Store Balance],MATCH(A77,TableInventory[Item ID],0)),0)+IFERROR(INDEX(TableInventory[Work In Process],MATCH(A77,TableInventory[Item ID],0)),0) -> 150 | G77: =F77-E77 -> 148.35 | H77: =IF(LEN(IF((COUNTIFS(TableBOM[Product ID],$D$3,TableBOM[Item ID],$A77)>0)*($H$3>0),$C$3&", ","") & IF((COUNTIFS(TableBOM[Product ID],$D$4,TableBOM[Item ID],$A77)>0)*($H$4>0),$C$4&", ","") & IF((COUNTIFS(TableBOM[Product ID],$D$5,TableBOM[Item ID],$A77)>0)*($H$5>0),$C$5&", ","") & IF((COUNTIFS(TableBOM[Product ID],$D$6,TableBOM[Item ID],$A77)>0)*($H$6>0),$C$6&", ","") & IF((COUNTIFS(TableBOM[Product ID],$D$7,TableBOM[Item ID],$A77)>0)*($H$7>0),$C$7&", ","") & IF((COUNTIFS(TableBOM[Product ID],$D$8,TableBOM[Item ID],$A77)>0)*($H$8>0),$C$8&", ",""))>1,LEFT(IF((COUNTIFS(TableBOM[Product ID],$D$3,TableBOM[Item ID],$A77)>0)*($H$3>0),$C$3&", ","") & IF((COUNTIFS(TableBOM[Product ID],$D$4,TableBOM[Item ID],$A77)>0)*($H$4>0),$C$4&", ","") & IF((COUNTIFS(TableBOM[Product ID],$D$5,TableBOM[Item ID],$A77)>0)*($H$5>0),$C$5&", ","") & IF((COUNTIFS(TableBOM[Product ID],$D$6,TableBOM[Item ID],$A77)>0)*($H$6>0),$C$6&", ","") & IF((COUNTIFS(TableBOM[Product ID],$D$7,TableBOM[Item ID],$A77)>0)*($H$7>0),$C$7&", ","") & IF((COUNTIFS(TableBOM[Product ID],$D$8,TableBOM[Item ID],$A77)>0)*($H$8>0),$C$8&", ",""),LEN(IF((COUNTIFS(TableBOM[Product ID],$D$3,TableBOM[Item ID],$A77)>0)*($H$3>0),$C$3&", ","") & IF((COUNTIFS(TableBOM[Product ID],$D$4,TableBOM[Item ID],$A77)>0)*($H$4>0),$C$4&", ","") & IF((COUNTIFS(TableBOM[Product ID],$D$5,TableBOM[Item ID],$A77)>0)*($H$5>0),$C$5&", ","") & IF((COUNTIFS(TableBOM[Product ID],$D$6,TableBOM[Item ID],$A77)>0)*($H$6>0),$C$6&", ","") & IF((COUNTIFS(TableBOM[Product ID],$D$7,TableBOM[Item ID],$A77)>0)*($H$7>0),$C$7&", ","") & IF((COUNTIFS(TableBOM[Product ID],$D$8,TableBOM[Item ID],$A77)>0)*($H$8>0),$C$8&", ",""))-2),"") -> ECZEMUS OINTMENT 0.03% 10G | I77: =IF(E77=0,"Not needed",IF(G77<0,"SHORTAGE",IF(G77<F77*0.1,"LOW","OK"))) -> OK
A78: 191 | B78: THINNER | C78: THINNER LACQUER SOL EPOXY | D78: L | E78: =SUMPRODUCT((TableBOM[Item ID]=A78)*TableBOM[Per 1000 Units]*(1+TableBOM[Scrap %])*SUMIF($D$3:$D$8,TableBOM[Product ID],$H$3:$H$8)/1000) -> 0 | F78: =IFERROR(INDEX(TableInventory[Store Balance],MATCH(A78,TableInventory[Item ID],0)),0)+IFERROR(INDEX(TableInventory[Work In Process],MATCH(A78,TableInventory[Item ID],0)),0) -> 75 | G78: =F78-E78 -> 75 | H78: =IF(LEN(IF((COUNTIFS(TableBOM[Product ID],$D$3,TableBOM[Item ID],$A78)>0)*($H$3>0),$C$3&", ","") & IF((COUNTIFS(TableBOM[Product ID],$D$4,TableBOM[Item ID],$A78)>0)*($H$4>0),$C$4&", ","") & IF((COUNTIFS(TableBOM[Product ID],$D$5,TableBOM[Item ID],$A78)>0)*($H$5>0),$C$5&", ","") & IF((COUNTIFS(TableBOM[Product ID],$D$6,TableBOM[Item ID],$A78)>0)*($H$6>0),$C$6&", ","") & IF((COUNTIFS(TableBOM[Product ID],$D$7,TableBOM[Item ID],$A78)>0)*($H$7>0),$C$7&", ","") & IF((COUNTIFS(TableBOM[Product ID],$D$8,TableBOM[Item ID],$A78)>0)*($H$8>0),$C$8&", ",""))>1,LEFT(IF((COUNTIFS(TableBOM[Product ID],$D$3,TableBOM[Item ID],$A78)>0)*($H$3>0),$C$3&", ","") & IF((COUNTIFS(TableBOM[Product ID],$D$4,TableBOM[Item ID],$A78)>0)*($H$4>0),$C$4&", ","") & IF((COUNTIFS(TableBOM[Product ID],$D$5,TableBOM[Item ID],$A78)>0)*($H$5>0),$C$5&", ","") & IF((COUNTIFS(TableBOM[Product ID],$D$6,TableBOM[Item ID],$A78)>0)*($H$6>0),$C$6&", ","") & IF((COUNTIFS(TableBOM[Product ID],$D$7,TableBOM[Item ID],$A78)>0)*($H$7>0),$C$7&", ","") & IF((COUNTIFS(TableBOM[Product ID],$D$8,TableBOM[Item ID],$A78)>0)*($H$8>0),$C$8&", ",""),LEN(IF((COUNTIFS(TableBOM[Product ID],$D$3,TableBOM[Item ID],$A78)>0)*($H$3>0),$C$3&", ","") & IF((COUNTIFS(TableBOM[Product ID],$D$4,TableBOM[Item ID],$A78)>0)*($H$4>0),$C$4&", ","") & IF((COUNTIFS(TableBOM[Product ID],$D$5,TableBOM[Item ID],$A78)>0)*($H$5>0),$C$5&", ","") & IF((COUNTIFS(TableBOM[Product ID],$D$6,TableBOM[Item ID],$A78)>0)*($H$6>0),$C$6&", ","") & IF((COUNTIFS(TableBOM[Product ID],$D$7,TableBOM[Item ID],$A78)>0)*($H$7>0),$C$7&", ","") & IF((COUNTIFS(TableBOM[Product ID],$D$8,TableBOM[Item ID],$A78)>0)*($H$8>0),$C$8&", ",""))-2),"") | I78: =IF(E78=0,"Not needed",IF(G78<0,"SHORTAGE",IF(G78<F78*0.1,"LOW","OK"))) -> Not needed
A79: 2680 | B79: PET RESIN | C79: PET RESIN A-84 | D79: kg | E79: =SUMPRODUCT((TableBOM[Item ID]=A79)*TableBOM[Per 1000 Units]*(1+TableBOM[Scrap %])*SUMIF($D$3:$D$8,TableBOM[Product ID],$H$3:$H$8)/1000) -> 0 | F79: =IFERROR(INDEX(TableInventory[Store Balance],MATCH(A79,TableInventory[Item ID],0)),0)+IFERROR(INDEX(TableInventory[Work In Process],MATCH(A79,TableInventory[Item ID],0)),0) -> 2000 | G79: =F79-E79 -> 2000 | H79: =IF(LEN(IF((COUNTIFS(TableBOM[Product ID],$D$3,TableBOM[Item ID],$A79)>0)*($H$3>0),$C$3&", ","") & IF((COUNTIFS(TableBOM[Product ID],$D$4,TableBOM[Item ID],$A79)>0)*($H$4>0),$C$4&", ","") & IF((COUNTIFS(TableBOM[Product ID],$D$5,TableBOM[Item ID],$A79)>0)*($H$5>0),$C$5&", ","") & IF((COUNTIFS(TableBOM[Product ID],$D$6,TableBOM[Item ID],$A79)>0)*($H$6>0),$C$6&", ","") & IF((COUNTIFS(TableBOM[Product ID],$D$7,TableBOM[Item ID],$A79)>0)*($H$7>0),$C$7&", ","") & IF((COUNTIFS(TableBOM[Product ID],$D$8,TableBOM[Item ID],$A79)>0)*($H$8>0),$C$8&", ",""))>1,LEFT(IF((COUNTIFS(TableBOM[Product ID],$D$3,TableBOM[Item ID],$A79)>0)*($H$3>0),$C$3&", ","") & IF((COUNTIFS(TableBOM[Product ID],$D$4,TableBOM[Item ID],$A79)>0)*($H$4>0),$C$4&", ","") & IF((COUNTIFS(TableBOM[Product ID],$D$5,TableBOM[Item ID],$A79)>0)*($H$5>0),$C$5&", ","") & IF((COUNTIFS(TableBOM[Product ID],$D$6,TableBOM[Item ID],$A79)>0)*($H$6>0),$C$6&", ","") & IF((COUNTIFS(TableBOM[Product ID],$D$7,TableBOM[Item ID],$A79)>0)*($H$7>0),$C$7&", ","") & IF((COUNTIFS(TableBOM[Product ID],$D$8,TableBOM[Item ID],$A79)>0)*($H$8>0),$C$8&", ",""),LEN(IF((COUNTIFS(TableBOM[Product ID],$D$3,TableBOM[Item ID],$A79)>0)*($H$3>0),$C$3&", ","") & IF((COUNTIFS(TableBOM[Product ID],$D$4,TableBOM[Item ID],$A79)>0)*($H$4>0),$C$4&", ","") & IF((COUNTIFS(TableBOM[Product ID],$D$5,TableBOM[Item ID],$A79)>0)*($H$5>0),$C$5&", ","") & IF((COUNTIFS(TableBOM[Product ID],$D$6,TableBOM[Item ID],$A79)>0)*($H$6>0),$C$6&", ","") & IF((COUNTIFS(TableBOM[Product ID],$D$7,TableBOM[Item ID],$A79)>0)*($H$7>0),$C$7&", ","") & IF((COUNTIFS(TableBOM[Product ID],$D$8,TableBOM[Item ID],$A79)>0)*($H$8>0),$C$8&", ",""))-2),"") | I79: =IF(E79=0,"Not needed",IF(G79<0,"SHORTAGE",IF(G79<F79*0.1,"LOW","OK"))) -> Not needed
A80: 3492 | B80: MASTER BATCH | C80: MASTER BATCH (PA M27) GREEN | D80: kg | E80: =SUMPRODUCT((TableBOM[Item ID]=A80)*TableBOM[Per 1000 Units]*(1+TableBOM[Scrap %])*SUMIF($D$3:$D$8,TableBOM[Product ID],$H$3:$H$8)/1000) -> 0 | F80: =IFERROR(INDEX(TableInventory[Store Balance],MATCH(A80,TableInventory[Item ID],0)),0)+IFERROR(INDEX(TableInventory[Work In Process],MATCH(A80,TableInventory[Item ID],0)),0) -> 75 | G80: =F80-E80 -> 75 | H80: =IF(LEN(IF((COUNTIFS(TableBOM[Product ID],$D$3,TableBOM[Item ID],$A80)>0)*($H$3>0),$C$3&", ","") & IF((COUNTIFS(TableBOM[Product ID],$D$4,TableBOM[Item ID],$A80)>0)*($H$4>0),$C$4&", ","") & IF((COUNTIFS(TableBOM[Product ID],$D$5,TableBOM[Item ID],$A80)>0)*($H$5>0),$C$5&", ","") & IF((COUNTIFS(TableBOM[Product ID],$D$6,TableBOM[Item ID],$A80)>0)*($H$6>0),$C$6&", ","") & IF((COUNTIFS(TableBOM[Product ID],$D$7,TableBOM[Item ID],$A80)>0)*($H$7>0),$C$7&", ","") & IF((COUNTIFS(TableBOM[Product ID],$D$8,TableBOM[Item ID],$A80)>0)*($H$8>0),$C$8&", ",""))>1,LEFT(IF((COUNTIFS(TableBOM[Product ID],$D$3,TableBOM[Item ID],$A80)>0)*($H$3>0),$C$3&", ","") & IF((COUNTIFS(TableBOM[Product ID],$D$4,TableBOM[Item ID],$A80)>0)*($H$4>0),$C$4&", ","") & IF((COUNTIFS(TableBOM[Product ID],$D$5,TableBOM[Item ID],$A80)>0)*($H$5>0),$C$5&", ","") & IF((COUNTIFS(TableBOM[Product ID],$D$6,TableBOM[Item ID],$A80)>0)*($H$6>0),$C$6&", ","") & IF((COUNTIFS(TableBOM[Product ID],$D$7,TableBOM[Item ID],$A80)>0)*($H$7>0),$C$7&", ","") & IF((COUNTIFS(TableBOM[Product ID],$D$8,TableBOM[Item ID],$A80)>0)*($H$8>0),$C$8&", ",""),LEN(IF((COUNTIFS(TableBOM[Product ID],$D$3,TableBOM[Item ID],$A80)>0)*($H$3>0),$C$3&", ","") & IF((COUNTIFS(TableBOM[Product ID],$D$4,TableBOM[Item ID],$A80)>0)*($H$4>0),$C$4&", ","") & IF((COUNTIFS(TableBOM[Product ID],$D$5,TableBOM[Item ID],$A80)>0)*($H$5>0),$C$5&", ","") & IF((COUNTIFS(TableBOM[Product ID],$D$6,TableBOM[Item ID],$A80)>0)*($H$6>0),$C$6&", ","") & IF((COUNTIFS(TableBOM[Product ID],$D$7,TableBOM[Item ID],$A80)>0)*($H$7>0),$C$7&", ","") & IF((COUNTIFS(TableBOM[Product ID],$D$8,TableBOM[Item ID],$A80)>0)*($H$8>0),$C$8&", ",""))-2),"") | I80: =IF(E80=0,"Not needed",IF(G80<0,"SHORTAGE",IF(G80<F80*0.1,"LOW","OK"))) -> Not needed
A81: 4002 | B81: MASTER BATCH | C81: MASTER BATCH YELLOW CMN# 3087 | D81: kg | E81: =SUMPRODUCT((TableBOM[Item ID]=A81)*TableBOM[Per 1000 Units]*(1+TableBOM[Scrap %])*SUMIF($D$3:$D$8,TableBOM[Product ID],$H$3:$H$8)/1000) -> 0 | F81: =IFERROR(INDEX(TableInventory[Store Balance],MATCH(A81,TableInventory[Item ID],0)),0)+IFERROR(INDEX(TableInventory[Work In Process],MATCH(A81,TableInventory[Item ID],0)),0) -> 100 | G81: =F81-E81 -> 100 | H81: =IF(LEN(IF((COUNTIFS(TableBOM[Product ID],$D$3,TableBOM[Item ID],$A81)>0)*($H$3>0),$C$3&", ","") & IF((COUNTIFS(TableBOM[Product ID],$D$4,TableBOM[Item ID],$A81)>0)*($H$4>0),$C$4&", ","") & IF((COUNTIFS(TableBOM[Product ID],$D$5,TableBOM[Item ID],$A81)>0)*($H$5>0),$C$5&", ","") & IF((COUNTIFS(TableBOM[Product ID],$D$6,TableBOM[Item ID],$A81)>0)*($H$6>0),$C$6&", ","") & IF((COUNTIFS(TableBOM[Product ID],$D$7,TableBOM[Item ID],$A81)>0)*($H$7>0),$C$7&", ","") & IF((COUNTIFS(TableBOM[Product ID],$D$8,TableBOM[Item ID],$A81)>0)*($H$8>0),$C$8&", ",""))>1,LEFT(IF((COUNTIFS(TableBOM[Product ID],$D$3,TableBOM[Item ID],$A81)>0)*($H$3>0),$C$3&", ","") & IF((COUNTIFS(TableBOM[Product ID],$D$4,TableBOM[Item ID],$A81)>0)*($H$4>0),$C$4&", ","") & IF((COUNTIFS(TableBOM[Product ID],$D$5,TableBOM[Item ID],$A81)>0)*($H$5>0),$C$5&", ","") & IF((COUNTIFS(TableBOM[Product ID],$D$6,TableBOM[Item ID],$A81)>0)*($H$6>0),$C$6&", ","") & IF((COUNTIFS(TableBOM[Product ID],$D$7,TableBOM[Item ID],$A81)>0)*($H$7>0),$C$7&", ","") & IF((COUNTIFS(TableBOM[Product ID],$D$8,TableBOM[Item ID],$A81)>0)*($H$8>0),$C$8&", ",""),LEN(IF((COUNTIFS(TableBOM[Product ID],$D$3,TableBOM[Item ID],$A81)>0)*($H$3>0),$C$3&", ","") & IF((COUNTIFS(TableBOM[Product ID],$D$4,TableBOM[Item ID],$A81)>0)*($H$4>0),$C$4&", ","") & IF((COUNTIFS(TableBOM[Product ID],$D$5,TableBOM[Item ID],$A81)>0)*($H$5>0),$C$5&", ","") & IF((COUNTIFS(TableBOM[Product ID],$D$6,TableBOM[Item ID],$A81)>0)*($H$6>0),$C$6&", ","") & IF((COUNTIFS(TableBOM[Product ID],$D$7,TableBOM[Item ID],$A81)>0)*($H$7>0),$C$7&", ","") & IF((COUNTIFS(TableBOM[Product ID],$D$8,TableBOM[Item ID],$A81)>0)*($H$8>0),$C$8&", ",""))-2),"") | I81: =IF(E81=0,"Not needed",IF(G81<0,"SHORTAGE",IF(G81<F81*0.1,"LOW","OK"))) -> Not needed
... A93: 3043 | B93: PACKING | C93: PLASTIC DOORI | D93: ROLL | E93: =SUMPRODUCT((TableBOM[Item ID]=A93)*TableBOM[Per 1000 Units]*(1+TableBOM[Scrap %])*SUMIF($D$3:$D$8,TableBOM[Product ID],$H$3:$H$8)/1000) -> 0 | F93: =IFERROR(INDEX(TableInventory[Store Balance],MATCH(A93,TableInventory[Item ID],0)),0)+IFERROR(INDEX(TableInventory[Work In Process],MATCH(A93,TableInventory[Item ID],0)),0) -> 0 | G93: =F93-E93 -> 0 | H93: =IF(LEN(IF((COUNTIFS(TableBOM[Product ID],$D$3,TableBOM[Item ID],$A93)>0)*($H$3>0),$C$3&", ","") & IF((COUNTIFS(TableBOM[Product ID],$D$4,TableBOM[Item ID],$A93)>0)*($H$4>0),$C$4&", ","") & IF((COUNTIFS(TableBOM[Product ID],$D$5,TableBOM[Item ID],$A93)>0)*($H$5>0),$C$5&", ","") & IF((COUNTIFS(TableBOM[Product ID],$D$6,TableBOM[Item ID],$A93)>0)*($H$6>0),$C$6&", ","") & IF((COUNTIFS(TableBOM[Product ID],$D$7,TableBOM[Item ID],$A93)>0)*($H$7>0),$C$7&", ","") & IF((COUNTIFS(TableBOM[Product ID],$D$8,TableBOM[Item ID],$A93)>0)*($H$8>0),$C$8&", ",""))>1,LEFT(IF((COUNTIFS(TableBOM[Product ID],$D$3,TableBOM[Item ID],$A93)>0)*($H$3>0),$C$3&", ","") & IF((COUNTIFS(TableBOM[Product ID],$D$4,TableBOM[Item ID],$A93)>0)*($H$4>0),$C$4&", ","") & IF((COUNTIFS(TableBOM[Product ID],$D$5,TableBOM[Item ID],$A93)>0)*($H$5>0),$C$5&", ","") & IF((COUNTIFS(TableBOM[Product ID],$D$6,TableBOM[Item ID],$A93)>0)*($H$6>0),$C$6&", ","") & IF((COUNTIFS(TableBOM[Product ID],$D$7,TableBOM[Item ID],$A93)>0)*($H$7>0),$C$7&", ","") & IF((COUNTIFS(TableBOM[Product ID],$D$8,TableBOM[Item ID],$A93)>0)*($H$8>0),$C$8&", ",""),LEN(IF((COUNTIFS(TableBOM[Product ID],$D$3,TableBOM[Item ID],$A93)>0)*($H$3>0),$C$3&", ","") & IF((COUNTIFS(TableBOM[Product ID],$D$4,TableBOM[Item ID],$A93)>0)*($H$4>0),$C$4&", ","") & IF((COUNTIFS(TableBOM[Product ID],$D$5,TableBOM[Item ID],$A93)>0)*($H$5>0),$C$5&", ","") & IF((COUNTIFS(TableBOM[Product ID],$D$6,TableBOM[Item ID],$A93)>0)*($H$6>0),$C$6&", ","") & IF((COUNTIFS(TableBOM[Product ID],$D$7,TableBOM[Item ID],$A93)>0)*($H$7>0),$C$7&", ","") & IF((COUNTIFS(TableBOM[Product ID],$D$8,TableBOM[Item ID],$A93)>0)*($H$8>0),$C$8&", ",""))-2),"") | I93: =IF(E93=0,"Not needed",IF(G93<0,"SHORTAGE",IF(G93<F93*0.1,"LOW","OK"))) -> Not needed
A96: JULY 2026 PET Required Pet Orders
A97: Dia | B97: Customer | C97: Product Name | D97: Product ID | E97: Job Order # | F97: Required Qty | G97: Produced | H97: Remaining Balance | I97: Priority
A98: 120 ml | B98: Samsol International Private Limited | C98: PET BOTTLE SMALL (120ML) YELLOW | D98: 8005 | E98: 336 & 337 | F98: =INDEX(Tubex_Dashboard!$G$11:$G$61,MATCH(MRP!D98,Tubex_Dashboard!$F$11:$F$61,0)) -> 19840 | G98: =INDEX(Tubex_Dashboard!$H$11:$H$100,MATCH(MRP!D98,Tubex_Dashboard!$F$11:$F$100,0)) -> 0 | H98: =F98-G98 -> 19840
A99: 150 ml | B99: Alpha Labs PVT LTD | C99: TRANSPARENT BOTTLE 150ML | D99: 8001 | E99: 319 | F99: =INDEX(Tubex_Dashboard!$G$11:$G$61,MATCH(MRP!D99,Tubex_Dashboard!$F$11:$F$61,0)) -> 153167 | G99: =INDEX(Tubex_Dashboard!$H$11:$H$100,MATCH(MRP!D99,Tubex_Dashboard!$F$11:$F$100,0)) -> 0 | H99: =F99-G99 -> 153167
A100: 200 ml | B100: Samsol International Private Limited | C100: PET BOTTLE LARGE 200ML WHITE | D100: 8007 | E100: 334 & 338 | F100: =INDEX(Tubex_Dashboard!$G$11:$G$61,MATCH(MRP!D100,Tubex_Dashboard!$F$11:$F$61,0)) -> 10000 | G100: =INDEX(Tubex_Dashboard!$H$11:$H$100,MATCH(MRP!D100,Tubex_Dashboard!$F$11:$F$100,0)) -> 0 | H100: =F100-G100 -> 10000
A101: 200 ml | B101: Samsol International Private Limited | C101: BT-200ML MUSTARD OIL (TRANSPARENT) | D101: 8014 | E101: 339 | F101: =INDEX(Tubex_Dashboard!$G$11:$G$61,MATCH(MRP!D101,Tubex_Dashboard!$F$11:$F$61,0)) -> 10000 | G101: =INDEX(Tubex_Dashboard!$H$11:$H$100,MATCH(MRP!D101,Tubex_Dashboard!$F$11:$F$100,0)) -> 0 | H101: =F101-G101 -> 10000
A102: 200 ml | B102: Samsol International Private Limited | C102: PET BOTTLE LARGE (200 ML) YELLOW | D102: 8006 | F102: =INDEX(Tubex_Dashboard!$G$11:$G$61,MATCH(MRP!D102,Tubex_Dashboard!$F$11:$F$61,0)) -> 42400 | G102: =INDEX(Tubex_Dashboard!$H$11:$H$100,MATCH(MRP!D102,Tubex_Dashboard!$F$11:$F$100,0)) -> 0 | H102: =F102-G102 -> 42400
A103: 130 ml | B103: Mablay Beauty PVT LTD. | C103: PET BOTTLE 130ML WHITE | D103: 8015 | E103: 344 | F103: =INDEX(Tubex_Dashboard!$G$11:$G$61,MATCH(MRP!D103,Tubex_Dashboard!$F$11:$F$61,0)) -> 15000 | G103: =INDEX(Tubex_Dashboard!$H$11:$H$100,MATCH(MRP!D103,Tubex_Dashboard!$F$11:$F$100,0)) -> 0 | H103: =F103-G103 -> 15000
E104: TOTAL: | F104: =SUM(F98:F103) -> 250407 | G104: =SUM(G98:G103) -> 0 | H104: =SUM(H98:H103) -> 250407
A105: JULY PET MATERIAL REQUIREMENT PLAN
A106: Item ID | B106: Category | C106: Item Name | D106: UOM | E106: Required Qty | F106: Current Stock (Store + WIP) | G106: Surplus / (Deficit) | H106: Product Name(s) | I106: Status
A107: 2680 | B107: PET RESIN | C107: PET RESIN A-84 | D107: kg | E107: =SUMPRODUCT((TableBOM[Item ID]=A107)*TableBOM[Per 1000 Units]*(1+TableBOM[Scrap %])*SUMIF($D$98:$D$103,TableBOM[Product ID],$H$98:$H$103)/1000) -> 5969.5787 | F107: =IFERROR(INDEX(TableInventory[Store Balance],MATCH(A107,TableInventory[Item ID],0)),0)+IFERROR(INDEX(TableInventory[Work In Process],MATCH(A107,TableInventory[Item ID],0)),0) -> 2000 | G107: =F107-E107 -> -3969.5787 | H107: =IF(LEN(IF((COUNTIFS(TableBOM[Product ID],$D$98,TableBOM[Item ID],$A107)>0)*($H$98>0),$C$98&", ","") & IF((COUNTIFS(TableBOM[Product ID],$D$99,TableBOM[Item ID],$A107)>0)*($H$99>0),$C$99&", ","") & IF((COUNTIFS(TableBOM[Product ID],$D$100,TableBOM[Item ID],$A107)>0)*($H$100>0),$C$100&", ","") & IF((COUNTIFS(TableBOM[Product ID],$D$101,TableBOM[Item ID],$A107)>0)*($H$101>0),$C$101&", ","") & IF((COUNTIFS(TableBOM[Product ID],$D$102,TableBOM[Item ID],$A107)>0)*($H$102>0),$C$102&", ","") & IF((COUNTIFS(TableBOM[Product ID],$D$103,TableBOM[Item ID],$A107)>0)*($H$103>0),$C$103&", ",""))>1,LEFT(IF((COUNTIFS(TableBOM[Product ID],$D$98,TableBOM[Item ID],$A107)>0)*($H$98>0),$C$98&", ","") & IF((COUNTIFS(TableBOM[Product ID],$D$99,TableBOM[Item ID],$A107)>0)*($H$99>0),$C$99&", ","") & IF((COUNTIFS(TableBOM[Product ID],$D$100,TableBOM[Item ID],$A107)>0)*($H$100>0),$C$100&", ","") & IF((COUNTIFS(TableBOM[Product ID],$D$101,TableBOM[Item ID],$A107)>0)*($H$101>0),$C$101&", ","") & IF((COUNTIFS(TableBOM[Product ID],$D$102,TableBOM[Item ID],$A107)>0)*($H$102>0),$C$102&", ","") & IF((COUNTIFS(TableBOM[Product ID],$D$103,TableBOM[Item ID],$A107)>0)*($H$103>0),$C$103&", ",""),LEN(IF((COUNTIFS(TableBOM[Product ID],$D$98,TableBOM[Item ID],$A107)>0)*($H$98>0),$C$98&", ","") & IF((COUNTIFS(TableBOM[Product ID],$D$99,TableBOM[Item ID],$A107)>0)*($H$99>0),$C$99&", ","") & IF((COUNTIFS(TableBOM[Product ID],$D$100,TableBOM[Item ID],$A107)>0)*($H$100>0),$C$100&", ","") & IF((COUNTIFS(TableBOM[Product ID],$D$101,TableBOM[Item ID],$A107)>0)*($H$101>0),$C$101&", ","") & IF((COUNTIFS(TableBOM[Product ID],$D$102,TableBOM[Item ID],$A107)>0)*($H$102>0),$C$102&", ","") & IF((COUNTIFS(TableBOM[Product ID],$D$103,TableBOM[Item ID],$A107)>0)*($H$103>0),$C$103&", ",""))-2),"") -> PET BOTTLE SMALL (120ML) YELLOW, TRANSPARENT BOTTLE 150ML, PET BOTTLE LARGE 200ML WHITE, BT-200ML MUSTARD OIL (TRANSPARENT), PET BOTTLE LARGE (200 ML) YELLOW | I107: =IF(E107=0,"Not needed",IF(G107<0,"SHORTAGE",IF(G107<F107*0.1,"LOW","OK"))) -> SHORTAGE
A108: 4070 | B108: MASTER BATCH | C108: MASTER BATCH ONCOLOR YELLOW NE12340208-ZN | D108: kg | E108: =SUMPRODUCT((TableBOM[Item ID]=A108)*TableBOM[Per 1000 Units]*(1+TableBOM[Scrap %])*SUMIF($D$98:$D$103,TableBOM[Product ID],$H$98:$H$103)/1000) -> 81.4844 | F108: =IFERROR(INDEX(TableInventory[Store Balance],MATCH(A108,TableInventory[Item ID],0)),0)+IFERROR(INDEX(TableInventory[Work In Process],MATCH(A108,TableInventory[Item ID],0)),0) -> 0 | G108: =F108-E108 -> -81.4844 | H108: =IF(LEN(IF((COUNTIFS(TableBOM[Product ID],$D$98,TableBOM[Item ID],$A108)>0)*($H$98>0),$C$98&", ","") & IF((COUNTIFS(TableBOM[Product ID],$D$99,TableBOM[Item ID],$A108)>0)*($H$99>0),$C$99&", ","") & IF((COUNTIFS(TableBOM[Product ID],$D$100,TableBOM[Item ID],$A108)>0)*($H$100>0),$C$100&", ","") & IF((COUNTIFS(TableBOM[Product ID],$D$101,TableBOM[Item ID],$A108)>0)*($H$101>0),$C$101&", ","") & IF((COUNTIFS(TableBOM[Product ID],$D$102,TableBOM[Item ID],$A108)>0)*($H$102>0),$C$102&", ","") & IF((COUNTIFS(TableBOM[Product ID],$D$103,TableBOM[Item ID],$A108)>0)*($H$103>0),$C$103&", ",""))>1,LEFT(IF((COUNTIFS(TableBOM[Product ID],$D$98,TableBOM[Item ID],$A108)>0)*($H$98>0),$C$98&", ","") & IF((COUNTIFS(TableBOM[Product ID],$D$99,TableBOM[Item ID],$A108)>0)*($H$99>0),$C$99&", ","") & IF((COUNTIFS(TableBOM[Product ID],$D$100,TableBOM[Item ID],$A108)>0)*($H$100>0),$C$100&", ","") & IF((COUNTIFS(TableBOM[Product ID],$D$101,TableBOM[Item ID],$A108)>0)*($H$101>0),$C$101&", ","") & IF((COUNTIFS(TableBOM[Product ID],$D$102,TableBOM[Item ID],$A108)>0)*($H$102>0),$C$102&", ","") & IF((COUNTIFS(TableBOM[Product ID],$D$103,TableBOM[Item ID],$A108)>0)*($H$103>0),$C$103&", ",""),LEN(IF((COUNTIFS(TableBOM[Product ID],$D$98,TableBOM[Item ID],$A108)>0)*($H$98>0),$C$98&", ","") & IF((COUNTIFS(TableBOM[Product ID],$D$99,TableBOM[Item ID],$A108)>0)*($H$99>0),$C$99&", ","") & IF((COUNTIFS(TableBOM[Product ID],$D$100,TableBOM[Item ID],$A108)>0)*($H$100>0),$C$100&", ","") & IF((COUNTIFS(TableBOM[Product ID],$D$101,TableBOM[Item ID],$A108)>0)*($H$101>0),$C$101&", ","") & IF((COUNTIFS(TableBOM[Product ID],$D$102,TableBOM[Item ID],$A108)>0)*($H$102>0),$C$102&", ","") & IF((COUNTIFS(TableBOM[Product ID],$D$103,TableBOM[Item ID],$A108)>0)*($H$103>0),$C$103&", ",""))-2),"") -> PET BOTTLE SMALL (120ML) YELLOW, PET BOTTLE LARGE (200 ML) YELLOW | I108: =IF(E108=0,"Not needed",IF(G108<0,"SHORTAGE",IF(G108<F108*0.1,"LOW","OK"))) -> SHORTAGE
A109: 5816 | B109: MASTER BATCH | C109: MASTER BATCH WHITE PRC-MC ET02340000 | D109: kg | E109: =SUMPRODUCT((TableBOM[Item ID]=A109)*TableBOM[Per 1000 Units]*(1+TableBOM[Scrap %])*SUMIF($D$98:$D$103,TableBOM[Product ID],$H$98:$H$103)/1000) -> 14.375 | F109: =IFERROR(INDEX(TableInventory[Store Balance],MATCH(A109,TableInventory[Item ID],0)),0)+IFERROR(INDEX(TableInventory[Work In Process],MATCH(A109,TableInventory[Item ID],0)),0) -> 0 | G109: =F109-E109 -> -14.375 | H109: =IF(LEN(IF((COUNTIFS(TableBOM[Product ID],$D$98,TableBOM[Item ID],$A109)>0)*($H$98>0),$C$98&", ","") & IF((COUNTIFS(TableBOM[Product ID],$D$99,TableBOM[Item ID],$A109)>0)*($H$99>0),$C$99&", ","") & IF((COUNTIFS(TableBOM[Product ID],$D$100,TableBOM[Item ID],$A109)>0)*($H$100>0),$C$100&", ","") & IF((COUNTIFS(TableBOM[Product ID],$D$101,TableBOM[Item ID],$A109)>0)*($H$101>0),$C$101&", ","") & IF((COUNTIFS(TableBOM[Product ID],$D$102,TableBOM[Item ID],$A109)>0)*($H$102>0),$C$102&", ","") & IF((COUNTIFS(TableBOM[Product ID],$D$103,TableBOM[Item ID],$A109)>0)*($H$103>0),$C$103&", ",""))>1,LEFT(IF((COUNTIFS(TableBOM[Product ID],$D$98,TableBOM[Item ID],$A109)>0)*($H$98>0),$C$98&", ","") & IF((COUNTIFS(TableBOM[Product ID],$D$99,TableBOM[Item ID],$A109)>0)*($H$99>0),$C$99&", ","") & IF((COUNTIFS(TableBOM[Product ID],$D$100,TableBOM[Item ID],$A109)>0)*($H$100>0),$C$100&", ","") & IF((COUNTIFS(TableBOM[Product ID],$D$101,TableBOM[Item ID],$A109)>0)*($H$101>0),$C$101&", ","") & IF((COUNTIFS(TableBOM[Product ID],$D$102,TableBOM[Item ID],$A109)>0)*($H$102>0),$C$102&", ","") & IF((COUNTIFS(TableBOM[Product ID],$D$103,TableBOM[Item ID],$A109)>0)*($H$103>0),$C$103&", ",""),LEN(IF((COUNTIFS(TableBOM[Product ID],$D$98,TableBOM[Item ID],$A109)>0)*($H$98>0),$C$98&", ","") & IF((COUNTIFS(TableBOM[Product ID],$D$99,TableBOM[Item ID],$A109)>0)*($H$99>0),$C$99&", ","") & IF((COUNTIFS(TableBOM[Product ID],$D$100,TableBOM[Item ID],$A109)>0)*($H$100>0),$C$100&", ","") & IF((COUNTIFS(TableBOM[Product ID],$D$101,TableBOM[Item ID],$A109)>0)*($H$101>0),$C$101&", ","") & IF((COUNTIFS(TableBOM[Product ID],$D$102,TableBOM[Item ID],$A109)>0)*($H$102>0),$C$102&", ","") & IF((COUNTIFS(TableBOM[Product ID],$D$103,TableBOM[Item ID],$A109)>0)*($H$103>0),$C$103&", ",""))-2),"") -> PET BOTTLE LARGE 200ML WHITE | I109: =IF(E109=0,"Not needed",IF(G109<0,"SHORTAGE",IF(G109<F109*0.1,"LOW","OK"))) -> SHORTAGE
A110: 5977 | B110: Carton | C110: MASTER CARTON 38"X24"X15.5" | D110: PCS | E110: =SUMPRODUCT((TableBOM[Item ID]=A110)*TableBOM[Per 1000 Units]*(1+TableBOM[Scrap %])*SUMIF($D$98:$D$103,TableBOM[Product ID],$H$98:$H$103)/1000) -> 191.46641 | F110: =IFERROR(INDEX(TableInventory[Store Balance],MATCH(A110,TableInventory[Item ID],0)),0)+IFERROR(INDEX(TableInventory[Work In Process],MATCH(A110,TableInventory[Item ID],0)),0) -> 61 | G110: =F110-E110 -> -130.46641 | H110: =IF(LEN(IF((COUNTIFS(TableBOM[Product ID],$D$98,TableBOM[Item ID],$A110)>0)*($H$98>0),$C$98&", ","") & IF((COUNTIFS(TableBOM[Product ID],$D$99,TableBOM[Item ID],$A110)>0)*($H$99>0),$C$99&", ","") & IF((COUNTIFS(TableBOM[Product ID],$D$100,TableBOM[Item ID],$A110)>0)*($H$100>0),$C$100&", ","") & IF((COUNTIFS(TableBOM[Product ID],$D$101,TableBOM[Item ID],$A110)>0)*($H$101>0),$C$101&", ","") & IF((COUNTIFS(TableBOM[Product ID],$D$102,TableBOM[Item ID],$A110)>0)*($H$102>0),$C$102&", ","") & IF((COUNTIFS(TableBOM[Product ID],$D$103,TableBOM[Item ID],$A110)>0)*($H$103>0),$C$103&", ",""))>1,LEFT(IF((COUNTIFS(TableBOM[Product ID],$D$98,TableBOM[Item ID],$A110)>0)*($H$98>0),$C$98&", ","") & IF((COUNTIFS(TableBOM[Product ID],$D$99,TableBOM[Item ID],$A110)>0)*($H$99>0),$C$99&", ","") & IF((COUNTIFS(TableBOM[Product ID],$D$100,TableBOM[Item ID],$A110)>0)*($H$100>0),$C$100&", ","") & IF((COUNTIFS(TableBOM[Product ID],$D$101,TableBOM[Item ID],$A110)>0)*($H$101>0),$C$101&", ","") & IF((COUNTIFS(TableBOM[Product ID],$D$102,TableBOM[Item ID],$A110)>0)*($H$102>0),$C$102&", ","") & IF((COUNTIFS(TableBOM[Product ID],$D$103,TableBOM[Item ID],$A110)>0)*($H$103>0),$C$103&", ",""),LEN(IF((COUNTIFS(TableBOM[Product ID],$D$98,TableBOM[Item ID],$A110)>0)*($H$98>0),$C$98&", ","") & IF((COUNTIFS(TableBOM[Product ID],$D$99,TableBOM[Item ID],$A110)>0)*($H$99>0),$C$99&", ","") & IF((COUNTIFS(TableBOM[Product ID],$D$100,TableBOM[Item ID],$A110)>0)*($H$100>0),$C$100&", ","") & IF((COUNTIFS(TableBOM[Product ID],$D$101,TableBOM[Item ID],$A110)>0)*($H$101>0),$C$101&", ","") & IF((COUNTIFS(TableBOM[Product ID],$D$102,TableBOM[Item ID],$A110)>0)*($H$102>0),$C$102&", ","") & IF((COUNTIFS(TableBOM[Product ID],$D$103,TableBOM[Item ID],$A110)>0)*($H$103>0),$C$103&", ",""))-2),"") -> TRANSPARENT BOTTLE 150ML | I110: =IF(E110=0,"Not needed",IF(G110<0,"SHORTAGE",IF(G110<F110*0.1,"LOW","OK"))) -> SHORTAGE
A111: 2267 | B111: Poly Bag | C111: POLY BAG 20X30 (LDPE) | D111: PCS | E111: =SUMPRODUCT((TableBOM[Item ID]=A111)*TableBOM[Per 1000 Units]*(1+TableBOM[Scrap %])*SUMIF($D$98:$D$103,TableBOM[Product ID],$H$98:$H$103)/1000) -> 1721.857 | F111: =IFERROR(INDEX(TableInventory[Store Balance],MATCH(A111,TableInventory[Item ID],0)),0)+IFERROR(INDEX(TableInventory[Work In Process],MATCH(A111,TableInventory[Item ID],0)),0) -> 75 | G111: =F111-E111 -> -1646.857 | H111: =IF(LEN(IF((COUNTIFS(TableBOM[Product ID],$D$98,TableBOM[Item ID],$A111)>0)*($H$98>0),$C$98&", ","") & IF((COUNTIFS(TableBOM[Product ID],$D$99,TableBOM[Item ID],$A111)>0)*($H$99>0),$C$99&", ","") & IF((COUNTIFS(TableBOM[Product ID],$D$100,TableBOM[Item ID],$A111)>0)*($H$100>0),$C$100&", ","") & IF((COUNTIFS(TableBOM[Product ID],$D$101,TableBOM[Item ID],$A111)>0)*($H$101>0),$C$101&", ","") & IF((COUNTIFS(TableBOM[Product ID],$D$102,TableBOM[Item ID],$A111)>0)*($H$102>0),$C$102&", ","") & IF((COUNTIFS(TableBOM[Product ID],$D$103,TableBOM[Item ID],$A111)>0)*($H$103>0),$C$103&", ",""))>1,LEFT(IF((COUNTIFS(TableBOM[Product ID],$D$98,TableBOM[Item ID],$A111)>0)*($H$98>0),$C$98&", ","") & IF((COUNTIFS(TableBOM[Product ID],$D$99,TableBOM[Item ID],$A111)>0)*($H$99>0),$C$99&", ","") & IF((COUNTIFS(TableBOM[Product ID],$D$100,TableBOM[Item ID],$A111)>0)*($H$100>0),$C$100&", ","") & IF((COUNTIFS(TableBOM[Product ID],$D$101,TableBOM[Item ID],$A111)>0)*($H$101>0),$C$101&", ","") & IF((COUNTIFS(TableBOM[Product ID],$D$102,TableBOM[Item ID],$A111)>0)*($H$102>0),$C$102&", ","") & IF((COUNTIFS(TableBOM[Product ID],$D$103,TableBOM[Item ID],$A111)>0)*($H$103>0),$C$103&", ",""),LEN(IF((COUNTIFS(TableBOM[Product ID],$D$98,TableBOM[Item ID],$A111)>0)*($H$98>0),$C$98&", ","") & IF((COUNTIFS(TableBOM[Product ID],$D$99,TableBOM[Item ID],$A111)>0)*($H$99>0),$C$99&", ","") & IF((COUNTIFS(TableBOM[Product ID],$D$100,TableBOM[Item ID],$A111)>0)*($H$100>0),$C$100&", ","") & IF((COUNTIFS(TableBOM[Product ID],$D$101,TableBOM[Item ID],$A111)>0)*($H$101>0),$C$101&", ","") & IF((COUNTIFS(TableBOM[Product ID],$D$102,TableBOM[Item ID],$A111)>0)*($H$102>0),$C$102&", ","") & IF((COUNTIFS(TableBOM[Product ID],$D$103,TableBOM[Item ID],$A111)>0)*($H$103>0),$C$103&", ",""))-2),"") -> PET BOTTLE SMALL (120ML) YELLOW, TRANSPARENT BOTTLE 150ML | I111: =IF(E111=0,"Not needed",IF(G111<0,"SHORTAGE",IF(G111<F111*0.1,"LOW","OK"))) -> SHORTAGE
A112: 3006 | B112: POLY BAG | C112: POLY BAG 24X36 (LDPE) | D112: PCS | E112: =SUMPRODUCT((TableBOM[Item ID]=A112)*TableBOM[Per 1000 Units]*(1+TableBOM[Scrap %])*SUMIF($D$98:$D$103,TableBOM[Product ID],$H$98:$H$103)/1000) -> 597.97608 | F112: =IFERROR(INDEX(TableInventory[Store Balance],MATCH(A112,TableInventory[Item ID],0)),0)+IFERROR(INDEX(TableInventory[Work In Process],MATCH(A112,TableInventory[Item ID],0)),0) -> 201 | G112: =F112-E112 -> -396.97608 | H112: =IF(LEN(IF((COUNTIFS(TableBOM[Product ID],$D$98,TableBOM[Item ID],$A112)>0)*($H$98>0),$C$98&", ","") & IF((COUNTIFS(TableBOM[Product ID],$D$99,TableBOM[Item ID],$A112)>0)*($H$99>0),$C$99&", ","") & IF((COUNTIFS(TableBOM[Product ID],$D$100,TableBOM[Item ID],$A112)>0)*($H$100>0),$C$100&", ","") & IF((COUNTIFS(TableBOM[Product ID],$D$101,TableBOM[Item ID],$A112)>0)*($H$101>0),$C$101&", ","") & IF((COUNTIFS(TableBOM[Product ID],$D$102,TableBOM[Item ID],$A112)>0)*($H$102>0),$C$102&", ","") & IF((COUNTIFS(TableBOM[Product ID],$D$103,TableBOM[Item ID],$A112)>0)*($H$103>0),$C$103&", ",""))>1,LEFT(IF((COUNTIFS(TableBOM[Product ID],$D$98,TableBOM[Item ID],$A112)>0)*($H$98>0),$C$98&", ","") & IF((COUNTIFS(TableBOM[Product ID],$D$99,TableBOM[Item ID],$A112)>0)*($H$99>0),$C$99&", ","") & IF((COUNTIFS(TableBOM[Product ID],$D$100,TableBOM[Item ID],$A112)>0)*($H$100>0),$C$100&", ","") & IF((COUNTIFS(TableBOM[Product ID],$D$101,TableBOM[Item ID],$A112)>0)*($H$101>0),$C$101&", ","") & IF((COUNTIFS(TableBOM[Product ID],$D$102,TableBOM[Item ID],$A112)>0)*($H$102>0),$C$102&", ","") & IF((COUNTIFS(TableBOM[Product ID],$D$103,TableBOM[Item ID],$A112)>0)*($H$103>0),$C$103&", ",""),LEN(IF((COUNTIFS(TableBOM[Product ID],$D$98,TableBOM[Item ID],$A112)>0)*($H$98>0),$C$98&", ","") & IF((COUNTIFS(TableBOM[Product ID],$D$99,TableBOM[Item ID],$A112)>0)*($H$99>0),$C$99&", ","") & IF((COUNTIFS(TableBOM[Product ID],$D$100,TableBOM[Item ID],$A112)>0)*($H$100>0),$C$100&", ","") & IF((COUNTIFS(TableBOM[Product ID],$D$101,TableBOM[Item ID],$A112)>0)*($H$101>0),$C$101&", ","") & IF((COUNTIFS(TableBOM[Product ID],$D$102,TableBOM[Item ID],$A112)>0)*($H$102>0),$C$102&", ","") & IF((COUNTIFS(TableBOM[Product ID],$D$103,TableBOM[Item ID],$A112)>0)*($H$103>0),$C$103&", ",""))-2),"") -> PET BOTTLE LARGE 200ML WHITE, BT-200ML MUSTARD OIL (TRANSPARENT), PET BOTTLE LARGE (200 ML) YELLOW | I112: =IF(E112=0,"Not needed",IF(G112<0,"SHORTAGE",IF(G112<F112*0.1,"LOW","OK"))) -> SHORTAGE
A113: 3635 | B113: TAPE | C113: PACKING TAPE 2" OF 60 YARDS | D113: PCS | E113: =SUMPRODUCT((TableBOM[Item ID]=A113)*TableBOM[Per 1000 Units]*(1+TableBOM[Scrap %])*SUMIF($D$98:$D$103,TableBOM[Product ID],$H$98:$H$103)/1000) -> 4.7558353 | F113: =IFERROR(INDEX(TableInventory[Store Balance],MATCH(A113,TableInventory[Item ID],0)),0)+IFERROR(INDEX(TableInventory[Work In Process],MATCH(A113,TableInventory[Item ID],0)),0) -> 513 | G113: =F113-E113 -> 508.24416 | H113: =IF(LEN(IF((COUNTIFS(TableBOM[Product ID],$D$98,TableBOM[Item ID],$A113)>0)*($H$98>0),$C$98&", ","") & IF((COUNTIFS(TableBOM[Product ID],$D$99,TableBOM[Item ID],$A113)>0)*($H$99>0),$C$99&", ","") & IF((COUNTIFS(TableBOM[Product ID],$D$100,TableBOM[Item ID],$A113)>0)*($H$100>0),$C$100&", ","") & IF((COUNTIFS(TableBOM[Product ID],$D$101,TableBOM[Item ID],$A113)>0)*($H$101>0),$C$101&", ","") & IF((COUNTIFS(TableBOM[Product ID],$D$102,TableBOM[Item ID],$A113)>0)*($H$102>0),$C$102&", ","") & IF((COUNTIFS(TableBOM[Product ID],$D$103,TableBOM[Item ID],$A113)>0)*($H$103>0),$C$103&", ",""))>1,LEFT(IF((COUNTIFS(TableBOM[Product ID],$D$98,TableBOM[Item ID],$A113)>0)*($H$98>0),$C$98&", ","") & IF((COUNTIFS(TableBOM[Product ID],$D$99,TableBOM[Item ID],$A113)>0)*($H$99>0),$C$99&", ","") & IF((COUNTIFS(TableBOM[Product ID],$D$100,TableBOM[Item ID],$A113)>0)*($H$100>0),$C$100&", ","") & IF((COUNTIFS(TableBOM[Product ID],$D$101,TableBOM[Item ID],$A113)>0)*($H$101>0),$C$101&", ","") & IF((COUNTIFS(TableBOM[Product ID],$D$102,TableBOM[Item ID],$A113)>0)*($H$102>0),$C$102&", ","") & IF((COUNTIFS(TableBOM[Product ID],$D$103,TableBOM[Item ID],$A113)>0)*($H$103>0),$C$103&", ",""),LEN(IF((COUNTIFS(TableBOM[Product ID],$D$98,TableBOM[Item ID],$A113)>0)*($H$98>0),$C$98&", ","") & IF((COUNTIFS(TableBOM[Product ID],$D$99,TableBOM[Item ID],$A113)>0)*($H$99>0),$C$99&", ","") & IF((COUNTIFS(TableBOM[Product ID],$D$100,TableBOM[Item ID],$A113)>0)*($H$100>0),$C$100&", ","") & IF((COUNTIFS(TableBOM[Product ID],$D$101,TableBOM[Item ID],$A113)>0)*($H$101>0),$C$101&", ","") & IF((COUNTIFS(TableBOM[Product ID],$D$102,TableBOM[Item ID],$A113)>0)*($H$102>0),$C$102&", ","") & IF((COUNTIFS(TableBOM[Product ID],$D$103,TableBOM[Item ID],$A113)>0)*($H$103>0),$C$103&", ",""))-2),"") -> TRANSPARENT BOTTLE 150ML | I113: =IF(E113=0,"Not needed",IF(G113<0,"SHORTAGE",IF(G113<F113*0.1,"LOW","OK"))) -> OK
A114: 3043 | B114: PACKING | C114: PLASTIC DOORI | D114: ROLL | E114: =SUMPRODUCT((TableBOM[Item ID]=A114)*TableBOM[Per 1000 Units]*(1+TableBOM[Scrap %])*SUMIF($D$98:$D$103,TableBOM[Product ID],$H$98:$H$103)/1000) -> 1.3535903 | F114: =IFERROR(INDEX(TableInventory[Store Balance],MATCH(A114,TableInventory[Item ID],0)),0)+IFERROR(INDEX(TableInventory[Work In Process],MATCH(A114,TableInventory[Item ID],0)),0) -> 0 | G114: =F114-E114 -> -1.3535903 | H114: =IF(LEN(IF((COUNTIFS(TableBOM[Product ID],$D$98,TableBOM[Item ID],$A114)>0)*($H$98>0),$C$98&", ","") & IF((COUNTIFS(TableBOM[Product ID],$D$99,TableBOM[Item ID],$A114)>0)*($H$99>0),$C$99&", ","") & IF((COUNTIFS(TableBOM[Product ID],$D$100,TableBOM[Item ID],$A114)>0)*($H$100>0),$C$100&", ","") & IF((COUNTIFS(TableBOM[Product ID],$D$101,TableBOM[Item ID],$A114)>0)*($H$101>0),$C$101&", ","") & IF((COUNTIFS(TableBOM[Product ID],$D$102,TableBOM[Item ID],$A114)>0)*($H$102>0),$C$102&", ","") & IF((COUNTIFS(TableBOM[Product ID],$D$103,TableBOM[Item ID],$A114)>0)*($H$103>0),$C$103&", ",""))>1,LEFT(IF((COUNTIFS(TableBOM[Product ID],$D$98,TableBOM[Item ID],$A114)>0)*($H$98>0),$C$98&", ","") & IF((COUNTIFS(TableBOM[Product ID],$D$99,TableBOM[Item ID],$A114)>0)*($H$99>0),$C$99&", ","") & IF((COUNTIFS(TableBOM[Product ID],$D$100,TableBOM[Item ID],$A114)>0)*($H$100>0),$C$100&", ","") & IF((COUNTIFS(TableBOM[Product ID],$D$101,TableBOM[Item ID],$A114)>0)*($H$101>0),$C$101&", ","") & IF((COUNTIFS(TableBOM[Product ID],$D$102,TableBOM[Item ID],$A114)>0)*($H$102>0),$C$102&", ","") & IF((COUNTIFS(TableBOM[Product ID],$D$103,TableBOM[Item ID],$A114)>0)*($H$103>0),$C$103&", ",""),LEN(IF((COUNTIFS(TableBOM[Product ID],$D$98,TableBOM[Item ID],$A114)>0)*($H$98>0),$C$98&", ","") & IF((COUNTIFS(TableBOM[Product ID],$D$99,TableBOM[Item ID],$A114)>0)*($H$99>0),$C$99&", ","") & IF((COUNTIFS(TableBOM[Product ID],$D$100,TableBOM[Item ID],$A114)>0)*($H$100>0),$C$100&", ","") & IF((COUNTIFS(TableBOM[Product ID],$D$101,TableBOM[Item ID],$A114)>0)*($H$101>0),$C$101&", ","") & IF((COUNTIFS(TableBOM[Product ID],$D$102,TableBOM[Item ID],$A114)>0)*($H$102>0),$C$102&", ","") & IF((COUNTIFS(TableBOM[Product ID],$D$103,TableBOM[Item ID],$A114)>0)*($H$103>0),$C$103&", ",""))-2),"") -> PET BOTTLE SMALL (120ML) YELLOW, TRANSPARENT BOTTLE 150ML, PET BOTTLE LARGE 200ML WHITE, BT-200ML MUSTARD OIL (TRANSPARENT), PET BOTTLE LARGE (200 ML) YELLOW | I114: =IF(E114=0,"Not needed",IF(G114<0,"SHORTAGE",IF(G114<F114*0.1,"LOW","OK"))) -> SHORTAGE
A116: INK — Avg Monthly Usage | Data: May 2025 – Apr 2026 | 271.9 kg issued / 8,617,293 tubes = 31.6 g / 1,000 tubes | E116: =SUMPRODUCT((TableBOM[Item ID]=A116)*TableBOM[Per 1000 Units]*(1+TableBOM[Scrap %])*SUMIF($D$98:$D$103,TableBOM[Product ID],$H$98:$H$103)/1000) -> 0 | H116: =IF(LEN(IF((COUNTIFS(TableBOM[Product ID],$D$98,TableBOM[Item ID],$A116)>0)*($H$98>0),$C$98&", ","") & IF((COUNTIFS(TableBOM[Product ID],$D$99,TableBOM[Item ID],$A116)>0)*($H$99>0),$C$99&", ","") & IF((COUNTIFS(TableBOM[Product ID],$D$100,TableBOM[Item ID],$A116)>0)*($H$100>0),$C$100&", ","") & IF((COUNTIFS(TableBOM[Product ID],$D$101,TableBOM[Item ID],$A116)>0)*($H$101>0),$C$101&", ","") & IF((COUNTIFS(TableBOM[Product ID],$D$102,TableBOM[Item ID],$A116)>0)*($H$102>0),$C$102&", ","") & IF((COUNTIFS(TableBOM[Product ID],$D$103,TableBOM[Item ID],$A116)>0)*($H$103>0),$C$103&", ",""))>1,LEFT(IF((COUNTIFS(TableBOM[Product ID],$D$98,TableBOM[Item ID],$A116)>0)*($H$98>0),$C$98&", ","") & IF((COUNTIFS(TableBOM[Product ID],$D$99,TableBOM[Item ID],$A116)>0)*($H$99>0),$C$99&", ","") & IF((COUNTIFS(TableBOM[Product ID],$D$100,TableBOM[Item ID],$A116)>0)*($H$100>0),$C$100&", ","") & IF((COUNTIFS(TableBOM[Product ID],$D$101,TableBOM[Item ID],$A116)>0)*($H$101>0),$C$101&", ","") & IF((COUNTIFS(TableBOM[Product ID],$D$102,TableBOM[Item ID],$A116)>0)*($H$102>0),$C$102&", ","") & IF((COUNTIFS(TableBOM[Product ID],$D$103,TableBOM[Item ID],$A116)>0)*($H$103>0),$C$103&", ",""),LEN(IF((COUNTIFS(TableBOM[Product ID],$D$98,TableBOM[Item ID],$A116)>0)*($H$98>0),$C$98&", ","") & IF((COUNTIFS(TableBOM[Product ID],$D$99,TableBOM[Item ID],$A116)>0)*($H$99>0),$C$99&", ","") & IF((COUNTIFS(TableBOM[Product ID],$D$100,TableBOM[Item ID],$A116)>0)*($H$100>0),$C$100&", ","") & IF((COUNTIFS(TableBOM[Product ID],$D$101,TableBOM[Item ID],$A116)>0)*($H$101>0),$C$101&", ","") & IF((COUNTIFS(TableBOM[Product ID],$D$102,TableBOM[Item ID],$A116)>0)*($H$102>0),$C$102&", ","") & IF((COUNTIFS(TableBOM[Product ID],$D$103,TableBOM[Item ID],$A116)>0)*($H$103>0),$C$103&", ",""))-2),"")
A117: Item ID | B117: Category | C117: Item Name | D117: UOM | E117: =SUMPRODUCT((TableBOM[Item ID]=A117)*TableBOM[Per 1000 Units]*(1+TableBOM[Scrap %])*SUMIF($D$98:$D$103,TableBOM[Product ID],$H$98:$H$103)/1000) -> 0 | F117: Days of Stock Left | G117: Status | H117: =IF(LEN(IF((COUNTIFS(TableBOM[Product ID],$D$98,TableBOM[Item ID],$A117)>0)*($H$98>0),$C$98&", ","") & IF((COUNTIFS(TableBOM[Product ID],$D$99,TableBOM[Item ID],$A117)>0)*($H$99>0),$C$99&", ","") & IF((COUNTIFS(TableBOM[Product ID],$D$100,TableBOM[Item ID],$A117)>0)*($H$100>0),$C$100&", ","") & IF((COUNTIFS(TableBOM[Product ID],$D$101,TableBOM[Item ID],$A117)>0)*($H$101>0),$C$101&", ","") & IF((COUNTIFS(TableBOM[Product ID],$D$102,TableBOM[Item ID],$A117)>0)*($H$102>0),$C$102&", ","") & IF((COUNTIFS(TableBOM[Product ID],$D$103,TableBOM[Item ID],$A117)>0)*($H$103>0),$C$103&", ",""))>1,LEFT(IF((COUNTIFS(TableBOM[Product ID],$D$98,TableBOM[Item ID],$A117)>0)*($H$98>0),$C$98&", ","") & IF((COUNTIFS(TableBOM[Product ID],$D$99,TableBOM[Item ID],$A117)>0)*($H$99>0),$C$99&", ","") & IF((COUNTIFS(TableBOM[Product ID],$D$100,TableBOM[Item ID],$A117)>0)*($H$100>0),$C$100&", ","") & IF((COUNTIFS(TableBOM[Product ID],$D$101,TableBOM[Item ID],$A117)>0)*($H$101>0),$C$101&", ","") & IF((COUNTIFS(TableBOM[Product ID],$D$102,TableBOM[Item ID],$A117)>0)*($H$102>0),$C$102&", ","") & IF((COUNTIFS(TableBOM[Product ID],$D$103,TableBOM[Item ID],$A117)>0)*($H$103>0),$C$103&", ",""),LEN(IF((COUNTIFS(TableBOM[Product ID],$D$98,TableBOM[Item ID],$A117)>0)*($H$98>0),$C$98&", ","") & IF((COUNTIFS(TableBOM[Product ID],$D$99,TableBOM[Item ID],$A117)>0)*($H$99>0),$C$99&", ","") & IF((COUNTIFS(TableBOM[Product ID],$D$100,TableBOM[Item ID],$A117)>0)*($H$100>0),$C$100&", ","") & IF((COUNTIFS(TableBOM[Product ID],$D$101,TableBOM[Item ID],$A117)>0)*($H$101>0),$C$101&", ","") & IF((COUNTIFS(TableBOM[Product ID],$D$102,TableBOM[Item ID],$A117)>0)*($H$102>0),$C$102&", ","") & IF((COUNTIFS(TableBOM[Product ID],$D$103,TableBOM[Item ID],$A117)>0)*($H$103>0),$C$103&", ",""))-2),"") | I117: g / 1,000 tubes (ref)
A118: 3734 | B118: INK | C118: MAGENTA (LOCAL) 32500 | D118: kg | E118: =SUMPRODUCT((TableBOM[Item ID]=A118)*TableBOM[Per 1000 Units]*(1+TableBOM[Scrap %])*SUMIF($D$98:$D$103,TableBOM[Product ID],$H$98:$H$103)/1000) -> 0 | F118: =IF(E111=0,0,ROUND(H111/E111*30,1)) -> #VALUE! | G118: =IF(E111=0,"Not needed",IF(H111-E111<0,"SHORTAGE",IF(H111-E111<E111,"LOW","OK"))) -> #VALUE! | H118: =IF(LEN(IF((COUNTIFS(TableBOM[Product ID],$D$98,TableBOM[Item ID],$A118)>0)*($H$98>0),$C$98&", ","") & IF((COUNTIFS(TableBOM[Product ID],$D$99,TableBOM[Item ID],$A118)>0)*($H$99>0),$C$99&", ","") & IF((COUNTIFS(TableBOM[Product ID],$D$100,TableBOM[Item ID],$A118)>0)*($H$100>0),$C$100&", ","") & IF((COUNTIFS(TableBOM[Product ID],$D$101,TableBOM[Item ID],$A118)>0)*($H$101>0),$C$101&", ","") & IF((COUNTIFS(TableBOM[Product ID],$D$102,TableBOM[Item ID],$A118)>0)*($H$102>0),$C$102&", ","") & IF((COUNTIFS(TableBOM[Product ID],$D$103,TableBOM[Item ID],$A118)>0)*($H$103>0),$C$103&", ",""))>1,LEFT(IF((COUNTIFS(TableBOM[Product ID],$D$98,TableBOM[Item ID],$A118)>0)*($H$98>0),$C$98&", ","") & IF((COUNTIFS(TableBOM[Product ID],$D$99,TableBOM[Item ID],$A118)>0)*($H$99>0),$C$99&", ","") & IF((COUNTIFS(TableBOM[Product ID],$D$100,TableBOM[Item ID],$A118)>0)*($H$100>0),$C$100&", ","") & IF((COUNTIFS(TableBOM[Product ID],$D$101,TableBOM[Item ID],$A118)>0)*($H$101>0),$C$101&", ","") & IF((COUNTIFS(TableBOM[Product ID],$D$102,TableBOM[Item ID],$A118)>0)*($H$102>0),$C$102&", ","") & IF((COUNTIFS(TableBOM[Product ID],$D$103,TableBOM[Item ID],$A118)>0)*($H$103>0),$C$103&", ",""),LEN(IF((COUNTIFS(TableBOM[Product ID],$D$98,TableBOM[Item ID],$A118)>0)*($H$98>0),$C$98&", ","") & IF((COUNTIFS(TableBOM[Product ID],$D$99,TableBOM[Item ID],$A118)>0)*($H$99>0),$C$99&", ","") & IF((COUNTIFS(TableBOM[Product ID],$D$100,TableBOM[Item ID],$A118)>0)*($H$100>0),$C$100&", ","") & IF((COUNTIFS(TableBOM[Product ID],$D$101,TableBOM[Item ID],$A118)>0)*($H$101>0),$C$101&", ","") & IF((COUNTIFS(TableBOM[Product ID],$D$102,TableBOM[Item ID],$A118)>0)*($H$102>0),$C$102&", ","") & IF((COUNTIFS(TableBOM[Product ID],$D$103,TableBOM[Item ID],$A118)>0)*($H$103>0),$C$103&", ",""))-2),"") | I118: 6.38
A119: 6038 | B119: INK | C119: INK BLUE PC | D119: kg | E119: =SUMPRODUCT((TableBOM[Item ID]=A119)*TableBOM[Per 1000 Units]*(1+TableBOM[Scrap %])*SUMIF($D$98:$D$103,TableBOM[Product ID],$H$98:$H$103)/1000) -> 0 | F119: =IF(E112=0,0,ROUND(H112/E112*30,1)) -> #VALUE! | G119: =IF(E112=0,"Not needed",IF(H112-E112<0,"SHORTAGE",IF(H112-E112<E112,"LOW","OK"))) -> #VALUE! | H119: =IF(LEN(IF((COUNTIFS(TableBOM[Product ID],$D$98,TableBOM[Item ID],$A119)>0)*($H$98>0),$C$98&", ","") & IF((COUNTIFS(TableBOM[Product ID],$D$99,TableBOM[Item ID],$A119)>0)*($H$99>0),$C$99&", ","") & IF((COUNTIFS(TableBOM[Product ID],$D$100,TableBOM[Item ID],$A119)>0)*($H$100>0),$C$100&", ","") & IF((COUNTIFS(TableBOM[Product ID],$D$101,TableBOM[Item ID],$A119)>0)*($H$101>0),$C$101&", ","") & IF((COUNTIFS(TableBOM[Product ID],$D$102,TableBOM[Item ID],$A119)>0)*($H$102>0),$C$102&", ","") & IF((COUNTIFS(TableBOM[Product ID],$D$103,TableBOM[Item ID],$A119)>0)*($H$103>0),$C$103&", ",""))>1,LEFT(IF((COUNTIFS(TableBOM[Product ID],$D$98,TableBOM[Item ID],$A119)>0)*($H$98>0),$C$98&", ","") & IF((COUNTIFS(TableBOM[Product ID],$D$99,TableBOM[Item ID],$A119)>0)*($H$99>0),$C$99&", ","") & IF((COUNTIFS(TableBOM[Product ID],$D$100,TableBOM[Item ID],$A119)>0)*($H$100>0),$C$100&", ","") & IF((COUNTIFS(TableBOM[Product ID],$D$101,TableBOM[Item ID],$A119)>0)*($H$101>0),$C$101&", ","") & IF((COUNTIFS(TableBOM[Product ID],$D$102,TableBOM[Item ID],$A119)>0)*($H$102>0),$C$102&", ","") & IF((COUNTIFS(TableBOM[Product ID],$D$103,TableBOM[Item ID],$A119)>0)*($H$103>0),$C$103&", ",""),LEN(IF((COUNTIFS(TableBOM[Product ID],$D$98,TableBOM[Item ID],$A119)>0)*($H$98>0),$C$98&", ","") & IF((COUNTIFS(TableBOM[Product ID],$D$99,TableBOM[Item ID],$A119)>0)*($H$99>0),$C$99&", ","") & IF((COUNTIFS(TableBOM[Product ID],$D$100,TableBOM[Item ID],$A119)>0)*($H$100>0),$C$100&", ","") & IF((COUNTIFS(TableBOM[Product ID],$D$101,TableBOM[Item ID],$A119)>0)*($H$101>0),$C$101&", ","") & IF((COUNTIFS(TableBOM[Product ID],$D$102,TableBOM[Item ID],$A119)>0)*($H$102>0),$C$102&", ","") & IF((COUNTIFS(TableBOM[Product ID],$D$103,TableBOM[Item ID],$A119)>0)*($H$103>0),$C$103&", ",""))-2),"") | I119: 2.9
A120: 3858 | B120: INK | C120: GOLD (LOCAL) 97035 | D120: kg | E120: =SUMPRODUCT((TableBOM[Item ID]=A120)*TableBOM[Per 1000 Units]*(1+TableBOM[Scrap %])*SUMIF($D$98:$D$103,TableBOM[Product ID],$H$98:$H$103)/1000) -> 0 | F120: =IF(E113=0,0,ROUND(H113/E113*30,1)) -> #VALUE! | G120: =IF(E113=0,"Not needed",IF(H113-E113<0,"SHORTAGE",IF(H113-E113<E113,"LOW","OK"))) -> #VALUE! | H120: =IF(LEN(IF((COUNTIFS(TableBOM[Product ID],$D$98,TableBOM[Item ID],$A120)>0)*($H$98>0),$C$98&", ","") & IF((COUNTIFS(TableBOM[Product ID],$D$99,TableBOM[Item ID],$A120)>0)*($H$99>0),$C$99&", ","") & IF((COUNTIFS(TableBOM[Product ID],$D$100,TableBOM[Item ID],$A120)>0)*($H$100>0),$C$100&", ","") & IF((COUNTIFS(TableBOM[Product ID],$D$101,TableBOM[Item ID],$A120)>0)*($H$101>0),$C$101&", ","") & IF((COUNTIFS(TableBOM[Product ID],$D$102,TableBOM[Item ID],$A120)>0)*($H$102>0),$C$102&", ","") & IF((COUNTIFS(TableBOM[Product ID],$D$103,TableBOM[Item ID],$A120)>0)*($H$103>0),$C$103&", ",""))>1,LEFT(IF((COUNTIFS(TableBOM[Product ID],$D$98,TableBOM[Item ID],$A120)>0)*($H$98>0),$C$98&", ","") & IF((COUNTIFS(TableBOM[Product ID],$D$99,TableBOM[Item ID],$A120)>0)*($H$99>0),$C$99&", ","") & IF((COUNTIFS(TableBOM[Product ID],$D$100,TableBOM[Item ID],$A120)>0)*($H$100>0),$C$100&", ","") & IF((COUNTIFS(TableBOM[Product ID],$D$101,TableBOM[Item ID],$A120)>0)*($H$101>0),$C$101&", ","") & IF((COUNTIFS(TableBOM[Product ID],$D$102,TableBOM[Item ID],$A120)>0)*($H$102>0),$C$102&", ","") & IF((COUNTIFS(TableBOM[Product ID],$D$103,TableBOM[Item ID],$A120)>0)*($H$103>0),$C$103&", ",""),LEN(IF((COUNTIFS(TableBOM[Product ID],$D$98,TableBOM[Item ID],$A120)>0)*($H$98>0),$C$98&", ","") & IF((COUNTIFS(TableBOM[Product ID],$D$99,TableBOM[Item ID],$A120)>0)*($H$99>0),$C$99&", ","") & IF((COUNTIFS(TableBOM[Product ID],$D$100,TableBOM[Item ID],$A120)>0)*($H$100>0),$C$100&", ","") & IF((COUNTIFS(TableBOM[Product ID],$D$101,TableBOM[Item ID],$A120)>0)*($H$101>0),$C$101&", ","") & IF((COUNTIFS(TableBOM[Product ID],$D$102,TableBOM[Item ID],$A120)>0)*($H$102>0),$C$102&", ","") & IF((COUNTIFS(TableBOM[Product ID],$D$103,TableBOM[Item ID],$A120)>0)*($H$103>0),$C$103&", ",""))-2),"") | I120: 2.8
A121: 3754 | B121: INK | C121: RED BRONZE (LOCAL) 32519 | D121: kg | E121: =SUMPRODUCT((TableBOM[Item ID]=A121)*TableBOM[Per 1000 Units]*(1+TableBOM[Scrap %])*SUMIF($D$98:$D$103,TableBOM[Product ID],$H$98:$H$103)/1000) -> 0 | F121: =IF(E114=0,0,ROUND(H114/E114*30,1)) -> #VALUE! | G121: =IF(E114=0,"Not needed",IF(H114-E114<0,"SHORTAGE",IF(H114-E114<E114,"LOW","OK"))) -> #VALUE! | H121: =IF(LEN(IF((COUNTIFS(TableBOM[Product ID],$D$98,TableBOM[Item ID],$A121)>0)*($H$98>0),$C$98&", ","") & IF((COUNTIFS(TableBOM[Product ID],$D$99,TableBOM[Item ID],$A121)>0)*($H$99>0),$C$99&", ","") & IF((COUNTIFS(TableBOM[Product ID],$D$100,TableBOM[Item ID],$A121)>0)*($H$100>0),$C$100&", ","") & IF((COUNTIFS(TableBOM[Product ID],$D$101,TableBOM[Item ID],$A121)>0)*($H$101>0),$C$101&", ","") & IF((COUNTIFS(TableBOM[Product ID],$D$102,TableBOM[Item ID],$A121)>0)*($H$102>0),$C$102&", ","") & IF((COUNTIFS(TableBOM[Product ID],$D$103,TableBOM[Item ID],$A121)>0)*($H$103>0),$C$103&", ",""))>1,LEFT(IF((COUNTIFS(TableBOM[Product ID],$D$98,TableBOM[Item ID],$A121)>0)*($H$98>0),$C$98&", ","") & IF((COUNTIFS(TableBOM[Product ID],$D$99,TableBOM[Item ID],$A121)>0)*($H$99>0),$C$99&", ","") & IF((COUNTIFS(TableBOM[Product ID],$D$100,TableBOM[Item ID],$A121)>0)*($H$100>0),$C$100&", ","") & IF((COUNTIFS(TableBOM[Product ID],$D$101,TableBOM[Item ID],$A121)>0)*($H$101>0),$C$101&", ","") & IF((COUNTIFS(TableBOM[Product ID],$D$102,TableBOM[Item ID],$A121)>0)*($H$102>0),$C$102&", ","") & IF((COUNTIFS(TableBOM[Product ID],$D$103,TableBOM[Item ID],$A121)>0)*($H$103>0),$C$103&", ",""),LEN(IF((COUNTIFS(TableBOM[Product ID],$D$98,TableBOM[Item ID],$A121)>0)*($H$98>0),$C$98&", ","") & IF((COUNTIFS(TableBOM[Product ID],$D$99,TableBOM[Item ID],$A121)>0)*($H$99>0),$C$99&", ","") & IF((COUNTIFS(TableBOM[Product ID],$D$100,TableBOM[Item ID],$A121)>0)*($H$100>0),$C$100&", ","") & IF((COUNTIFS(TableBOM[Product ID],$D$101,TableBOM[Item ID],$A121)>0)*($H$101>0),$C$101&", ","") & IF((COUNTIFS(TableBOM[Product ID],$D$102,TableBOM[Item ID],$A121)>0)*($H$102>0),$C$102&", ","") & IF((COUNTIFS(TableBOM[Product ID],$D$103,TableBOM[Item ID],$A121)>0)*($H$103>0),$C$103&", ",""))-2),"") | I121: 2.67
A122: 3755 | B122: INK | C122: INK BLUE ES 164 | D122: kg | E122: =SUMPRODUCT((TableBOM[Item ID]=A122)*TableBOM[Per 1000 Units]*(1+TableBOM[Scrap %])*SUMIF($D$98:$D$103,TableBOM[Product ID],$H$98:$H$103)/1000) -> 0 | F122: =IF(E115=0,0,ROUND(H115/E115*30,1)) -> 0 | G122: =IF(E115=0,"Not needed",IF(H115-E115<0,"SHORTAGE",IF(H115-E115<E115,"LOW","OK"))) -> Not needed | H122: =IF(LEN(IF((COUNTIFS(TableBOM[Product ID],$D$98,TableBOM[Item ID],$A122)>0)*($H$98>0),$C$98&", ","") & IF((COUNTIFS(TableBOM[Product ID],$D$99,TableBOM[Item ID],$A122)>0)*($H$99>0),$C$99&", ","") & IF((COUNTIFS(TableBOM[Product ID],$D$100,TableBOM[Item ID],$A122)>0)*($H$100>0),$C$100&", ","") & IF((COUNTIFS(TableBOM[Product ID],$D$101,TableBOM[Item ID],$A122)>0)*($H$101>0),$C$101&", ","") & IF((COUNTIFS(TableBOM[Product ID],$D$102,TableBOM[Item ID],$A122)>0)*($H$102>0),$C$102&", ","") & IF((COUNTIFS(TableBOM[Product ID],$D$103,TableBOM[Item ID],$A122)>0)*($H$103>0),$C$103&", ",""))>1,LEFT(IF((COUNTIFS(TableBOM[Product ID],$D$98,TableBOM[Item ID],$A122)>0)*($H$98>0),$C$98&", ","") & IF((COUNTIFS(TableBOM[Product ID],$D$99,TableBOM[Item ID],$A122)>0)*($H$99>0),$C$99&", ","") & IF((COUNTIFS(TableBOM[Product ID],$D$100,TableBOM[Item ID],$A122)>0)*($H$100>0),$C$100&", ","") & IF((COUNTIFS(TableBOM[Product ID],$D$101,TableBOM[Item ID],$A122)>0)*($H$101>0),$C$101&", ","") & IF((COUNTIFS(TableBOM[Product ID],$D$102,TableBOM[Item ID],$A122)>0)*($H$102>0),$C$102&", ","") & IF((COUNTIFS(TableBOM[Product ID],$D$103,TableBOM[Item ID],$A122)>0)*($H$103>0),$C$103&", ",""),LEN(IF((COUNTIFS(TableBOM[Product ID],$D$98,TableBOM[Item ID],$A122)>0)*($H$98>0),$C$98&", ","") & IF((COUNTIFS(TableBOM[Product ID],$D$99,TableBOM[Item ID],$A122)>0)*($H$99>0),$C$99&", ","") & IF((COUNTIFS(TableBOM[Product ID],$D$100,TableBOM[Item ID],$A122)>0)*($H$100>0),$C$100&", ","") & IF((COUNTIFS(TableBOM[Product ID],$D$101,TableBOM[Item ID],$A122)>0)*($H$101>0),$C$101&", ","") & IF((COUNTIFS(TableBOM[Product ID],$D$102,TableBOM[Item ID],$A122)>0)*($H$102>0),$C$102&", ","") & IF((COUNTIFS(TableBOM[Product ID],$D$103,TableBOM[Item ID],$A122)>0)*($H$103>0),$C$103&", ",""))-2),"") | I122: 2.44
A123: 1928 | B123: INK | C123: BLACK (LOCAL) 77842 | D123: kg | E123: =SUMPRODUCT((TableBOM[Item ID]=A123)*TableBOM[Per 1000 Units]*(1+TableBOM[Scrap %])*SUMIF($D$98:$D$103,TableBOM[Product ID],$H$98:$H$103)/1000) -> 0 | F123: =IF(E116=0,0,ROUND(H116/E116*30,1)) -> 0 | G123: =IF(E116=0,"Not needed",IF(H116-E116<0,"SHORTAGE",IF(H116-E116<E116,"LOW","OK"))) -> Not needed | H123: =IF(LEN(IF((COUNTIFS(TableBOM[Product ID],$D$98,TableBOM[Item ID],$A123)>0)*($H$98>0),$C$98&", ","") & IF((COUNTIFS(TableBOM[Product ID],$D$99,TableBOM[Item ID],$A123)>0)*($H$99>0),$C$99&", ","") & IF((COUNTIFS(TableBOM[Product ID],$D$100,TableBOM[Item ID],$A123)>0)*($H$100>0),$C$100&", ","") & IF((COUNTIFS(TableBOM[Product ID],$D$101,TableBOM[Item ID],$A123)>0)*($H$101>0),$C$101&", ","") & IF((COUNTIFS(TableBOM[Product ID],$D$102,TableBOM[Item ID],$A123)>0)*($H$102>0),$C$102&", ","") & IF((COUNTIFS(TableBOM[Product ID],$D$103,TableBOM[Item ID],$A123)>0)*($H$103>0),$C$103&", ",""))>1,LEFT(IF((COUNTIFS(TableBOM[Product ID],$D$98,TableBOM[Item ID],$A123)>0)*($H$98>0),$C$98&", ","") & IF((COUNTIFS(TableBOM[Product ID],$D$99,TableBOM[Item ID],$A123)>0)*($H$99>0),$C$99&", ","") & IF((COUNTIFS(TableBOM[Product ID],$D$100,TableBOM[Item ID],$A123)>0)*($H$100>0),$C$100&", ","") & IF((COUNTIFS(TableBOM[Product ID],$D$101,TableBOM[Item ID],$A123)>0)*($H$101>0),$C$101&", ","") & IF((COUNTIFS(TableBOM[Product ID],$D$102,TableBOM[Item ID],$A123)>0)*($H$102>0),$C$102&", ","") & IF((COUNTIFS(TableBOM[Product ID],$D$103,TableBOM[Item ID],$A123)>0)*($H$103>0),$C$103&", ",""),LEN(IF((COUNTIFS(TableBOM[Product ID],$D$98,TableBOM[Item ID],$A123)>0)*($H$98>0),$C$98&", ","") & IF((COUNTIFS(TableBOM[Product ID],$D$99,TableBOM[Item ID],$A123)>0)*($H$99>0),$C$99&", ","") & IF((COUNTIFS(TableBOM[Product ID],$D$100,TableBOM[Item ID],$A123)>0)*($H$100>0),$C$100&", ","") & IF((COUNTIFS(TableBOM[Product ID],$D$101,TableBOM[Item ID],$A123)>0)*($H$101>0),$C$101&", ","") & IF((COUNTIFS(TableBOM[Product ID],$D$102,TableBOM[Item ID],$A123)>0)*($H$102>0),$C$102&", ","") & IF((COUNTIFS(TableBOM[Product ID],$D$103,TableBOM[Item ID],$A123)>0)*($H$103>0),$C$103&", ",""))-2),"") | I123: 2.32
A124: 7094 | B124: INK | C124: INK GOLD V0221267AT-401363 IMPORTED | D124: kg | E124: =SUMPRODUCT((TableBOM[Item ID]=A124)*TableBOM[Per 1000 Units]*(1+TableBOM[Scrap %])*SUMIF($D$98:$D$103,TableBOM[Product ID],$H$98:$H$103)/1000) -> 0 | F124: =IF(E117=0,0,ROUND(H117/E117*30,1)) -> 0 | G124: =IF(E117=0,"Not needed",IF(H117-E117<0,"SHORTAGE",IF(H117-E117<E117,"LOW","OK"))) -> Not needed | H124: =IF(LEN(IF((COUNTIFS(TableBOM[Product ID],$D$98,TableBOM[Item ID],$A124)>0)*($H$98>0),$C$98&", ","") & IF((COUNTIFS(TableBOM[Product ID],$D$99,TableBOM[Item ID],$A124)>0)*($H$99>0),$C$99&", ","") & IF((COUNTIFS(TableBOM[Product ID],$D$100,TableBOM[Item ID],$A124)>0)*($H$100>0),$C$100&", ","") & IF((COUNTIFS(TableBOM[Product ID],$D$101,TableBOM[Item ID],$A124)>0)*($H$101>0),$C$101&", ","") & IF((COUNTIFS(TableBOM[Product ID],$D$102,TableBOM[Item ID],$A124)>0)*($H$102>0),$C$102&", ","") & IF((COUNTIFS(TableBOM[Product ID],$D$103,TableBOM[Item ID],$A124)>0)*($H$103>0),$C$103&", ",""))>1,LEFT(IF((COUNTIFS(TableBOM[Product ID],$D$98,TableBOM[Item ID],$A124)>0)*($H$98>0),$C$98&", ","") & IF((COUNTIFS(TableBOM[Product ID],$D$99,TableBOM[Item ID],$A124)>0)*($H$99>0),$C$99&", ","") & IF((COUNTIFS(TableBOM[Product ID],$D$100,TableBOM[Item ID],$A124)>0)*($H$100>0),$C$100&", ","") & IF((COUNTIFS(TableBOM[Product ID],$D$101,TableBOM[Item ID],$A124)>0)*($H$101>0),$C$101&", ","") & IF((COUNTIFS(TableBOM[Product ID],$D$102,TableBOM[Item ID],$A124)>0)*($H$102>0),$C$102&", ","") & IF((COUNTIFS(TableBOM[Product ID],$D$103,TableBOM[Item ID],$A124)>0)*($H$103>0),$C$103&", ",""),LEN(IF((COUNTIFS(TableBOM[Product ID],$D$98,TableBOM[Item ID],$A124)>0)*($H$98>0),$C$98&", ","") & IF((COUNTIFS(TableBOM[Product ID],$D$99,TableBOM[Item ID],$A124)>0)*($H$99>0),$C$99&", ","") & IF((COUNTIFS(TableBOM[Product ID],$D$100,TableBOM[Item ID],$A124)>0)*($H$100>0),$C$100&", ","") & IF((COUNTIFS(TableBOM[Product ID],$D$101,TableBOM[Item ID],$A124)>0)*($H$101>0),$C$101&", ","") & IF((COUNTIFS(TableBOM[Product ID],$D$102,TableBOM[Item ID],$A124)>0)*($H$102>0),$C$102&", ","") & IF((COUNTIFS(TableBOM[Product ID],$D$103,TableBOM[Item ID],$A124)>0)*($H$103>0),$C$103&", ",""))-2),"") | I124: 2.32
A125: 3736 | B125: INK | C125: WHITE (LOCAL) 07094 | D125: kg | E125: =SUMPRODUCT((TableBOM[Item ID]=A125)*TableBOM[Per 1000 Units]*(1+TableBOM[Scrap %])*SUMIF($D$98:$D$103,TableBOM[Product ID],$H$98:$H$103)/1000) -> 0 | F125: =IF(E118=0,0,ROUND(H118/E118*30,1)) -> 0 | G125: =IF(E118=0,"Not needed",IF(H118-E118<0,"SHORTAGE",IF(H118-E118<E118,"LOW","OK"))) -> Not needed | H125: =IF(LEN(IF((COUNTIFS(TableBOM[Product ID],$D$98,TableBOM[Item ID],$A125)>0)*($H$98>0),$C$98&", ","") & IF((COUNTIFS(TableBOM[Product ID],$D$99,TableBOM[Item ID],$A125)>0)*($H$99>0),$C$99&", ","") & IF((COUNTIFS(TableBOM[Product ID],$D$100,TableBOM[Item ID],$A125)>0)*($H$100>0),$C$100&", ","") & IF((COUNTIFS(TableBOM[Product ID],$D$101,TableBOM[Item ID],$A125)>0)*($H$101>0),$C$101&", ","") & IF((COUNTIFS(TableBOM[Product ID],$D$102,TableBOM[Item ID],$A125)>0)*($H$102>0),$C$102&", ","") & IF((COUNTIFS(TableBOM[Product ID],$D$103,TableBOM[Item ID],$A125)>0)*($H$103>0),$C$103&", ",""))>1,LEFT(IF((COUNTIFS(TableBOM[Product ID],$D$98,TableBOM[Item ID],$A125)>0)*($H$98>0),$C$98&", ","") & IF((COUNTIFS(TableBOM[Product ID],$D$99,TableBOM[Item ID],$A125)>0)*($H$99>0),$C$99&", ","") & IF((COUNTIFS(TableBOM[Product ID],$D$100,TableBOM[Item ID],$A125)>0)*($H$100>0),$C$100&", ","") & IF((COUNTIFS(TableBOM[Product ID],$D$101,TableBOM[Item ID],$A125)>0)*($H$101>0),$C$101&", ","") & IF((COUNTIFS(TableBOM[Product ID],$D$102,TableBOM[Item ID],$A125)>0)*($H$102>0),$C$102&", ","") & IF((COUNTIFS(TableBOM[Product ID],$D$103,TableBOM[Item ID],$A125)>0)*($H$103>0),$C$103&", ",""),LEN(IF((COUNTIFS(TableBOM[Product ID],$D$98,TableBOM[Item ID],$A125)>0)*($H$98>0),$C$98&", ","") & IF((COUNTIFS(TableBOM[Product ID],$D$99,TableBOM[Item ID],$A125)>0)*($H$99>0),$C$99&", ","") & IF((COUNTIFS(TableBOM[Product ID],$D$100,TableBOM[Item ID],$A125)>0)*($H$100>0),$C$100&", ","") & IF((COUNTIFS(TableBOM[Product ID],$D$101,TableBOM[Item ID],$A125)>0)*($H$101>0),$C$101&", ","") & IF((COUNTIFS(TableBOM[Product ID],$D$102,TableBOM[Item ID],$A125)>0)*($H$102>0),$C$102&", ","") & IF((COUNTIFS(TableBOM[Product ID],$D$103,TableBOM[Item ID],$A125)>0)*($H$103>0),$C$103&", ",""))-2),"") | I125: 1.6
A126: 3955 | B126: INK | C126: GERANIUM (EVER SHINE) ES-130 | D126: kg | E126: =SUMPRODUCT((TableBOM[Item ID]=A126)*TableBOM[Per 1000 Units]*(1+TableBOM[Scrap %])*SUMIF($D$98:$D$103,TableBOM[Product ID],$H$98:$H$103)/1000) -> 0 | F126: =IF(E119=0,0,ROUND(H119/E119*30,1)) -> 0 | G126: =IF(E119=0,"Not needed",IF(H119-E119<0,"SHORTAGE",IF(H119-E119<E119,"LOW","OK"))) -> Not needed | H126: =IF(LEN(IF((COUNTIFS(TableBOM[Product ID],$D$98,TableBOM[Item ID],$A126)>0)*($H$98>0),$C$98&", ","") & IF((COUNTIFS(TableBOM[Product ID],$D$99,TableBOM[Item ID],$A126)>0)*($H$99>0),$C$99&", ","") & IF((COUNTIFS(TableBOM[Product ID],$D$100,TableBOM[Item ID],$A126)>0)*($H$100>0),$C$100&", ","") & IF((COUNTIFS(TableBOM[Product ID],$D$101,TableBOM[Item ID],$A126)>0)*($H$101>0),$C$101&", ","") & IF((COUNTIFS(TableBOM[Product ID],$D$102,TableBOM[Item ID],$A126)>0)*($H$102>0),$C$102&", ","") & IF((COUNTIFS(TableBOM[Product ID],$D$103,TableBOM[Item ID],$A126)>0)*($H$103>0),$C$103&", ",""))>1,LEFT(IF((COUNTIFS(TableBOM[Product ID],$D$98,TableBOM[Item ID],$A126)>0)*($H$98>0),$C$98&", ","") & IF((COUNTIFS(TableBOM[Product ID],$D$99,TableBOM[Item ID],$A126)>0)*($H$99>0),$C$99&", ","") & IF((COUNTIFS(TableBOM[Product ID],$D$100,TableBOM[Item ID],$A126)>0)*($H$100>0),$C$100&", ","") & IF((COUNTIFS(TableBOM[Product ID],$D$101,TableBOM[Item ID],$A126)>0)*($H$101>0),$C$101&", ","") & IF((COUNTIFS(TableBOM[Product ID],$D$102,TableBOM[Item ID],$A126)>0)*($H$102>0),$C$102&", ","") & IF((COUNTIFS(TableBOM[Product ID],$D$103,TableBOM[Item ID],$A126)>0)*($H$103>0),$C$103&", ",""),LEN(IF((COUNTIFS(TableBOM[Product ID],$D$98,TableBOM[Item ID],$A126)>0)*($H$98>0),$C$98&", ","") & IF((COUNTIFS(TableBOM[Product ID],$D$99,TableBOM[Item ID],$A126)>0)*($H$99>0),$C$99&", ","") & IF((COUNTIFS(TableBOM[Product ID],$D$100,TableBOM[Item ID],$A126)>0)*($H$100>0),$C$100&", ","") & IF((COUNTIFS(TableBOM[Product ID],$D$101,TableBOM[Item ID],$A126)>0)*($H$101>0),$C$101&", ","") & IF((COUNTIFS(TableBOM[Product ID],$D$102,TableBOM[Item ID],$A126)>0)*($H$102>0),$C$102&", ","") & IF((COUNTIFS(TableBOM[Product ID],$D$103,TableBOM[Item ID],$A126)>0)*($H$103>0),$C$103&", ",""))-2),"") | I126: 1.28
A127: 7398 | B127: INK | C127: PURPLE 48054 | D127: kg | E127: =SUMPRODUCT((TableBOM[Item ID]=A127)*TableBOM[Per 1000 Units]*(1+TableBOM[Scrap %])*SUMIF($D$98:$D$103,TableBOM[Product ID],$H$98:$H$103)/1000) -> 0 | F127: =IF(E120=0,0,ROUND(H120/E120*30,1)) -> 0 | G127: =IF(E120=0,"Not needed",IF(H120-E120<0,"SHORTAGE",IF(H120-E120<E120,"LOW","OK"))) -> Not needed | H127: =IF(LEN(IF((COUNTIFS(TableBOM[Product ID],$D$98,TableBOM[Item ID],$A127)>0)*($H$98>0),$C$98&", ","") & IF((COUNTIFS(TableBOM[Product ID],$D$99,TableBOM[Item ID],$A127)>0)*($H$99>0),$C$99&", ","") & IF((COUNTIFS(TableBOM[Product ID],$D$100,TableBOM[Item ID],$A127)>0)*($H$100>0),$C$100&", ","") & IF((COUNTIFS(TableBOM[Product ID],$D$101,TableBOM[Item ID],$A127)>0)*($H$101>0),$C$101&", ","") & IF((COUNTIFS(TableBOM[Product ID],$D$102,TableBOM[Item ID],$A127)>0)*($H$102>0),$C$102&", ","") & IF((COUNTIFS(TableBOM[Product ID],$D$103,TableBOM[Item ID],$A127)>0)*($H$103>0),$C$103&", ",""))>1,LEFT(IF((COUNTIFS(TableBOM[Product ID],$D$98,TableBOM[Item ID],$A127)>0)*($H$98>0),$C$98&", ","") & IF((COUNTIFS(TableBOM[Product ID],$D$99,TableBOM[Item ID],$A127)>0)*($H$99>0),$C$99&", ","") & IF((COUNTIFS(TableBOM[Product ID],$D$100,TableBOM[Item ID],$A127)>0)*($H$100>0),$C$100&", ","") & IF((COUNTIFS(TableBOM[Product ID],$D$101,TableBOM[Item ID],$A127)>0)*($H$101>0),$C$101&", ","") & IF((COUNTIFS(TableBOM[Product ID],$D$102,TableBOM[Item ID],$A127)>0)*($H$102>0),$C$102&", ","") & IF((COUNTIFS(TableBOM[Product ID],$D$103,TableBOM[Item ID],$A127)>0)*($H$103>0),$C$103&", ",""),LEN(IF((COUNTIFS(TableBOM[Product ID],$D$98,TableBOM[Item ID],$A127)>0)*($H$98>0),$C$98&", ","") & IF((COUNTIFS(TableBOM[Product ID],$D$99,TableBOM[Item ID],$A127)>0)*($H$99>0),$C$99&", ","") & IF((COUNTIFS(TableBOM[Product ID],$D$100,TableBOM[Item ID],$A127)>0)*($H$100>0),$C$100&", ","") & IF((COUNTIFS(TableBOM[Product ID],$D$101,TableBOM[Item ID],$A127)>0)*($H$101>0),$C$101&", ","") & IF((COUNTIFS(TableBOM[Product ID],$D$102,TableBOM[Item ID],$A127)>0)*($H$102>0),$C$102&", ","") & IF((COUNTIFS(TableBOM[Product ID],$D$103,TableBOM[Item ID],$A127)>0)*($H$103>0),$C$103&", ",""))-2),"") | I127: 1.04
A128: 3857 | B128: INK | C128: ORANGE (LOCAL) | D128: kg | E128: =SUMPRODUCT((TableBOM[Item ID]=A128)*TableBOM[Per 1000 Units]*(1+TableBOM[Scrap %])*SUMIF($D$98:$D$103,TableBOM[Product ID],$H$98:$H$103)/1000) -> 0 | F128: =IF(E121=0,0,ROUND(H121/E121*30,1)) -> 0 | G128: =IF(E121=0,"Not needed",IF(H121-E121<0,"SHORTAGE",IF(H121-E121<E121,"LOW","OK"))) -> Not needed | H128: =IF(LEN(IF((COUNTIFS(TableBOM[Product ID],$D$98,TableBOM[Item ID],$A128)>0)*($H$98>0),$C$98&", ","") & IF((COUNTIFS(TableBOM[Product ID],$D$99,TableBOM[Item ID],$A128)>0)*($H$99>0),$C$99&", ","") & IF((COUNTIFS(TableBOM[Product ID],$D$100,TableBOM[Item ID],$A128)>0)*($H$100>0),$C$100&", ","") & IF((COUNTIFS(TableBOM[Product ID],$D$101,TableBOM[Item ID],$A128)>0)*($H$101>0),$C$101&", ","") & IF((COUNTIFS(TableBOM[Product ID],$D$102,TableBOM[Item ID],$A128)>0)*($H$102>0),$C$102&", ","") & IF((COUNTIFS(TableBOM[Product ID],$D$103,TableBOM[Item ID],$A128)>0)*($H$103>0),$C$103&", ",""))>1,LEFT(IF((COUNTIFS(TableBOM[Product ID],$D$98,TableBOM[Item ID],$A128)>0)*($H$98>0),$C$98&", ","") & IF((COUNTIFS(TableBOM[Product ID],$D$99,TableBOM[Item ID],$A128)>0)*($H$99>0),$C$99&", ","") & IF((COUNTIFS(TableBOM[Product ID],$D$100,TableBOM[Item ID],$A128)>0)*($H$100>0),$C$100&", ","") & IF((COUNTIFS(TableBOM[Product ID],$D$101,TableBOM[Item ID],$A128)>0)*($H$101>0),$C$101&", ","") & IF((COUNTIFS(TableBOM[Product ID],$D$102,TableBOM[Item ID],$A128)>0)*($H$102>0),$C$102&", ","") & IF((COUNTIFS(TableBOM[Product ID],$D$103,TableBOM[Item ID],$A128)>0)*($H$103>0),$C$103&", ",""),LEN(IF((COUNTIFS(TableBOM[Product ID],$D$98,TableBOM[Item ID],$A128)>0)*($H$98>0),$C$98&", ","") & IF((COUNTIFS(TableBOM[Product ID],$D$99,TableBOM[Item ID],$A128)>0)*($H$99>0),$C$99&", ","") & IF((COUNTIFS(TableBOM[Product ID],$D$100,TableBOM[Item ID],$A128)>0)*($H$100>0),$C$100&", ","") & IF((COUNTIFS(TableBOM[Product ID],$D$101,TableBOM[Item ID],$A128)>0)*($H$101>0),$C$101&", ","") & IF((COUNTIFS(TableBOM[Product ID],$D$102,TableBOM[Item ID],$A128)>0)*($H$102>0),$C$102&", ","") & IF((COUNTIFS(TableBOM[Product ID],$D$103,TableBOM[Item ID],$A128)>0)*($H$103>0),$C$103&", ",""))-2),"") | I128: 0.81
A129: 6040 | B129: INK | C129: INK CYAN PROCESS 51650 | D129: kg | E129: =SUMPRODUCT((TableBOM[Item ID]=A129)*TableBOM[Per 1000 Units]*(1+TableBOM[Scrap %])*SUMIF($D$98:$D$103,TableBOM[Product ID],$H$98:$H$103)/1000) -> 0 | F129: =IF(E122=0,0,ROUND(H122/E122*30,1)) -> 0 | G129: =IF(E122=0,"Not needed",IF(H122-E122<0,"SHORTAGE",IF(H122-E122<E122,"LOW","OK"))) -> Not needed | H129: =IF(LEN(IF((COUNTIFS(TableBOM[Product ID],$D$98,TableBOM[Item ID],$A129)>0)*($H$98>0),$C$98&", ","") & IF((COUNTIFS(TableBOM[Product ID],$D$99,TableBOM[Item ID],$A129)>0)*($H$99>0),$C$99&", ","") & IF((COUNTIFS(TableBOM[Product ID],$D$100,TableBOM[Item ID],$A129)>0)*($H$100>0),$C$100&", ","") & IF((COUNTIFS(TableBOM[Product ID],$D$101,TableBOM[Item ID],$A129)>0)*($H$101>0),$C$101&", ","") & IF((COUNTIFS(TableBOM[Product ID],$D$102,TableBOM[Item ID],$A129)>0)*($H$102>0),$C$102&", ","") & IF((COUNTIFS(TableBOM[Product ID],$D$103,TableBOM[Item ID],$A129)>0)*($H$103>0),$C$103&", ",""))>1,LEFT(IF((COUNTIFS(TableBOM[Product ID],$D$98,TableBOM[Item ID],$A129)>0)*($H$98>0),$C$98&", ","") & IF((COUNTIFS(TableBOM[Product ID],$D$99,TableBOM[Item ID],$A129)>0)*($H$99>0),$C$99&", ","") & IF((COUNTIFS(TableBOM[Product ID],$D$100,TableBOM[Item ID],$A129)>0)*($H$100>0),$C$100&", ","") & IF((COUNTIFS(TableBOM[Product ID],$D$101,TableBOM[Item ID],$A129)>0)*($H$101>0),$C$101&", ","") & IF((COUNTIFS(TableBOM[Product ID],$D$102,TableBOM[Item ID],$A129)>0)*($H$102>0),$C$102&", ","") & IF((COUNTIFS(TableBOM[Product ID],$D$103,TableBOM[Item ID],$A129)>0)*($H$103>0),$C$103&", ",""),LEN(IF((COUNTIFS(TableBOM[Product ID],$D$98,TableBOM[Item ID],$A129)>0)*($H$98>0),$C$98&", ","") & IF((COUNTIFS(TableBOM[Product ID],$D$99,TableBOM[Item ID],$A129)>0)*($H$99>0),$C$99&", ","") & IF((COUNTIFS(TableBOM[Product ID],$D$100,TableBOM[Item ID],$A129)>0)*($H$100>0),$C$100&", ","") & IF((COUNTIFS(TableBOM[Product ID],$D$101,TableBOM[Item ID],$A129)>0)*($H$101>0),$C$101&", ","") & IF((COUNTIFS(TableBOM[Product ID],$D$102,TableBOM[Item ID],$A129)>0)*($H$102>0),$C$102&", ","") & IF((COUNTIFS(TableBOM[Product ID],$D$103,TableBOM[Item ID],$A129)>0)*($H$103>0),$C$103&", ",""))-2),"") | I129: 0.7
...

Sheet Production_Log
A1: PRODUCTION LOG — One row per machine per product per day.
A2: Date | B2: Machine | C2: Customer | D2: Product Name | E2: Dia / Volume | F2: Product ID | G2: Target Quantity | H2: Good Quantity Produced | I2: Reject/Scrap Quantity | J2: Waste% | K2: Mechanical DT | L2: Electrical DT | M2: Material Shortage DT | N2: Changeover DT | O2: Operations DT | P2: Power Shutdown DT | Q2: Gas Shutdown DT | R2: Workers Shortage DT
A3: 46204 | B3: Lacquer-03 | C3: Golden Pearl Cosmetics (PVT) LTD | D3: HELLO HAIR COLOR | E3: 30 | F3: 6206 | G3: 12000 | H3: 11735 | I3: 265 | J3: =IFERROR(I3/(H3+I3),"") -> 0.022083333 | P3: 180
A4: 46204 | B4: Latex-01 | C4: Golden Pearl Cosmetics (PVT) LTD | D4: HELLO HAIR COLOR | E4: 30 | F4: 6206 | G4: 13000 | H4: 12990 | I4: 10 | J4: =IFERROR(I4/(H4+I4),"") -> 0.00076923077 | P4: 180
A5: 46204 | B5: PF Machine | C5: Alpha Labs PVT LTD | D5: TRANSPARENT BOTTLE 150ML | E5: 150 ml | F5: 8001 | G5: 0 | H5: 0 | I5: 0 | J5: =IFERROR(I5/(H5+I5),"") | L5: 240 | P5: 240
A6: 46204 | B6: Press-04 | C6: Golden Pearl Cosmetics (PVT) LTD | D6: HELLO HAIR COLOR | E6: 30 | F6: 6206 | G6: 12700 | H6: 12600 | I6: 100 | J6: =IFERROR(I6/(H6+I6),"") -> 0.0078740157 | P6: 180
A7: 46204 | B7: Press-06 | C7: Samsol International Private Limited | D7: S 43 25MM | E7: 25 | F7: 3447 | G7: 6000 | H7: 5905 | I7: 95 | J7: =IFERROR(I7/(H7+I7),"") -> 0.015833333 | O7: 120 | P7: 180
A8: 46204 | B8: Printing-03 | C8: Golden Pearl Cosmetics (PVT) LTD | D8: HELLO HAIR COLOR | E8: 30 | F8: 6206 | G8: 6200 | H8: 5950 | I8: 250 | J8: =IFERROR(I8/(H8+I8),"") -> 0.040322581 | K8: 120 | P8: 180
A9: 46205 | B9: Lacquer-03 | C9: Golden Pearl Cosmetics (PVT) LTD | D9: HELLO HAIR COLOR | E9: 30 | F9: 6206 | G9: 22000 | H9: 21650 | I9: 350 | J9: =IFERROR(I9/(H9+I9),"") -> 0.015909091 | P9: 60
A10: 46205 | B10: Latex-01 | C10: Golden Pearl Cosmetics (PVT) LTD | D10: HELLO HAIR COLOR | E10: 30 | F10: 6206 | G10: 22134 | H10: 22124 | I10: 10 | J10: =IFERROR(I10/(H10+I10),"") -> 0.00045179362 | P10: 60
A11: 46205 | B11: PF Machine | C11: Alpha Labs PVT LTD | D11: TRANSPARENT BOTTLE 150ML | E11: 150 ml | F11: 8001 | G11: 0 | H11: 0 | I11: 0 | J11: =IFERROR(I11/(H11+I11),"") | K11: 240 | O11: 240
A12: 46205 | B12: Press-04 | C12: Golden Pearl Cosmetics (PVT) LTD | D12: HELLO HAIR COLOR | E12: 30 | F12: 6206 | G12: 20400 | H12: 20270 | I12: 130 | J12: =IFERROR(I12/(H12+I12),"") -> 0.006372549 | P12: 60
A13: 46205 | B13: Printing-03 | C13: Golden Pearl Cosmetics (PVT) LTD | D13: HELLO HAIR COLOR | E13: 30 | F13: 6206 | G13: 19490 | H13: 19040 | I13: 450 | J13: =IFERROR(I13/(H13+I13),"") -> 0.023088763 | P13: 60
A14: 46206 | B14: Lacquer-03 | C14: Golden Pearl Cosmetics (PVT) LTD | D14: HELLO HAIR COLOR | E14: 30 | F14: 6206 | G14: 16000 | H14: 15760 | I14: 240 | J14: =IFERROR(I14/(H14+I14),"") -> 0.015 | M14: 60
